Workbook

Sheet 2024
B1: Auto Raya Sdn Bhd
B2: Monthly Summary After Sales 2024
C4: HINO
C5: ACCIDENT | H5: WINDSCREEN | M5: OTHERS | P5: TOTAL
C6: INTAKE | D6: INS - PARTS | E6: INS - LABOURS | F6: CREDIT | G6: CASH | H6: INTAKE | I6: INS - PARTS | J6: INS - LABOURS | K6: CREDIT | L6: CASH | M6: INTAKE | N6: CASH | O6: CREDIT | P6: INTAKE | Q6: TOTAL | R6: Avg
B7: JANUARY | C7: 2 | D7: ='HINO 2024'!G2+'HINO 2024'!G3 -> 54765.59 | E7: ='HINO 2024'!H2+'HINO 2024'!H3 -> 21180 | F7: 6366.9 | G7: 0 | H7: 1 | I7: ='HINO 2024'!G4 -> 696.06 | J7: ='HINO 2024'!H4 -> 420 | L7: 0 | M7: 0 | N7: 0 | O7: 0 | P7: =SUM(C7+H7+M7) -> 3 | Q7: =SUM(D7+E7+F7+G7+I7+J7+K7+L7+N7+O7) -> 83428.55 | R7: =Q7/P7 -> 27809.517
B8: FEBRUARY | C8: 1 | D8: ='HINO 2024'!G5 -> 53446.25 | E8: ='HINO 2024'!H5 -> 6000 | F8: 0 | G8: 0 | H8: 1 | I8: ='HINO 2024'!G6 -> 506.06 | J8: ='HINO 2024'!H6 -> 420 | L8: 0 | M8: 0 | N8: 0 | O8: 0 | P8: =SUM(C8+H8+M8) -> 2 | Q8: =SUM(D8+E8+F8+G8+I8+J8+K8+L8+N8+O8) -> 60372.31 | R8: =Q8/P8 -> 30186.155
B9: MARCH | C9: 0 | D9: 0 | E9: 0 | F9: 0 | G9: 0 | H9: 1 | I9: ='HINO 2024'!G7 -> 688.08 | J9: ='HINO 2024'!H7 -> 420 | L9: 0 | M9: 0 | N9: 0 | O9: 0 | P9: =SUM(C9+H9+M9) -> 1 | Q9: =SUM(D9+E9+F9+G9+I9+J9+K9+L9+N9+O9) -> 1108.08 | R9: =Q9/P9 -> 1108.08
B10: APRIL | C10: 2 | D10: ='HINO 2024'!G10+'HINO 2024'!G11 -> 15447.13 | E10: ='HINO 2024'!H10+'HINO 2024'!H11 -> 5616 | F10: 5700 | G10: 0 | H10: 2 | I10: ='HINO 2024'!G8+'HINO 2024'!G9 -> 1759.11 | J10: ='HINO 2024'!H8+'HINO 2024'!H9 -> 840 | L10: 0 | M10: 0 | N10: 0 | O10: 0 | P10: =SUM(C10+H10+M10) -> 4 | Q10: =SUM(D10+E10+F10+G10+I10+J10+K10+L10+N10+O10) -> 29362.24 | R10: =Q10/P10 -> 7340.56
B11: MAY | C11: 2 | D11: ='HINO 2024'!G12+'HINO 2024'!G15 -> 34184.35 | E11: ='HINO 2024'!H12+'HINO 2024'!H15 -> 6768 | F11: 912 | G11: 0 | H11: 3 | I11: ='HINO 2024'!G13+'HINO 2024'!G14+'HINO 2024'!G16 -> 1585.56 | J11: ='HINO 2024'!H13+'HINO 2024'!H14+'HINO 2024'!H16 -> 1440 | L11: 0 | M11: 0 | N11: 0 | O11: 0 | P11: =SUM(C11+H11+M11) -> 5 | Q11: =SUM(D11+E11+F11+G11+I11+J11+K11+L11+N11+O11) -> 44889.91 | R11: =Q11/P11 -> 8977.982
B12: JUNE | C12: 4 | D12: ='HINO 2024'!G17+'HINO 2024'!G18+'HINO 2024'!G19+'HINO 2024'!G21 -> 89981.07 | E12: ='HINO 2024'!H17+'HINO 2024'!H18+'HINO 2024'!H19+'HINO 2024'!H21 -> 17820 | F12: 11400 | G12: 0 | H12: 1 | I12: ='HINO 2024'!G20 -> 973.08 | J12: ='HINO 2024'!H20 -> 420 | L12: 0 | M12: 0 | N12: 0 | O12: 0 | P12: =SUM(C12+H12+M12) -> 5 | Q12: =SUM(D12+E12+F12+G12+I12+J12+K12+L12+N12+O12) -> 120594.15 | R12: =Q12/P12 -> 24118.83
B13: JULY | C13: 4 | D13: ='HINO 2024'!G30+'HINO 2024'!G31+'HINO 2024'!G34+'HINO 2024'!G37 -> 101460.05 | E13: ='HINO 2024'!H30+'HINO 2024'!H31+'HINO 2024'!H34+'HINO 2024'!H37 -> 24948 | F13: 237.5 | G13: 0 | H13: 0 | I13: 0 | J13: 0 | L13: 0 | M13: 2 | N13: 3350 | P13: =SUM(C13+H13+M13) -> 6 | Q13: =SUM(D13+E13+F13+G13+I13+J13+K13+L13+N13+O13) -> 129995.55 | R13: =Q13/P13 -> 21665.925
B14: AUGUST | C14: 2 | D14: ='HINO 2024'!G38+'HINO 2024'!G39 -> 51943.8 | E14: ='HINO 2024'!H38+'HINO 2024'!H39 -> 11412 | F14: 11670 | G14: 0 | H14: 0 | I14: 0 | J14: 0 | L14: 0 | M14: 0 | N14: 0 | O14: 0 | P14: =SUM(C14+H14+M14) -> 2 | Q14: =SUM(D14+E14+F14+G14+I14+J14+K14+L14+N14+O14) -> 75025.8 | R14: =Q14/P14 -> 37512.9
B15: SEPTEMBER | C15: 4 | D15: ='HINO 2024'!G40+'HINO 2024'!G41+'HINO 2024'!G42+'HINO 2024'!G43 -> 67422.15 | E15: ='HINO 2024'!H40+'HINO 2024'!H41+'HINO 2024'!H42+'HINO 2024'!H43 -> 17688 | F15: 4562 | G15: 0 | H15: 0 | I15: 0 | J15: 0 | L15: 0 | M15: 0 | N15: 0 | O15: 0 | P15: =SUM(C15+H15+M15) -> 4 | Q15: =SUM(D15+E15+F15+G15+I15+J15+K15+L15+N15+O15) -> 89672.15 | R15: =Q15/P15 -> 22418.037
B16: OCTOBER | C16: 1 | D16: ='HINO 2024'!G45 -> 6402.5 | E16: ='HINO 2024'!H45 -> 4380 | F16: 3277.5 | G16: 0 | H16: 1 | I16: ='HINO 2024'!G44 -> 973.08 | J16: ='HINO 2024'!H44 -> 420 | L16: 0 | M16: 0 | N16: 0 | O16: 0 | P16: =SUM(C16+H16+M16) -> 2 | Q16: =SUM(D16+E16+F16+G16+I16+J16+K16+L16+N16+O16) -> 15453.08 | R16: =Q16/P16 -> 7726.54
B17: NOVEMBER | C17: 2 | D17: ='HINO 2024'!G46+'HINO 2024'!G47 -> 82952.85 | E17: ='HINO 2024'!H46+'HINO 2024'!H47 -> 10620 | F17: 8521.26 | G17: 0 | H17: 0 | I17: 0 | J17: 0 | L17: 0 | M17: 0 | N17: 0 | O17: 0 | P17: =SUM(C17+H17+M17) -> 2 | Q17: =SUM(D17+E17+F17+G17+I17+J17+K17+L17+N17+O17) -> 102094.11 | R17: =Q17/P17 -> 51047.055
B18: DECEMBER | C18: 1 | D18: ='HINO 2024'!G57 -> 1045.01 | E18: ='HINO 2024'!H57 -> 262.2 | F18: 2090 | G18: 0 | H18: 1 | I18: ='HINO 2024'!G56 -> 973.08 | J18: ='HINO 2024'!H56 -> 420 | L18: 0 | M18: 0 | N18: 0 | O18: 0 | P18: =SUM(C18+H18+M18) -> 2 | Q18: =SUM(D18+E18+F18+G18+I18+J18+K18+L18+N18+O18) -> 4790.29 | R18: =Q18/P18 -> 2395.145
C19: =SUM(C7:C18) -> 25 | D19: =SUM(D7:D18) -> 559050.75 | E19: =SUM(E7:E18) -> 126694.2 | F19: =SUM(F7:F18) -> 54737.16 | G19: =SUM(G7:G18) -> 0 | H19: =SUM(H7:H18) -> 11 | I19: =SUM(I7:I18) -> 8154.11 | J19: =SUM(J7:J18) -> 4800 | ... Q19: =SUM(Q7:Q18) -> 756786.22 | R19: =Q19/P19 -> 19915.427
C22: MITSUBISHI
C23: ACCIDENT | H23: WINDSCREEN | M23: OTHERS | P23: TOTAL
C24: INTAKE | D24: INS - PARTS | E24: INS - LABOURS | F24: CREDIT | G24: CASH | H24: INTAKE | I24: INS - PARTS | J24: INS - LABOURS | K24: CREDIT | L24: CASH | M24: INTAKE | N24: CASH | O24: CREDIT | P24: INTAKE | Q24: TOTAL | R24: Avg
B25: JANUARY | C25: 7 | D25: ='MITS 2024'!G2+'MITS 2024'!G3+'MITS 2024'!G6+'MITS 2024'!G7+'MITS 2024'!G8+'MITS 2024'!G9+'MITS 2024'!G14 -> 93567.1 | E25: ='MITS 2024'!H2+'MITS 2024'!H3+'MITS 2024'!H6+'MITS 2024'!H7+'MITS 2024'!H8+'MITS 2024'!H9+'MITS 2024'!H14 -> 30384 | G25: 0 | H25: 5 | I25: ='MITS 2024'!G4+'MITS 2024'!G11+'MITS 2024'!G12+'MITS 2024'!G13+'MITS 2024'!G15 -> 9659.41 | J25: ='MITS 2024'!H4+'MITS 2024'!H11+'MITS 2024'!H12+'MITS 2024'!H13+'MITS 2024'!H15 -> 1248 | K25: 0 | L25: 0 | M25: 1 | N25: 1400 | O25: 0 | P25: =SUM(C25+H25+M25) -> 13 | Q25: =SUM(D25+E25+F25+G25+I25+J25+K25+L25+N25+O25) -> 136258.51 | R25: =Q25/P25 -> 10481.424
B26: FEBRUARY | C26: 2 | D26: ='MITS 2024'!G16+'MITS 2024'!G18 -> 52204.13 | E26: ='MITS 2024'!H16+'MITS 2024'!H18 -> 7488 | G26: 0 | H26: 1 | I26: ='MITS 2024'!G19 -> 2237.22 | J26: ='MITS 2024'!H19 -> 240 | K26: 0 | L26: 0 | M26: 1 | N26: 0 | O26: 10870.95 | P26: =SUM(C26+H26+M26) -> 4 | Q26: =SUM(D26+E26+F26+G26+I26+J26+K26+L26+N26+O26) -> 73040.3 | R26: =Q26/P26 -> 18260.075
B27: MARCH | C27: 7 | D27: ='MITS 2024'!G22+'MITS 2024'!G24+'MITS 2024'!G26+'MITS 2024'!G28+'MITS 2024'!G29+'MITS 2024'!G30+'MITS 2024'!G31 -> 82354.95 | E27: ='MITS 2024'!H22+'MITS 2024'!H24+'MITS 2024'!H26+'MITS 2024'!H28+'MITS 2024'!H29+'MITS 2024'!H30+'MITS 2024'!H31 -> 23040 | F27: 8699.63 | G27: 0 | H27: 4 | I27: ='MITS 2024'!G25+'MITS 2024'!G27+'MITS 2024'!G34 -> 6231.13 | J27: ='MITS 2024'!H25+'MITS 2024'!H27+'MITS 2024'!H34 -> 1266 | K27: 0 | L27: 2131.1 | M27: 2 | N27: 1344.1 | P27: =SUM(C27+H27+M27) -> 13 | Q27: =SUM(D27+E27+F27+G27+I27+J27+K27+L27+N27+O27) -> 125066.91 | R27: =Q27/P27 -> 9620.5315
B28: APRIL | C28: 7 | D28: ='MITS 2024'!G37+'MITS 2024'!G38+'MITS 2024'!G39+'MITS 2024'!G40+'MITS 2024'!G41+'MITS 2024'!G47+'MITS 2024'!G52 -> 82116.35 | E28: ='MITS 2024'!H37+'MITS 2024'!H38+'MITS 2024'!H39+'MITS 2024'!H40+'MITS 2024'!H41+'MITS 2024'!H47+'MITS 2024'!H52 -> 22728 | F28: 10184.71 | G28: 0 | H28: 6 | I28: ='MITS 2024'!G35+'MITS 2024'!G36+'MITS 2024'!G42+'MITS 2024'!G43+'MITS 2024'!G44+'MITS 2024'!G46 -> 11876.13 | J28: ='MITS 2024'!H35+'MITS 2024'!H36+'MITS 2024'!H42+'MITS 2024'!H43+'MITS 2024'!H44+'MITS 2024'!H46 -> 1428 | K28: 0 | L28: 0 | M28: 4 | N28: 0 | O28: 1130 | P28: =SUM(C28+H28+M28) -> 17 | Q28: =SUM(D28+E28+F28+G28+I28+J28+K28+L28+N28+O28) -> 129463.19 | R28: =Q28/P28 -> 7615.4818
B29: MAY | C29: 10 | D29: ='MITS 2024'!G53+'MITS 2024'!G54+'MITS 2024'!G55+'MITS 2024'!G56+'MITS 2024'!G61+'MITS 2024'!G63+'MITS 2024'!G64+'MITS 2024'!G65+'MITS 2024'!G66+'MITS 2024'!G69 -> 83909.6 | E29: ='MITS 2024'!H53+'MITS 2024'!H54+'MITS 2024'!H55+'MITS 2024'!H56+'MITS 2024'!H61+'MITS 2024'!H63+'MITS 2024'!H64+'MITS 2024'!H65+'MITS 2024'!H66+'MITS 2024'!H69 -> 26700 | F29: 712.5 | G29: 0 | H29: 3 | I29: ='MITS 2024'!G67+'MITS 2024'!G68+'MITS 2024'!G70 -> 4617.89 | J29: ='MITS 2024'!H67+'MITS 2024'!H68+'MITS 2024'!H70 -> 720 | K29: 0 | L29: 0 | M29: 6 | N29: 0 | O29: 2705.85 | P29: =SUM(C29+H29+M29) -> 19 | Q29: =SUM(D29+E29+F29+G29+I29+J29+K29+L29+N29+O29) -> 119365.84 | R29: =Q29/P29 -> 6282.4126
B30: JUNE | C30: 5 | D30: ='MITS 2024'!G72+'MITS 2024'!G73+'MITS 2024'!G74+'MITS 2024'!G81+'MITS 2024'!G82 -> 66073.51 | E30: ='MITS 2024'!H72+'MITS 2024'!H73+'MITS 2024'!H74+'MITS 2024'!H81+'MITS 2024'!H82 -> 18072 | F30: 0 | G30: 1528.86 | H30: 5 | I30: ='MITS 2024'!G75+'MITS 2024'!G76+'MITS 2024'!G77+'MITS 2024'!G78+'MITS 2024'!G79 -> 8742.65 | J30: ='MITS 2024'!H75+'MITS 2024'!H76+'MITS 2024'!H77+'MITS 2024'!H78+'MITS 2024'!H79 -> 1164 | K30: 0 | L30: 0 | M30: 0 | N30: 0 | O30: 0 | P30: =SUM(C30+H30+M30) -> 10 | Q30: =SUM(D30+E30+F30+G30+I30+J30+K30+L30+N30+O30) -> 95581.02 | R30: =Q30/P30 -> 9558.102
B31: JULY | C31: 9 | D31: ='MITS 2024'!G83+'MITS 2024'!G84+'MITS 2024'!G85+'MITS 2024'!G86+'MITS 2024'!G87+'MITS 2024'!G89+'MITS 2024'!G91+'MITS 2024'!G93+'MITS 2024'!G95 -> 162237.65 | E31: ='MITS 2024'!H83+'MITS 2024'!H84+'MITS 2024'!H85+'MITS 2024'!H86+'MITS 2024'!H87+'MITS 2024'!H89+'MITS 2024'!H91+'MITS 2024'!H93+'MITS 2024'!H95 -> 41439 | F31: 6368.37 | G31: 0 | H31: 5 | I31: ='MITS 2024'!G88+'MITS 2024'!G90+'MITS 2024'!G92+'MITS 2024'!G94+'MITS 2024'!G96 -> 6771.83 | J31: ='MITS 2024'!H88+'MITS 2024'!H90+'MITS 2024'!H92+'MITS 2024'!H94+'MITS 2024'!H96 -> 912 | K31: 0 | L31: 0 | M31: 0 | N31: 0 | O31: 0 | P31: =SUM(C31+H31+M31) -> 14 | Q31: =SUM(D31+E31+F31+G31+I31+J31+K31+L31+N31+O31) -> 217728.85 | R31: =Q31/P31 -> 15552.061
B32: AUGUST | C32: 10 | D32: ='MITS 2024'!G100+'MITS 2024'!G101+'MITS 2024'!G102+'MITS 2024'!G103+'MITS 2024'!G106+'MITS 2024'!G107+'MITS 2024'!G108+'MITS 2024'!G111+'MITS 2024'!G112+'MITS 2024'!G113 -> 72365.72 | E32: ='MITS 2024'!H100+'MITS 2024'!H101+'MITS 2024'!H102+'MITS 2024'!H103+'MITS 2024'!H106+'MITS 2024'!H107+'MITS 2024'!H108+'MITS 2024'!H111+'MITS 2024'!H112+'MITS 2024'!H113 -> 33528 | F32: 5076.27 | G32: 0 | H32: 3 | I32: ='MITS 2024'!G104+'MITS 2024'!G109+'MITS 2024'!G110 -> 7186.78 | J32: ='MITS 2024'!H104+'MITS 2024'!H109+'MITS 2024'!H110 -> 792 | K32: 0 | L32: 0 | M32: 4 | N32: 300 | O32: 6811.39 | P32: =SUM(C32+H32+M32) -> 17 | Q32: =SUM(D32+E32+F32+G32+I32+J32+K32+L32+N32+O32) -> 126060.16 | R32: =Q32/P32 -> 7415.3035
B33: SEPTEMBER | C33: 5 | D33: ='MITS 2024'!G114+'MITS 2024'!G119+'MITS 2024'!G121+'MITS 2024'!G122+'MITS 2024'!G123 -> 56523.05 | E33: ='MITS 2024'!H114+'MITS 2024'!H119+'MITS 2024'!H121+'MITS 2024'!H122+'MITS 2024'!H123 -> 24036 | F33: 0 | G33: 0 | H33: 5 | I33: ='MITS 2024'!G118+'MITS 2024'!G120+'MITS 2024'!G125+'MITS 2024'!G126+'MITS 2024'!G127 -> 10975.58 | J33: ='MITS 2024'!H118+'MITS 2024'!H120+'MITS 2024'!H125+'MITS 2024'!H126+'MITS 2024'!H127 -> 1320 | K33: 0 | L33: 0 | M33: 4 | N33: 2102.1 | O33: 930 | P33: =SUM(C33+H33+M33) -> 14 | Q33: =SUM(D33+E33+F33+G33+I33+J33+K33+L33+N33+O33) -> 95886.73 | R33: =Q33/P33 -> 6849.0521
B34: OCTOBER | C34: 8 | D34: ='MITS 2024'!G128+'MITS 2024'!G129+'MITS 2024'!G131+'MITS 2024'!G133+'MITS 2024'!G134+'MITS 2024'!G136+'MITS 2024'!G137+'MITS 2024'!G138 -> 166938.41 | E34: ='MITS 2024'!H128+'MITS 2024'!H129+'MITS 2024'!H131+'MITS 2024'!H133+'MITS 2024'!H134+'MITS 2024'!H136+'MITS 2024'!H137+'MITS 2024'!H138 -> 28158 | F34: 2907 | G34: 0 | H34: 7 | I34: ='MITS 2024'!G130+'MITS 2024'!G135+'MITS 2024'!G139+'MITS 2024'!G140+'MITS 2024'!G141+'MITS 2024'!G142+'MITS 2024'!G145 -> 14217.34 | J34: ='MITS 2024'!H130+'MITS 2024'!H135+'MITS 2024'!H139+'MITS 2024'!H140+'MITS 2024'!H141+'MITS 2024'!H142+'MITS 2024'!H145 -> 1860 | K34: 0 | L34: 0 | M34: 3 | N34: 7884.81 | O34: 1961 | P34: =SUM(C34+H34+M34) -> 18 | Q34: =SUM(D34+E34+F34+G34+I34+J34+K34+L34+N34+O34) -> 223926.56 | R34: =Q34/P34 -> 12440.364
B35: NOVEMBER | C35: 9 | D35: ='MITS 2024'!G146+'MITS 2024'!G147+'MITS 2024'!G148+'MITS 2024'!G149+'MITS 2024'!G150+'MITS 2024'!G151+'MITS 2024'!G156+'MITS 2024'!G157+'MITS 2024'!G158 -> 68433.45 | E35: ='MITS 2024'!H146+'MITS 2024'!H147+'MITS 2024'!H148+'MITS 2024'!H149+'MITS 2024'!H150+'MITS 2024'!H151+'MITS 2024'!H156+'MITS 2024'!H157+'MITS 2024'!H158 -> 17389 | F35: 4421.28 | G35: 0 | H35: 4 | I35: ='MITS 2024'!G152+'MITS 2024'!G153+'MITS 2024'!G154+'MITS 2024'!G155 -> 8353.54 | J35: ='MITS 2024'!H152+'MITS 2024'!H153+'MITS 2024'!H154+'MITS 2024'!H155 -> 1032 | K35: 0 | L35: 0 | M35: 0 | N35: 0 | O35: 0 | P35: =SUM(C35+H35+M35) -> 13 | Q35: =SUM(D35+E35+F35+G35+I35+J35+K35+L35+N35+O35) -> 99629.27 | R35: =Q35/P35 -> 7663.79
B36: DECEMBER | C36: 2 | D36: ='MITS 2024'!G159+'MITS 2024'!G160 -> 59314.97 | E36: ='MITS 2024'!H159+'MITS 2024'!H160 -> 7476 | F36: 1320.5 | G36: 0 | H36: 7 | I36: ='MITS 2024'!G161+'MITS 2024'!G162+'MITS 2024'!G163+'MITS 2024'!G164+'MITS 2024'!G165+'MITS 2024'!G166+'MITS 2024'!G167 -> 11923.41 | J36: ='MITS 2024'!H161+'MITS 2024'!H162+'MITS 2024'!H163+'MITS 2024'!H164+'MITS 2024'!H165+'MITS 2024'!H166+'MITS 2024'!H167 -> 1776 | K36: 951.48 | L36: 0 | M36: 0 | N36: 0 | O36: 0 | P36: =SUM(C36+H36+M36) -> 9 | Q36: =SUM(D36+E36+F36+G36+I36+J36+K36+L36+N36+O36) -> 82762.36 | R36: =Q36/P36 -> 9195.8178
C37: =SUM(C25:C36) -> 81 | D37: =SUM(D25:D36) -> 1046038.9 | E37: =SUM(E25:E36) -> 280438 | F37: =SUM(F25:F36) -> 39690.26 | G37: =SUM(G25:G36) -> 1528.86 | H37: =SUM(H25:H36) -> 55 | I37: =SUM(I25:I36) -> 102792.91 | J37: =SUM(J25:J36) -> 13758 | ... Q37: =SUM(Q25:Q36) -> 1524769.7 | R37: =Q37/P37 -> 9470.6193
C40: AFTER SALES SERVICE
C41: SERVICE FUSO | M41: SERVICE HINO | P41: TOTAL
C42: INTAKE | D42: FREE SERVICE | G42: INTAKE | H42: WARRANTY | I42: INTAKE | L42: CASH | M42: INTAKE | N42: INVOICE | O42: CASH | P42: INTAKE | Q42: TOTAL | R42: Avg
B43: JANUARY | C43: 1 | D43: 348.21 | G43: 0 | H43: 0 | I43: 2 | L43: 1448.67 | M43: 0 | N43: 0 | O43: 0 | P43: =SUM(C43+G43+I43+M43) -> 3 | Q43: =SUM(D43+H43+L43+N43) -> 1796.88 | R43: =Q43/P43 -> 598.96
B44: FEBRUARY | C44: 0 | D44: 0 | G44: 0 | H44: 0 | I44: 0 | L44: 0 | M44: 0 | N44: 0 | O44: 0 | P44: =SUM(C44+G44+I44+M44) -> 0 | Q44: =SUM(D44+H44+L44+N44) -> 0 | R44: =Q44/P44 -> #DIV/0!
B45: MARCH | C45: 3 | D45: 1426.8 | G45: 1 | H45: 205.68 | I45: 1 | L45: 1091 | M45: 0 | N45: 0 | O45: 0 | P45: =SUM(C45+G45+I45+M45) -> 5 | Q45: =SUM(D45+H45+L45+N45) -> 2723.48 | R45: =Q45/P45 -> 544.696
B46: APRIL | C46: 2 | D46: 1267.41 | G46: 1 | H46: 3317.57 | I46: 1 | L46: 988.3 | M46: 0 | N46: 0 | O46: 0 | P46: =SUM(C46+G46+I46+M46) -> 4 | Q46: =SUM(D46+H46+L46+N46) -> 5573.28 | R46: =Q46/P46 -> 1393.32
B47: MAY | C47: 1 | D47: 351.81 | G47: 1 | H47: 369.36 | I47: 0 | L47: 0 | M47: 0 | N47: 0 | O47: 0 | P47: =SUM(C47+G47+I47+M47) -> 2 | Q47: =SUM(D47+H47+L47+N47) -> 721.17 | R47: =Q47/P47 -> 360.585
B48: JUNE | C48: 4 | D48: 1767.81 | G48: 0 | H48: 0 | I48: 1 | L48: 615 | M48: 8 | N48: 2748.2 | O48: 0 | P48: =SUM(C48+G48+I48+M48) -> 13 | Q48: =SUM(D48+H48+L48+N48) -> 5131.01 | R48: =Q48/P48 -> 394.69308
B49: JULY | C49: 2 | D49: 1040.39 | G49: 0 | H49: 0 | I49: 0 | M49: 2 | N49: 2688.4 | O49: 0 | P49: =SUM(C49+G49+I49+M49) -> 4 | Q49: =SUM(D49+H49+L49+N49) -> 3728.79 | R49: =Q49/P49 -> 932.1975
B50: AUGUST | C50: 0 | D50: 0 | G50: 0 | H50: 0 | I50: 0 | M50: 0 | N50: 0 | O50: 0 | P50: =SUM(C50+G50+I50+M50) -> 0 | Q50: =SUM(D50+H50+L50+N50) -> 0 | R50: =Q50/P50 -> #DIV/0!
B51: SEPTEMBER | C51: 3 | D51: 1516.4 | G51: 0 | H51: 0 | I51: 1 | L51: 1707.55 | M51: 0 | N51: 0 | O51: 0 | P51: =SUM(C51+G51+I51+M51) -> 4 | Q51: =SUM(D51+H51+L51+N51) -> 3223.95 | R51: =Q51/P51 -> 805.9875
B52: OCTOBER | C52: 0 | D52: 0 | G52: 1 | H52: 1920.24 | I52: 1 | L52: 601.3 | M52: 0 | N52: 0 | O52: 0 | P52: =SUM(C52+G52+I52+M52) -> 2 | Q52: =SUM(D52+H52+L52+N52) -> 2521.54 | R52: =Q52/P52 -> 1260.77
B53: NOVEMBER | C53: 3 | D53: 1426.8 | G53: 1 | H53: 661.2 | I53: 0 | L53: 0 | M53: 8 | N53: 3456 | O53: 0 | P53: =SUM(C53+G53+I53+M53) -> 12 | Q53: =SUM(D53+H53+L53+N53) -> 5544 | R53: =Q53/P53 -> 462
B54: DECEMBER | C54: 1 | D54: 445.01 | G54: 0 | H54: 0 | I54: 0 | L54: 0 | M54: 10 | N54: 6489.94 | O54: 0 | P54: =SUM(C54+G54+I54+M54) -> 11 | Q54: =SUM(D54+H54+L54+N54) -> 6934.95 | R54: =Q54/P54 -> 630.45
C55: =SUM(C43:C54) -> 20 | D55: =SUM(D43:D54) -> 9590.64 | G55: =SUM(G43:G54) -> 5 | H55: =SUM(H43:H54) -> 6474.05 | I55: =SUM(I43:I54) -> 7 | L55: =SUM(L43:L54) -> 6451.82 | M55: =SUM(M43:M54) -> 28 | N55: =SUM(N43:N54) -> 15382.54 | P55: =SUM(P43:P54) -> 60 | Q55: =SUM(Q43:Q54) -> 37899.05 | R55: =Q55/P55 -> 631.65083
I57: Average Per Month : | L57: =(Q19/(COUNTA(C7:C18))) -> 63065.518 | M57: HINO
I58: Average Per Month : | L58: =(Q37/(COUNTA(C25:C36))) -> 127064.14 | M58: MITSUBUSHI
I59: Average Per Month : | L59: =Q55/(COUNTA(C43:C54)) -> 3158.2542 | M59: AFTER SALES SERVICE
P60: B&P Sales %
D61: Hino | G61: Mitsubishi | I61: B&P | L61: Service | N61: Total | P61: Hino | Q61: Mitsubishi | R61: Service
B62: Total Insurance | D62: =SUM(D19+I19) -> 567204.86 | G62: =SUM(D37+I37) -> 1148831.8 | I62: =D62+G62 -> 1716036.7 | L62: =D55+H55+N55 -> 31447.23 | N62: =SUM(I62:M62) -> 1747483.9 | P62: =SUM(D62/N62) -> 0.32458374 | Q62: =SUM(G62/N62) -> 0.65742054 | R62: =L62/N62 -> 0.01799572
B63: Total WindScreen | D63: =SUM(I19:L19) -> 12954.11 | G63: =SUM(I37:L37) -> 119633.49 | I63: =D63+G63 -> 132587.6 | N63: =SUM(I63:M63) -> 132587.6 | P63: =SUM(D63/N63) -> 0.097702274 | Q63: =SUM(G63/N63) -> 0.90229773 | R63: =L63/N63 -> 0
B64: Total Cash Job | D64: =G19+L19+N19 -> 3350 | G64: =G37+L37+N37 -> 16690.97 | I64: =D64+G64 -> 20040.97 | L64: =L55 -> 6451.82 | N64: =SUM(I64:M64) -> 26492.79 | P64: =SUM(D64/N64) -> 0.1264495 | Q64: =SUM(G64/N64) -> 0.63001934 | R64: =L64/N64 -> 0.24353116
B65: Others | D65: =O19 -> 0 | G65: =O37 -> 24409.19 | I65: =D65+G65 -> 24409.19 | N65: =SUM(I65:M65) -> 24409.19
B66: Total : | D66: =SUM(D62:D65)-I19 -> 575354.86 | G66: =SUM(G62:G65)-I37 -> 1206772.5 | I66: =SUM(I62:I65)-I63 -> 1760486.8 | L66: =SUM(L62:L65) -> 37899.05 | N66: =SUM(N62:N65)-N63 -> 1798385.9 | P66: - | Q66: -
B69: REMARKS:
B70: ** ALL THE PROCESSING FEE, EXCESS FEE, 2F CLAIMS TO BE RECOGNISE UNDER ACCIDENT & WINDSCREEN (CREDIT COLUMN).

Sheet MITS 2023
A1: TRANSNO | C1: DATE | D1: CUSTOMER NAME | E1: REG NO | F1: JOBNO | G1: P.TOTAL | H1: L.TOTAL | I1: GTOTAL | J1: TOTAL | K1: SVC TYPE
A2: MBPCASH2311001 | B2: NOV | C2: 45239 | D2: NARIZAH | E2: VKJ1617 | F2: MBPWO2311001 | G2: 282 | H2: 318 | I2: 600 | J2: 600 | K2: CR | L2: SPRAY
A3: MBPSI2311001 | B3: NOV | C3: 45254 | D3: AUTO RAYA TIMUR SDN BHD | E3: VKM7660 | F3: MBPWO2311011 | G3: 1084.9 | H3: 228 | I3: 1312.9 | J3: 1312.9 | K3: WS
A4: MBPSI2312001 | B4: DEC | C4: 45262 | D4: MUHAMMAD FARIDDUDIN BIN SALLEH | E4: SMF9353 | F4: MBPWO2312007 | G4: 900 | I4: 900 | J4: 900 | K4: CR | L4: SPRAY
A5: MBPSI2312002 | B5: DEC | C5: 45273 | D5: AUTO RAYA TIMUR SDN BHD | E5: VFU9990 | F5: MBPWO2311008 | G5: 1517.35 | H5: 300 | I5: 1817.35 | J5: 1817.35 | K5: WS
A6: MBPSI2312003 | B6: DEC | C6: 45287 | D6: AUTO RAYA TIMUR SDN BHD | E6: VJN4429 | F6: MBPWO2311015 | G6: 1566.05 | H6: 276 | I6: 1842.05 | J6: 1842.05 | K6: WS
A7: MBPSI2312004 | B7: DEC | C7: 45287 | D7: AUTO RAYA TIMUR SDN BHD | E7: CEQ6122 | F7: MBPWO2311014 | G7: 2596.32 | H7: 240 | I7: 2836.32 | J7: 2836.32 | K7: WS
A8: MBPSI2312005 | B8: DEC | C8: 45288 | D8: AUTO RAYA TIMUR SDN BHD | E8: JUK1169 | F8: MBPWO2311012 | G8: 1642.39 | H8: 708 | I8: 2350.39 | J8: 2350.39 | K8: OD
A9: MBPSI2312006 | B9: DEC | C9: 45288 | D9: AUTO RAYA TIMUR SDN BHD | E9: VKH8524 | F9: MBPWO2311013 | G9: 3739.61 | H9: 3132 | I9: 6871.61 | J9: 6871.61 | K9: OD
A10: MBPSI2312007 | B10: DEC | C10: 45288 | D10: AUTO RAYA TIMUR SDN BHD | E10: SMF9353 | F10: MBPWO2311003 | G10: 19138.12 | H10: 3840 | I10: 22978.12 | J10: 22978.12 | K10: OD
A11: MBPSI2312008 | B11: DEC | C11: 45290 | D11: AUTO RAYA TIMUR SDN BHD | E11: VFW1566 | F11: MBPWO2311005 | G11: 31483.63 | H11: 2916 | I11: 34399.63 | J11: 34399.63 | K11: OD
A12: MBPSI2312009 | B12: DEC | C12: 45289 | D12: AUTO RAYA TIMUR SDN BHD | E12: BQQ2927 | F12: MBPWO2312002 | G12: 11115 | H12: 2736 | I12: 13851 | J12: 13851 | K12: OD
A13: MBPSI2312010 | B13: DEC | C13: 45290 | D13: AUTO RAYA TIMUR SDN BHD | E13: BQN1336 | F13: MBPWO2311006 | G13: 5586.6 | H13: 7908 | I13: 13494.6 | J13: 13494.6 | K13: OD
J15: =SUM(J2:J14) -> 103253.97
A21: TRANSNO | B21: MONTH | C21: DATE | D21: CUSTOMER NAME | E21: REFERENCE | F21: TOTAL
A22: MBPIV2403013 | B22: MAR | C22: 45365 | D22: AUTO RAYA TIMUR SDN BHD | E22: VJJ9120 | F22: 822.7 | G22: OD
A23: MBPIV2403014 | B23: MAR | C23: 45373 | D23: AUTO RAYA TIMUR SDN BHD | E23: AKT3446 | F23: 3126.93 | G23: OD
A24: MBPIV2403015 | B24: MAR | C24: 45376 | D24: AUTO RAYA TIMUR SDN BHD | E24: CEP8036 | F24: 4750 | G24: OD
F26: =SUM(F22:F24) -> 8699.63

Sheet MITS 2024
A1: TRANSNO | C1: DATE | D1: CUSTOMER NAME | E1: REG NO | F1: JOBNO | G1: P.TOTAL | H1: L.TOTAL | I1: GTOTAL | J1: TOTAL | K1: SVC TYPE
A2: MBPSI2401001 | B2: JAN | C2: 45295 | D2: AUTO RAYA TIMUR SDN BHD | E2: CEM8056 | F2: MBPWO2311007 | G2: 17559.82 | H2: 6072 | I2: 23631.82 | J2: 23631.82 | K2: OD
A3: MBPSI2401002 | C3: 45296 | D3: AUTO RAYA TIMUR SDN BHD | E3: CEN9684 | F3: MBPWO2401001 | G3: 5047.53 | H3: 2628 | I3: 7675.53 | J3: 7675.53 | K3: OD
A4: MBPSI2401003 | B4: JAN | C4: 45297 | D4: AUTO RAYA TIMUR SDN BHD | E4: KFN7175 | F4: MBPWO2312006 | G4: 2936.8 | H4: 240 | I4: 3176.8 | J4: 3176.8 | K4: WS
A5: MBPSI2401004 | C5: 45299 | D5: MUHAMAD KHAIRUL LUBIS BIN RAZAK | E5: KFP8082 | F5: MBPWO2401003 | G5: 90 | H5: 1310 | I5: 1400 | J5: 1400 | K5: CR | L5: CASH
A6: MBPSI2401005 | C6: 45301 | D6: AUTO RAYA TIMUR SDN BHD | E6: VKK5775 | F6: MBPWO2311009 | G6: 22110.19 | H6: 5328 | I6: 27438.19 | J6: 27438.19 | K6: OD
A7: MBPSI2401006 | C7: 45302 | D7: AUTO RAYA TIMUR SDN BHD | E7: VGY9225 | F7: MBPWO2312005 | G7: 5043.15 | H7: 1764 | I7: 6807.15 | J7: 6807.15 | K7: OD
A8: MBPSI2401007 | C8: 45308 | D8: AUTO RAYA TIMUR SDN BHD | E8: VHA8645 | F8: MBPWO2311004 | G8: 12185.29 | H8: 2616 | I8: 14801.29 | J8: 14801.29 | K8: OD
A9: MBPSI2401008 | C9: 45308 | D9: AUTO RAYA TIMUR SDN BHD | E9: SU7816G | F9: MBPWO2312004 | G9: 25105.62 | H9: 7956 | I9: 33061.62 | J9: 33061.62 | K9: OD
A10: MBPSI2401009 | C10: 45310 | D10: AUTO RAYA TIMUR SDN BHD | E10: WC4350F | F10: MBPWO2401007 | G10: 2025.57 | H10: 240 | I10: 0 | J10: 2265.57 | K10: CANCEL
A11: MBPSI2401010 | C11: 45317 | D11: AUTO RAYA TIMUR SDN BHD | E11: VHA8645 | F11: MBPWO2401006 | G11: 1646.32 | H11: 240 | I11: 1886.32 | J11: 1886.32 | K11: WS
A12: MBPSI2401011 | C12: 45317 | D12: AUTO RAYA TIMUR SDN BHD | E12: WC4350F | F12: MBPWO2401007 | G12: 1857.6 | H12: 240 | I12: 2097.6 | J12: 2097.6 | K12: WS
A13: MBPSI2401012 | C13: 45314 | D13: AUTO RAYA TIMUR SDN BHD | E13: JQW3320 | F13: MBPWO2401010 | G13: 1633.64 | H13: 252 | I13: 1885.64 | J13: 1885.64 | K13: WS
A14: MBPSI2401013 | C14: 45298 | D14: AUTO RAYA TIMUR SDN BHD | E14: VGL2124 | F14: MBPWO2401008 | G14: 6515.5 | H14: 4020 | I14: 10535.5 | J14: 10535.5 | K14: OD
A15: MBPSI2401014 | C15: 45317 | D15: AUTO RAYA TIMUR SDN BHD | E15: UMT221 | F15: MBPWO2401009 | G15: 1585.05 | H15: 276 | I15: 1861.05 | J15: 1861.05 | K15: WS
A16: MBPSI2402001 | B16: FEB | C16: 45327 | D16: AUTO RAYA TIMUR SDN BHD | E16: RAQ9297 | F16: MBPWO2311002 | G16: 37606.72 | H16: 4020 | I16: 41626.72 | J16: 41626.72 | K16: OD
A17: MBPSI2402002 | C17: 45327 | D17: AUTO RAYA TIMUR SDN BHD | E17: 31841 | F17: MBPWO2312003 | G17: 3951.75 | H17: 6919.2 | I17: 10870.95 | J17: 10870.95 | K17: CR | L17: CREDIT
A18: MBPSI2402003 | C18: 45342 | D18: AUTO RAYA TIMUR SDN BHD | E18: AKT3446 | F18: MBPWO2402001 | G18: 14597.41 | H18: 3468 | I18: 18065.41 | J18: 18065.41 | K18: OD
A19: MBPSI2402004 | B19: FEB | C19: 45345 | D19: AUTO RAYA TIMUR SDN BHD | E19: QAB1974G | F19: MBPWO2402006 | G19: 2237.22 | H19: 240 | I19: 2477.22 | J19: 2477.22 | K19: WS
A20: MBPSI2403001 | C20: 45352 | D20: MUHAMMAD FARIDDUDIN BIN SALLEH | E20: SMF9353 | F20: MBPWO2403003 | G20: 260 | I20: 260 | J20: 260 | K20: CR | L20: CASH
A21: MBPSI2403002 | C21: 45356 | D21: AUTO RAYA TIMUR SDN BHD | E21: TCF150 | F21: MBPWO2403005 | G21: 1340.5 | I21: 1340.5 | K21: TRAINING
A22: MBPSI2403003 | B22: MAR | C22: 45356 | D22: AUTO RAYA TIMUR SDN BHD | E22: VKU9306 | F22: MBPWO2402004 | G22: 12208.98 | H22: 3132 | I22: 15340.98 | J22: 15340.98 | K22: OD
A23: MBPSI2403004 | C23: 45356 | D23: AUTO RAYA TIMUR SDN BHD | E23: JUC1888 | F23: MBPWO2403006 | G23: 1129.5 | I23: 1129.5 | J23: 1129.5 | K23: TRAINING
A24: MBPSI2403005 | C24: 45356 | D24: AUTO RAYA TIMUR SDN BHD | E24: CET5945 | F24: MBPWO2402005 | G24: 10235.36 | H24: 2484 | I24: 12719.36 | J24: 12719.36 | K24: OD
A25: MBPSI2403006 | B25: MAR | C25: 45359 | D25: AUTO RAYA TIMUR SDN BHD | E25: CEH9366 | F25: MBPWO2403004 | G25: 1128.02 | H25: 276 | I25: 1404.02 | J25: 1404.02 | K25: WS
A26: MBPSI2403007 | C26: 45359 | D26: AUTO RAYA TIMUR SDN BHD | E26: VKU7912 | F26: MBPWO2401002 | G26: 3673.85 | H26: 2124 | I26: 5797.85 | J26: 5797.85 | K26: OD
A27: MBPSI2403008 | C27: 45360 | D27: AUTO RAYA TIMUR SDN BHD | E27: JDE5445 | F27: MBPWO2403002 | G27: 3021.35 | H27: 240 | I27: 3261.35 | J27: 3261.35 | K27: WS
A28: MBPSI2403009 | C28: 45365 | D28: AUTO RAYA TIMUR SDN BHD | E28: SMK6928 | F28: MBPWO2402010 | G28: 2755.2 | H28: 2124 | I28: 4879.2 | J28: 4879.2 | K28: OD
A29: MBPSI2403010 | C29: 45365 | D29: AUTO RAYA TIMUR SDN BHD | E29: VKU7912 | F29: MBPWO2401005 | G29: 24862.38 | H29: 4248 | I29: 29110.38 | J29: 29110.38 | K29: OD
A30: MBPSI2403011 | C30: 45365 | D30: AUTO RAYA TIMUR SDN BHD | E30: VJJ9120 | F30: MBPWO2402003 | G30: 15330.8 | H30: 4452 | I30: 19782.8 | J30: 19782.8 | K30: OD
A31: MBPSI2403012 | C31: 45369 | D31: AUTO RAYA TIMUR SDN BHD | E31: AMK4010 | F31: MBPWO2402002 | G31: 13288.38 | H31: 4476 | I31: 17764.38 | J31: 17764.38 | K31: OD
A32: MBPSI2403013 | C32: 45370 | D32: MOHD RUKMAN BIN ABU HASAN | E32: DET1782 | F32: MBPWO2403009 | G32: 808.08 | H32: 276 | I32: 1084.1 | J32: 1084.1 | K32: CR | L32: CASH | M32: SCREEN REPLACEMENT
A33: MBPSI2403014 | C33: 45378 | D33: SAIFUL AZHAR BIN IBRAHIM | E33: WWS7678 | F33: MBPWO2403011 | G33: 1879.12 | H33: 252 | I33: 2131.1 | J33: 2131.1 | K33: WS | L33: CASH
A34: MBPSI2403015 | C34: 45378 | D34: AUTO RAYA TIMUR SDN BHD | E34: DEQ7921 | F34: MBPWO2403008 | G34: 2081.76 | H34: 750 | I34: 2831.76 | J34: 2831.76 | K34: WS
A35: MBPSI2404001 | B35: APR | C35: 45386 | D35: AUTO RAYA TIMUR SDN BHD | E35: SU3892F | F35: MBPWO2403007 | G35: 2610.75 | H35: 240 | I35: 2850.75 | J35: 2850.75 | K35: WS
A36: MBPSI2404002 | C36: 45397 | D36: AUTO RAYA TIMUR SDN BHD | E36: CEM7985 | F36: MBPWO2403013 | G36: 2116.76 | H36: 240 | I36: 2356.76 | J36: 2356.76 | K36: WS
A37: MBPSI2404003 | B37: APR | C37: 45398 | D37: AUTO RAYA TIMUR SDN BHD | E37: WA4150C | F37: MBPWO2403001 | G37: 3079.1 | H37: 2448 | I37: 5527.1 | J37: 5527.1 | K37: OD
A38: MBPSI2404004 | C38: 45398 | D38: AUTO RAYA TIMUR SDN BHD | E38: KFQ7001 | F38: MBPWO2402011 | G38: 7758.89 | H38: 2148 | I38: 9906.89 | J38: 9906.89 | K38: OD
A39: MBPSI2404005 | C39: 45401 | D39: AUTO RAYA TIMUR SDN BHD | E39: BQQ2927 | F39: MBPWO2404001 | G39: 4897.85 | H39: 2172 | I39: 7069.85 | J39: 7069.85 | K39: OD
A40: MBPSI2404006 | C40: 45401 | D40: AUTO RAYA TIMUR SDN BHD | E40: CEP8036 | F40: MBPWO2312001 | G40: 38784.63 | H40: 5580 | I40: 44364.63 | J40: 44364.63 | K40: OD
A41: MBPSI2404007 | C41: 45401 | D41: AUTO RAYA TIMUR SDN BHD | E41: ANE7068 | F41: MBPWO2403010 | G41: 20831.93 | H41: 6024 | I41: 26855.93 | J41: 26855.93 | K41: OD
A42: MBPSI2404008 | C42: 45401 | D42: AUTO RAYA TIMUR SDN BHD | E42: VFS7165 | F42: MBPWO2404002 | G42: 1084.67 | H42: 228 | I42: 1312.67 | J42: 1312.67 | K42: WS
A43: MBPSI2404009 | C43: 45406 | D43: AUTO RAYA TIMUR SDN BHD | E43: VKT9413 | F43: MBPWO2403012 | G43: 2609.05 | H43: 240 | I43: 2849.05 | J43: 2849.05 | K43: WS
A44: MBPSI2404010 | C44: 45406 | D44: AUTO RAYA TIMUR SDN BHD | E44: VBK4937 | F44: MBPWO2404005 | G44: 1660.95 | H44: 240 | I44: 1900.95 | J44: 1900.95 | K44: WS
A45: MBPSI2404011 | C45: 45406 | D45: AUTO RAYA TIMUR SDN BHD | E45: QM8084J | F45: MBPWO2404008 | G45: 171.8 | H45: 972 | I45: 0 | J45: 1143.8 | K45: CANCEL
A46: MBPSI2404012 | C46: 45406 | D46: AUTO RAYA TIMUR SDN BHD | E46: VFN5440 | F46: MBPWO2404009 | G46: 1793.95 | H46: 240 | I46: 2033.95 | J46: 2033.95 | K46: WS
A47: MBPSI2404013 | C47: 45406 | D47: AUTO RAYA TIMUR SDN BHD | E47: QM8084J | F47: MBPWO2404008 | G47: 171.8 | H47: 900 | I47: 1071.8 | J47: 1071.8 | K47: OD
A48: MBPSI2404014 | C48: 45408 | D48: AUTO RAYA TIMUR SDN BHD | E48: 092747 | F48: MBPWO2404011 | G48: 80 | H48: 230 | I48: 310 | J48: 310 | K48: CR | L48: CREDIT
A49: MBPSI2404015 | C49: 45408 | D49: AUTO RAYA TIMUR SDN BHD | E49: 087055 | F49: MBPWO2404013 | G49: 50 | H49: 150 | I49: 200 | J49: 200 | K49: CR | L49: CREDIT
A50: MBPSI2404016 | C50: 45408 | D50: AUTO RAYA TIMUR SDN BHD | E50: 095074 | F50: MBPWO2404012 | G50: 80 | H50: 230 | I50: 310 | J50: 310 | K50: CR | L50: CREDIT
A51: MBPSI2404017 | C51: 45408 | D51: AUTO RAYA TIMUR SDN BHD | E51: 092726 | F51: MBPWO2404014 | G51: 80 | H51: 230 | I51: 310 | J51: 310 | K51: CR | L51: CREDIT
A52: MBPSI2404018 | C52: 45411 | D52: AUTO RAYA TIMUR SDN BHD | E52: QM8801L | F52: MBPWO2404004 | G52: 6592.15 | H52: 3456 | I52: 10048.15 | J52: 10048.15 | K52: OD
A53: MBPSI2405001 | B53: MAY | C53: 45418 | D53: AUTO RAYA TIMUR SDN BHD | E53: QM8801L | F53: MBPWO2405004 | G53: 47.5 | I53: 47.5 | J53: 47.5 | K53: OD
A54: MBPSI2405002 | C54: 45422 | D54: AUTO RAYA TIMUR SDN BHD | E54: QAB7524H | F54: MBPWO2404015 | G54: 11817.05 | H54: 5244 | I54: 17061.05 | J54: 17061.05 | K54: OD
A55: MBPSI2405003 | C55: 45423 | D55: AUTO RAYA TIMUR SDN BHD | E55: VHJ2847 | F55: MBPWO2404007 | G55: 4903.2 | H55: 2940 | I55: 7843.2 | J55: 7843.2 | K55: OD
A56: MBPSI2405004 | C56: 45427 | D56: AUTO RAYA TIMUR SDN BHD | E56: SU7816G | F56: MBPWO2404010 | G56: 5360.01 | I56: 5360.01 | J56: 5360.01 | K56: OD
A57: MBPSI2405005 | C57: 45428 | D57: AUTO RAYA TIMUR SDN BHD | E57: 092751 | F57: MBPWO2405010 | G57: 80 | H57: 230 | I57: 310 | J57: 310 | K57: CR | L57: CREDIT
A58: MBPSI2405006 | C58: 45429 | D58: AUTO RAYA TIMUR SDN BHD | E58: 082926 | F58: MBPQN00010 | G58: 80 | H58: 230 | I58: 310 | J58: 310 | K58: CR | L58: CREDIT
A59: MBPSI2405007 | C59: 45430 | D59: AUTO RAYA TIMUR SDN BHD | E59: 092504 | F59: MBPWO2405012 | G59: 80 | H59: 230 | I59: 310 | J59: 310 | K59: CR | L59: CREDIT
A60: MBPSI2405008 | C60: 45430 | D60: AUTO RAYA TIMUR SDN BHD | E60: 092534 | F60: MBPWO2405014 | G60: 80 | H60: 230 | I60: 310 | J60: 310 | K60: CR | L60: CREDIT
A61: MBPSI2405009 | C61: 45433 | D61: AUTO RAYA TIMUR SDN BHD | E61: VKU5342 | F61: MBPWO2405001 | G61: 4517.17 | H61: 2124 | I61: 6641.17 | J61: 6641.17 | K61: OD
A62: MBPSI2405010 | C62: 45433 | D62: AUTO RAYA TIMUR SDN BHD | E62: VJY9012 | F62: MBPWO2405008 | G62: 1153.85 | H62: 252 | I62: 1405.85 | J62: 1405.85 | K62: CR | L62: CREDIT
A63: MBPSI2405011 | C63: 45436 | D63: AUTO RAYA TIMUR SDN BHD | E63: VLK6742 | F63: MBPWO2405003 | G63: 3096.63 | H63: 1452 | I63: 4548.63 | J63: 4548.63 | K63: OD
A64: MBPSI2405012 | C64: 45436 | D64: AUTO RAYA TIMUR SDN BHD | E64: CEK9753 | F64: MBPWO2405006 | G64: 1351.98 | H64: 3864 | I64: 5215.98 | J64: 5215.98 | K64: OD
A65: MBPSI2405013 | C65: 45436 | D65: AUTO RAYA TIMUR SDN BHD | E65: VKB4059 | F65: MBPWO2405007 | G65: 3263.71 | H65: 2628 | I65: 5891.71 | J65: 5891.71 | K65: OD
A66: MBPSI2405014 | C66: 45436 | D66: AUTO RAYA TIMUR SDN BHD | E66: VGH9547 | F66: MBPWO2405002 | G66: 4785.14 | H66: 4260 | I66: 9045.14 | J66: 9045.14 | K66: OD
A67: MBPSI2405015 | B67: MAY | C67: 45437 | D67: AUTO RAYA TIMUR SDN BHD | E67: SMK567 | F67: MBPWO2405017 | G67: 1316.85 | H67: 168 | I67: 1484.85 | J67: 1484.85 | K67: WS
A68: MBPSI2405016 | C68: 45441 | D68: AUTO RAYA TIMUR SDN BHD | E68: VJA1216 | F68: MBPWO2405013 | G68: 1698.02 | H68: 276 | I68: 1974.02 | J68: 1974.02 | K68: WS
A69: MBPSI2405017 | C69: 45441 | D69: AUTO RAYA TIMUR SDN BHD | E69: DEX4730 | F69: MBPWO2404016 | G69: 44767.21 | H69: 4188 | I69: 48955.21 | J69: 48955.21 | K69: OD
A70: MBPSI2405018 | C70: 45443 | D70: AUTO RAYA TIMUR SDN BHD | E70: CEV7882 | F70: MBPWO2405016 | G70: 1603.02 | H70: 276 | I70: 1879.02 | J70: 1879.02 | K70: WS
A71: MBPSI2405019 | C71: 45443 | D71: AUTO RAYA TIMUR SDN BHD | E71: WC1588B | F71: MBPWO2405022 | G71: 60 | I71: 60 | J71: 60 | K71: CR | L71: CREDIT
A72: MBPSI2406001 | B72: JUNE | C72: 45444 | D72: AUTO RAYA TIMUR SDN BHD | E72: CEV8030 | F72: MBPWO2405015 | G72: 4062.59 | H72: 2124 | I72: 6186.59 | J72: 6186.59 | K72: OD
A73: MBPSI2406002 | C73: 45444 | D73: AUTO RAYA TIMUR SDN BHD | E73: VKR1273 | F73: MBPWO2405019 | G73: 5969.73 | H73: 1740 | I73: 7709.73 | J73: 7709.73 | K73: OD
A74: MBPSI2406003 | C74: 45444 | D74: AUTO RAYA TIMUR SDN BHD | E74: VHL7999 | F74: MBPWO2405011 | G74: 2038.91 | H74: 2616 | I74: 4654.91 | J74: 4654.91 | K74: OD
A75: MBPSI2406004 | B75: JUNE | C75: 45451 | D75: AUTO RAYA TIMUR SDN BHD | E75: VEQ8560 | F75: MBPWO2405005 | G75: 2404.2 | H75: 252 | I75: 2656.2 | J75: 2656.2 | K75: WS
A76: MBPSI2406005 | C76: 45457 | D76: AUTO RAYA TIMUR SDN BHD | E76: SB3611H | F76: MBPWO2406004 | G76: 190.65 | H76: 120 | I76: 310.65 | J76: 310.65 | K76: WS
A77: MBPSI2406006 | C77: 45462 | D77: AUTO RAYA TIMUR SDN BHD | E77: QRT1391 | F77: MBPWO2406002 | G77: 1603.02 | H77: 276 | I77: 1879.02 | J77: 1879.02 | K77: WS
A78: MBPSI2406007 | C78: 45469 | D78: AUTO RAYA TIMUR SDN BHD | E78: PQU977 | F78: MBPWO2406009 | G78: 2116.76 | H78: 240 | I78: 2356.76 | J78: 2356.76 | K78: WS
A79: MBPSI2406008 | C79: 45470 | D79: AUTO RAYA TIMUR SDN BHD | E79: BRL1188 | F79: MBPWO2406003 | G79: 2428.02 | H79: 276 | I79: 2704.02 | J79: 2704.02 | K79: WS
A80: MBPSI2406009 | C80: 45470 | D80: TAN KIAT HUAT | E80: FE8298 | F80: MBPWO2406011 | G80: 349.5 | H80: 1179.36 | I80: 1528.86 | J80: 1528.86 | K80: OD | L80: CASH
A81: MBPSI2406010 | C81: 45470 | D81: AUTO RAYA TIMUR SDN BHD | E81: FE8298 | F81: MBPWO2405009 | G81: 23069.15 | H81: 6912 | I81: 29981.15 | J81: 29981.15 | K81: OD
A82: MBPSI2406011 | C82: 45470 | D82: AUTO RAYA TIMUR SDN BHD | E82: VGD4608 | F82: MBPWO2404017 | G82: 30933.13 | H82: 4680 | I82: 35613.13 | J82: 35613.13 | K82: OD
A83: MBPSI2407001 | B83: JULY | C83: 45482 | D83: AUTO RAYA TIMUR SDN BHD | E83: JUE9323 | F83: MBPWO2405020 | G83: 12698.71 | H83: 6060 | I83: 18758.71 | J83: 18758.71 | K83: OD
A84: MBPSI2407002 | C84: 45475 | D84: AUTO RAYA TIMUR SDN BHD | E84: CDS5872 | F84: MBPWO2404006 | G84: 12873.75 | H84: 4512 | I84: 17385.75 | J84: 17385.75 | K84: OD
A85: MBPSI2407003 | C85: 45477 | D85: AUTO RAYA TIMUR SDN BHD | E85: KFD7811 | F85: MBPWO2406007 | G85: 4499.32 | H85: 1776 | I85: 6275.32 | J85: 6275.32 | K85: OD
A86: MBPSI2407004 | C86: 45477 | D86: AUTO RAYA TIMUR SDN BHD | E86: SD1242W | F86: MBPWO2405021 | G86: 27652.45 | H86: 4620 | I86: 32272.45 | J86: 32272.45 | K86: OD
A87: MBPSI2407005 | C87: 45478 | D87: AUTO RAYA TIMUR SDN BHD | E87: CET8981 | F87: MBPWO2402008 | G87: 42314.69 | H87: 10800 | I87: 53114.69 | J87: 53114.69 | K87: OD
A88: MBPSI2407006 | B88: JULY | C88: 45484 | D88: AUTO RAYA TIMUR SDN BHD | E88: BRE5839 | F88: MBPWO2407004 | G88: 126.05 | H88: 120 | I88: 246.05 | J88: 246.05 | K88: WS
A89: MBPSI2407007 | C89: 45489 | D89: AUTO RAYA TIMUR SDN BHD | E89: BPV6531 | F89: MBPWO2406006 | G89: 10611.41 | H89: 1371 | I89: 11982.41 | J89: 11982.41 | K89: OD
A90: MBPSI2407008 | C90: 45491 | D90: MARZUKI BIN MOHAMAD | E90: JUK1169 | F90: MBPWO2407010 | G90: 580 | I90: 580 | J90: 580 | K90: WS
A91: MBPSI2407009 | C91: 45491 | D91: AUTO RAYA TIMUR SDN BHD | E91: CEV3938 | F91: MBPWO2406013 | G91: 14719.05 | H91: 2952 | I91: 17671.05 | J91: 17671.05 | K91: OD
A92: MBPSI2407010 | C92: 45492 | D92: AUTO RAYA TIMUR SDN BHD | E92: CET1019 | F92: MBPWO2407007 | G92: 1871 | H92: 276 | I92: 2147 | J92: 2147 | K92: WS
A93: MBPSI2407011 | C93: 45496 | D93: AUTO RAYA TIMUR SDN BHD | E93: VGS8456 | F93: MBPWO2401004 | G93: 25409 | H93: 7176 | I93: 32585 | J93: 32585 | K93: OD
A94: MBPSI2407012 | C94: 45496 | D94: AUTO RAYA TIMUR SDN BHD | E94: JUK1169 | F94: MBPWO2407009 | G94: 1128.02 | H94: 276 | I94: 1404.02 | J94: 1404.02 | K94: WS
A95: MBPSI2407013 | C95: 45497 | D95: AUTO RAYA TIMUR SDN BHD | E95: VHV6971 | F95: MBPWO2407001 | G95: 11459.27 | H95: 2172 | I95: 13631.27 | J95: 13631.27 | K95: OD
A96: MBPSI2407014 | C96: 45498 | D96: AUTO RAYA TIMUR SDN BHD | E96: MDR1242 | F96: MBPWO2407012 | G96: 3066.76 | H96: 240 | I96: 3306.76 | J96: 3306.76 | K96: WS
A97: MBPSI2408001 | C97: 45505 | D97: AUTO RAYA TIMUR SDN BHD | E97: 40379 | F97: MBPWO2407013 | G97: 903.95 | H97: 180 | I97: 1083.95 | J97: 1083.95 | K97: CR | L97: CREDIT
A98: MBPSI2408002 | C98: 45505 | D98: AUTO RAYA TIMUR SDN BHD | E98: 39826 | F98: MBPWO2407011 | G98: 3435.44 | H98: 1692 | I98: 5127.44 | J98: 5127.44 | K98: CR | L98: CREDIT
A99: MBPSI2408003 | C99: 45506 | D99: KAVI MANI A/L KESAVAN | E99: VHX1188 | F99: MBPWO2407018 | H99: 300 | I99: 300 | J99: 300 | K99: CR | L99: CASH
A100: MBPSI2408004 | B100: AUG | C100: 45509 | D100: AUTO RAYA TIMUR SDN BHD | E100: VHX1188 | F100: MBPWO2405018 | G100: 8597.15 | H100: 4548 | I100: 13145.15 | J100: 13145.15 | K100: OD
...

Sheet HINO 2024
A1: TRANSNO | C1: DATE | D1: CUSTOMER NAME | E1: REG NO | F1: JOBNO | G1: P.TOTAL | H1: L.TOTAL | I1: GTOTAL | J1: DISC. | K1: TOTAL | L1: SVC TYPE | M1: SVC TYPE
A2: HBPSI2401001 | B2: JAN | C2: 45296 | D2: EDARAN RIZ SDN BHD | E2: VGS7608 | F2: HBPWO2311003 | G2: 24280.29 | H2: 13560 | I2: 37840.29 | K2: 37840.29 | L2: OD
A3: HBPSI2401002 | B3: JAN | C3: 45321 | D3: EDARAN RIZ SDN BHD | E3: VLB4149 | F3: HBPWO2312001 | G3: 30485.3 | H3: 7620 | I3: 38105.3 | K3: 38105.3 | L3: OD
A4: HBPSI2401003 | B4: JAN | C4: 45322 | D4: EDARAN RIZ SDN BHD | E4: CDF7298 | F4: HBPWO2401001 | G4: 696.06 | H4: 420 | I4: 1116.06 | K4: 1116.06 | L4: WS
A5: HBPSI2402001 | B5: FEB | C5: 45341 | D5: EDARAN RIZ SDN BHD | E5: BMN4706 | F5: HBPWO2311002 | G5: 53446.25 | H5: 6000 | I5: 59446.25 | K5: 59446.25 | L5: OD
A6: HBPSI2402002 | B6: FEB | C6: 45343 | D6: EDARAN RIZ SDN BHD | E6: CEA6128 | F6: HBPWO2402001 | G6: 506.06 | H6: 420 | I6: 926.06 | K6: 926.06 | L6: WS
A7: HBPSI2403001 | B7: MAR | C7: 45359 | D7: EDARAN RIZ SDN BHD | E7: KEM6686 | F7: HBPWO2403001 | G7: 688.08 | H7: 420 | I7: 1108.08 | K7: 1108.08 | L7: WS
A8: HBPSI2404001 | B8: APR | C8: 45383 | D8: EDARAN RIZ SDN BHD | E8: VHT4642 | F8: HBPWO2403005 | G8: 973.08 | H8: 420 | I8: 1393.08 | K8: 1393.08 | L8: WS
A9: HBPSI2404002 | B9: APR | C9: 45386 | D9: EDARAN RIZ SDN BHD | E9: SWE6668 | F9: HBPWO2403004 | G9: 786.03 | H9: 420 | I9: 1206.03 | K9: 1206.03 | L9: WS
A10: HBPSI2404003 | B10: APR | C10: 45399 | D10: EDARAN RIZ SDN BHD | E10: T/N2206 | F10: HBPWO2403002 | G10: 1390.48 | I10: 1390.48 | K10: 1390.48 | L10: OD
A11: HBPSI2404004 | B11: APR | C11: 45399 | D11: EDARAN RIZ SDN BHD | E11: CDJ7715 | F11: HBPWO2402002 | G11: 14056.65 | H11: 5616 | I11: 19672.65 | K11: 19672.65 | L11: OD
A12: HBPSI2405001 | B12: MAY | C12: 45418 | D12: EDARAN RIZ SDN BHD | E12: VHU1133 | F12: HBPWO2402003 | G12: 27624.85 | H12: 4008 | I12: 31632.85 | K12: 31632.85 | L12: OD
A13: HBPSI2405002 | B13: MAY | C13: 45422 | D13: EDARAN RIZ SDN BHD | E13: BKM5452 | F13: HBPWO2405001 | G13: 433.52 | H13: 480 | I13: 913.52 | K13: 913.52 | L13: WS
A14: HBPSI2405003 | B14: MAY | C14: 45422 | D14: EDARAN RIZ SDN BHD | E14: BKN3892 | F14: HBPWO2405002 | G14: 433.52 | H14: 480 | I14: 913.52 | K14: 913.52 | L14: WS
A15: HBPSI2405004 | B15: MAY | C15: 45433 | D15: EDARAN RIZ SDN BHD | E15: PPS6686 | F15: HBPWO2404004 | G15: 6559.5 | H15: 2760 | I15: 9319.5 | K15: 9319.5 | L15: OD
A16: HBPSI2405005 | B16: MAY | C16: 45442 | D16: EDARAN RIZ SDN BHD | E16: PNW3866 | F16: HBPWO2405007 | G16: 718.52 | H16: 480 | I16: 1198.52 | K16: 1198.52 | L16: WS
A17: HBPSI2406001 | B17: JUNE | C17: 45449 | D17: EDARAN RIZ SDN BHD | E17: CEQ8209 | F17: HBPWO2404003 | G17: 7073.27 | H17: 2280 | I17: 9353.27 | K17: 9353.27 | L17: OD
A18: HBPSI2406002 | B18: JUNE | C18: 45456 | D18: EDARAN RIZ SDN BHD | E18: MDP5398 | F18: HBPWO2404001 | G18: 22112.87 | H18: 3720 | I18: 25832.87 | K18: 25832.87 | L18: OD
A19: HBPSI2406003 | B19: JUNE | C19: 45458 | D19: EDARAN RIZ SDN BHD | E19: WA6461G | F19: HBPWO2405003 | G19: 5568.44 | H19: 3120 | I19: 8688.44 | K19: 8688.44 | L19: OD
A20: HBPSI2406004 | B20: JUNE | C20: 45461 | D20: EDARAN RIZ SDN BHD | E20: CEP6209 | F20: HBPWO2406002 | G20: 973.08 | H20: 420 | I20: 1393.08 | K20: 1393.08 | L20: WS
A21: HBPSI2406005 | B21: JUNE | C21: 45468 | D21: EDARAN RIZ SDN BHD | E21: QBG8589 | F21: HBPWO2404002 | G21: 55226.49 | H21: 8700 | I21: 63926.49 | K21: 63926.49 | L21: OD
A22: HBPSI2406006 | B22: JUNE | C22: 45472 | D22: EDARAN RIZ SDN BHD | E22: VGK9635 | F22: HBPWO2406004 | H22: 908.2 | I22: 908.2 | K22: 908.2 | M22: FUSO INVOICE
A23: HBPSI2406007 | B23: JUNE | C23: 45472 | D23: EDARAN RIZ SDN BHD | E23: VGK8942 | F23: HBPWO2406005 | H23: 240 | I23: 240 | K23: 240 | M23: FUSO INVOICE
A24: HBPSI2406008 | B24: JUNE | C24: 45472 | D24: EDARAN RIZ SDN BHD | E24: VGU7551 | F24: HBPWO2406006 | H24: 240 | I24: 240 | K24: 240 | M24: FUSO INVOICE
A25: HBPSI2406009 | B25: JUNE | C25: 45472 | D25: EDARAN RIZ SDN BHD | E25: VGW6873 | F25: HBPWO2406007 | H25: 240 | I25: 240 | K25: 240 | M25: FUSO INVOICE
A26: HBPSI2406010 | B26: JUNE | C26: 45472 | D26: EDARAN RIZ SDN BHD | E26: VGS7608 | F26: HBPWO2406008 | H26: 240 | I26: 240 | K26: 240 | M26: FUSO INVOICE
A27: HBPSI2406011 | B27: JUNE | C27: 45472 | D27: EDARAN RIZ SDN BHD | E27: VGT3790 | F27: HBPWO2406009 | H27: 320 | I27: 320 | K27: 320 | M27: FUSO INVOICE
A28: HBPSI2406012 | B28: JUNE | C28: 45472 | D28: EDARAN RIZ SDN BHD | E28: VGN2843 | F28: HBPWO2406010 | H28: 320 | I28: 320 | K28: 320 | M28: FUSO INVOICE
A29: HBPSI2406013 | B29: JUNE | C29: 45472 | D29: EDARAN RIZ SDN BHD | E29: VGL7449 | F29: HBPWO2406011 | H29: 240 | I29: 240 | K29: 240 | M29: FUSO INVOICE
A30: HBPSI2407001 | B30: JULY | C30: 45474 | D30: EDARAN RIZ SDN BHD | E30: JPL5999 | F30: HBPWO2405004 | G30: 11018.99 | H30: 11100 | I30: 22118.99 | K30: 22118.99 | L30: OD
A31: HBPSI2407002 & HBPSI2407004 | B31: JULY | C31: 45478 | D31: EDARAN RIZ SDN BHD | E31: TCK3019 | F31: HBPWO2405008 | G31: 16499.45 | H31: 3000 | I31: 19499.45 | K31: 19499.45 | L31: OD
A32: HBPSI2407003 | B32: JULY | C32: 45489 | D32: OM SRI RAJAH TRADING | E32: QBG8589 | F32: HBPWO2406013 | G32: 3000 | I32: 1750 | J32: 1250 | K32: 1750 | L32: CR
A33: HBPSI2407005 | B33: JULY | C33: 45489 | D33: SHIKH ENTERPRISE | E33: TBX7589 | F33: HBPWO2407004 | G33: 1600 | I33: 1600 | K33: 1600 | L33: CR
A34: HBPSI2407006 | B34: JULY | C34: 45490 | D34: EDARAN RIZ SDN BHD | E34: TBX7589 | F34: HBPWO2405006 | G34: 34108.88 | H34: 4140 | I34: 38248.88 | K34: 38248.88 | L34: OD
A35: HBPSI2407007 | B35: JULY | C35: 45498 | D35: EDARAN RIZ SDN BHD | E35: VGK9635 | F35: HBPWO2407007 | H35: 1912.4 | I35: 1912.4 | K35: 1912.4 | M35: FUSO INVOICE
A36: HBPSI2407008 | B36: JULY | C36: 45498 | D36: EDARAN RIZ SDN BHD | E36: VGN2843 | F36: HBPWO2407008 | H36: 776 | I36: 776 | K36: 776 | M36: FUSO INVOICE
A37: HBPSI2407009 | B37: JULY | C37: 45497 | D37: EDARAN RIZ SDN BHD | E37: VDR7724 | F37: HBPWO2405005 | G37: 39832.73 | H37: 6708 | I37: 46540.73 | K37: 46540.73 | L37: OD
A38: HBPSI2408001 | B38: AUG | C38: 45528 | D38: EDARAN RIZ SDN BHD | E38: JVW2403 | F38: HBPWO2406001 | G38: 39559.6 | H38: 7800 | I38: 47359.6 | K38: 47359.6 | L38: OD
A39: HBPSI2408002 | B39: AUG | C39: 45534 | D39: EDARAN RIZ SDN BHD | E39: WYN442 | F39: HBPWO2407002 | G39: 12384.2 | H39: 3612 | I39: 15996.2 | K39: 15996.2 | L39: OD
A40: HBPSI2409001 | B40: SEP | C40: 45545 | D40: EDARAN RIZ SDN BHD | E40: KEY2569 | F40: HBPWO2407005 | G40: 28810.72 | H40: 8880 | I40: 37690.72 | K40: 37690.72 | L40: OD
A41: HBPSI2409002 | B41: SEP | C41: 45554 | D41: EDARAN RIZ SDN BHD | E41: TCW7101 | F41: HBPWO2408002 | G41: 9470.31 | H41: 2196 | I41: 11666.31 | K41: 11666.31 | L41: OD
A42: HBPSI2409003 | B42: SEP | C42: 45555 | D42: EDARAN RIZ SDN BHD | E42: MDW8893 | F42: HBPWO2408001 | G42: 10486.84 | H42: 2268 | I42: 12754.84 | K42: 12754.84 | L42: OD
A43: HBPSI2409004 | B43: SEP | C43: 45560 | D43: EDARAN RIZ SDN BHD | E43: VHY5222 | F43: HBPWO2408003 | G43: 18654.28 | H43: 4344 | I43: 22998.28 | K43: 22998.28 | L43: OD
A44: HBPSI2410001 | B44: OCT | C44: 45566 | D44: EDARAN RIZ SDN BHD | E44: SWE6668 | F44: HBPWO2409003 | G44: 973.08 | H44: 420 | I44: 1393.08 | K44: 1393.08 | L44: WS
A45: HBPSI2410002 | B45: OCT | C45: 45594 | D45: EDARAN RIZ SDN BHD | E45: SK8018D | F45: HBPWO2409002 | G45: 6402.5 | H45: 4380 | I45: 10782.5 | K45: 10782.5 | L45: OD
A46: HBPSI2411001 | B46: NOV | C46: 45604 | D46: EDARAN RIZ SDN BHD | E46: VBN9692 | F46: HBPWO2410003 | G46: 9898.33 | H46: 3540 | I46: 13438.33 | K46: 13438.33 | L46: OD
A47: HBPSI2411002 | B47: NOV | C47: 45612 | D47: EDARAN RIZ SDN BHD | E47: JXC3652 | F47: HBPWO2409001 | G47: 73054.52 | H47: 7080 | I47: 80134.52 | K47: 80134.52 | L47: OD
A48: HBPSI2411003 | B48: NOV | C48: 45625 | D48: EDARAN RIZ SDN BHD | E48: VGN2843 | F48: HBPWO2411002 | H48: 392 | I48: 392 | K48: 392 | L48: CANCEL
A49: HBPSI2411004 | B49: NOV | C49: 45625 | D49: EDARAN RIZ SDN BHD | E49: VGK9635 | F49: HBPWO2411003 | H49: 472 | I49: 472 | K49: 472 | L49: CANCEL
A50: HBPSI2411005 | B50: NOV | C50: 45625 | D50: EDARAN RIZ SDN BHD | E50: VGL7449 | F50: HBPWO2411004 | H50: 240 | I50: 240 | K50: 240 | L50: CANCEL
A51: HBPSI2411006 | B51: NOV | C51: 45625 | D51: EDARAN RIZ SDN BHD | E51: VGU7551 | F51: HBPWO2411005 | H51: 320 | I51: 320 | K51: 320 | L51: CANCEL
A52: HBPSI2411007 | B52: NOV | C52: 45625 | D52: EDARAN RIZ SDN BHD | E52: VGK8942 | F52: HBPWO2411006 | H52: 320 | I52: 320 | K52: 320 | L52: CANCEL
A53: HBPSI2411008 | B53: NOV | C53: 45625 | D53: EDARAN RIZ SDN BHD | E53: VGS7608 | F53: HBPWO2411007 | H53: 320 | I53: 320 | K53: 320 | L53: CANCEL
A54: HBPSI2411009 | B54: NOV | C54: 45625 | D54: EDARAN RIZ SDN BHD | E54: VGT3790 | F54: HBPWO2411008 | H54: 656 | I54: 656 | K54: 656 | L54: CANCEL
A55: HBPSI2411010 | B55: NOV | C55: 45625 | D55: EDARAN RIZ SDN BHD | E55: VGW6873 | F55: HBPWO2411009 | H55: 736 | I55: 736 | K55: 736 | L55: CANCEL
A56: HBPSI2412001 | B56: DEC | C56: 45637 | D56: EDARAN RIZ SDN BHD | E56: SYU1218 | F56: HBPWO2412001 | G56: 973.08 | H56: 420 | I56: 1393.08 | K56: 1393.08 | L56: WS
A57: HBPSI2412002 | B57: DEC | C57: 45637 | D57: EDARAN RIZ SDN BHD | E57: CEA8396 | F57: HBPWO2411001 | G57: 1045.01 | H57: 262.2 | I57: 1307.21 | K57: 1307.21 | L57: OD
A58: HBPSI2412003 | B58: DEC | C58: 45657 | D58: EDARAN RIZ SDN BHD | E58: VGW6873 | F58: HBPWO2412005 | G58: 68.06 | H58: 64 | I58: 132.06 | K58: 132.06 | M58: FUSO INVOICE
A59: HBPSI2412004 | B59: DEC | C59: 45657 | D59: EDARAN RIZ SDN BHD | E59: VGK8942 | F59: HBPWO2412006 | G59: 338.64 | H59: 64 | I59: 402.64 | K59: 402.64 | M59: FUSO INVOICE
A60: HBPSI2412005 | B60: DEC | C60: 45657 | D60: EDARAN RIZ SDN BHD | E60: VGK9635 | F60: HBPWO2412007 | G60: 760.28 | H60: 64 | I60: 824.28 | K60: 824.28 | M60: FUSO INVOICE
A61: HBPSI2412006 | B61: DEC | C61: 45657 | D61: EDARAN RIZ SDN BHD | E61: VGS7608 | F61: HBPWO2412008 | G61: 76.36 | H61: 64 | I61: 140.36 | K61: 140.36 | M61: FUSO INVOICE
A62: HBPSI2412007 | B62: DEC | C62: 45657 | D62: EDARAN RIZ SDN BHD | E62: VGU7551 | F62: HBPWO2412009 | G62: 380.14 | H62: 64 | I62: 444.14 | K62: 444.14 | M62: FUSO INVOICE
A63: HBPSI2412008 | B63: DEC | C63: 45657 | D63: EDARAN RIZ SDN BHD | E63: VGT3790 | F63: HBPWO2412010 | G63: 730.4 | H63: 64 | I63: 794.4 | K63: 794.4 | M63: FUSO INVOICE
A64: HBPSI2412009 | B64: DEC | C64: 45657 | D64: EDARAN RIZ SDN BHD | E64: VGL7449 | F64: HBPWO2412011 | G64: 29.88 | H64: 64 | I64: 93.88 | K64: 93.88 | M64: FUSO INVOICE
A65: HBPSI2412010 | B65: DEC | C65: 45657 | D65: EDARAN RIZ SDN BHD | E65: VGL7449 | F65: HBPWO2412013 | H65: 1168 | I65: 1168 | K65: 1168 | M65: FUSO INVOICE
K67: =SUM(K2:K66) -> 714941.42 | L67: =K67-SUM(K22:K29,K35:K36,K48:K55,K58:K65) -> 702049.06
A73: INVOICE LISTING
A74: TRANSNO | B74: MONTH | C74: DATE | D74: CUSTOMER NAME | E74: REFERENCE | F74: TOTAL | G74: G.TOTAL | H74: SVC TYPE
A75: HBPIV2401001 | B75: JAN | C75: 45301 | D75: EDARAN RIZ SDN BHD | E75: HBPWO2312001 | F75: 6366.9 | G75: 6366.9 | H75: OD
A76: HBPIV2401005 | B76: JAN | C76: 45322 | D76: AUTO RAYA SDN BHD | E76: STAFF USE | F76: 0 | G76: 0
A77: HBPIV2404001 | B77: APR | C77: 45385 | D77: EDARAN RIZ SDN BHD | E77: CDJ7715 | F77: 5700 | G77: 5700 | H77: OD
A78: HBPIV2405003 | B78: MAY | C78: 45425 | D78: EDARAN RIZ SDN BHD | E78: WA6461G, XZU411-0006994 | F78: 912 | G78: 912 | H78: OD
A79: HBPIV2406001 | B79: JUNE | C79: 45463 | D79: EDARAN RIZ SDN BHD | E79: BRA7133 | F79: 950 | G79: 950 | H79: OD
A80: HBPIV2406002 | B80: JUNE | C80: 45463 | D80: EDARAN RIZ SDN BHD | E80: VEL5937 | F80: 950 | G80: 950 | H80: OD
A81: HBPIV2406003 | B81: JUNE | C81: 45467 | D81: EDARAN RIZ SDN BHD | E81: TCK3019 | F81: 9500 | G81: 9500 | H81: OD
A82: HBPIV2407001 | B82: JULY | C82: 45498 | D82: EDARAN RIZ SDN BHD | E82: BRA7133 | F82: 237.5 | G82: 237.5 | H82: OD
A83: HBPIV2408001 | B83: AUG | C83: 45510 | D83: EDARAN RIZ SDN BHD | E83: NDW5114 | F83: 3469 | G83: 3469 | H83: OD
A84: HBPIV2408002 | B84: AUG | C84: 45510 | D84: EDARAN RIZ SDN BHD | E84: VEL5937 | F84: 1960 | G84: 1960 | H84: OD
A85: HBPIV2408003 | B85: AUG | C85: 45518 | D85: EDARAN RIZ SDN BHD | E85: NDW5114 | F85: 3591 | G85: 3591 | H85: OD
A86: HBPIV2408004 | B86: AUG | C86: 45533 | D86: EDARAN RIZ SDN BHD | E86: NDP2721 | F86: 1900 | G86: 1900 | H86: OD
A87: HBPIV2408005 | B87: AUG | C87: 45533 | D87: EDARAN RIZ SDN BHD | E87: NDP2721 | F87: 750 | G87: 750 | H87: OD
A88: HBPIV2409001 | B88: SEP | C88: 45541 | D88: EDARAN RIZ SDN BHD | E88: BNM8561 | F88: 4562 | G88: 4562 | H88: OD
A89: HBPIV2403001 | B89: MAR | C89: 45363 | D89: AUTO RAYA SDN BHD | E89: TSHIRT WITHDRAWAL | F89: 0 | G89: 0
A90: HBPIV2403002 | B90: MAR | C90: 45363 | D90: AUTO RAYA SDN BHD | E90: TSHIRT WITHDRAWAL | F90: 0 | G90: 0
A91: HBPIV2403003 | B91: MAR | C91: 45363 | D91: AUTO RAYA SDN BHD | E91: TSHIRT WITHDRAWAL | F91: 0 | G91: 0
A92: HBPIV2403004 | B92: MAR | C92: 45363 | D92: AUTO RAYA SDN BHD | E92: TSHIRT WITHDRAWAL | F92: 0 | G92: 0
A93: HBPIV2403005 | B93: MAR | C93: 45363 | D93: AUTO RAYA SDN BHD | E93: TSHIRT WITHDRAWAL | F93: 0 | G93: 0
A94: HBPIV2403006 | B94: MAR | C94: 45363 | D94: AUTO RAYA SDN BHD | E94: TSHIRT WITHDRAWAL | F94: 0 | G94: 0
A95: HBPIV2403007 | B95: MAR | C95: 45363 | D95: AUTO RAYA SDN BHD | E95: TSHIRT WITHDRAWAL | F95: 0 | G95: 0
A96: HBPIV2405001 | B96: MAY | C96: 45420 | D96: AUTO RAYA SDN BHD | E96: TSHIRT WITHDRAWAL | F96: 0 | G96: 0
A97: HBPIV2405002 | B97: MAY | C97: 45420 | D97: AUTO RAYA SDN BHD | E97: TSHIRT WITHDRAWAL | F97: 0 | G97: 0
A98: HBPIV2410001 | B98: OCT | C98: 45574 | D98: EDARAN RIZ SDN BHD | E98: BRA7133 | F98: 3277.5 | G98: 3277.5 | H98: OD
A99: HBPIV2411001 | B99: NOV | C99: 45600 | D99: EDARAN RIZ SDN BHD | E99: TCK3019 | F99: 8521.26 | G99: 8521.26 | H99: OD
A100: HBPIV2412001 | B100: DEC | C100: 45657 | D100: EDARAN RIZ SDN BHD | E100: NDS8129 | F100: 2090 | G100: 2090 | H100: OD
A101: HBPIV2401002 | B101: JAN | C101: 45302 | D101: AUTO RAYA SDN BHD | E101: GIFT | F101: 0 | G101: 0
A102: HBPIV2401003 | B102: JAN | C102: 45307 | D102: AUTO RAYA SDN BHD | E102: GIFT | F102: 0 | G102: 0
A103: HBPIV2401004 | B103: JAN | C103: 45317 | D103: AUTO RAYA SDN BHD | E103: STAFF USE | F103: 0 | G103: 0
G105: =SUM(G75:G104) -> 54737.16

Sheet FUSO 2024
A1: TRANSNO | B1: MONTH | C1: DATE | D1: CUSTOMER NAME | E1: REG NO | F1: JOBNO | G1: P.TOTAL | H1: L.TOTAL | I1: GTOTAL | J1: RD | K1: TOTAL
A2: FASSI2401001 | B2: JAN | C2: 45304 | D2: LCH TRANSPORT & SERVICE SDN BHD | E2: VKP8555 | F2: FASWO2401001 | I2: 0 | J2: 0 | K2: 0
A3: FASSI2401002 | B3: JAN | C3: 45306 | D3: FU SHENG TRADING | E3: CDE2118 | F3: FASWO2401002 | G3: 789.67 | H3: 240 | I3: 1029.67 | J3: 0 | K3: 1029.67 | L3: CASH
A4: FASSI2401003 | B4: JAN | C4: 45311 | D4: LHL MARKETING | E4: AMR3233 | F4: FASWO2401003 | G4: 304.97 | H4: 114 | I4: 419 | J4: 0.03 | K4: 419 | L4: CASH
A5: FASSI2403001 | B5: MAR | C5: 45352 | D5: FU SHENG TRADING | E5: UKM 2118 | F5: FASWO2402001 | I5: 0 | J5: 0 | K5: 0
A6: FASSI2403002 | B6: MAR | C6: 45359 | D6: REDHA CONSTRUCTIONS | E6: BRM1186 | F6: FASWO2403001 | I6: 0 | J6: 0 | K6: 0
A7: FASSI2403003 | B7: MAR | C7: 45359 | D7: ENG GUAN AGRICULTURE SDN BHD | E7: NDV7169 | F7: FASWO2403002 | I7: 0 | J7: 0 | K7: 0
A8: FASSI2403004 | B8: MAR | C8: 45371 | D8: LCH TRANSPORT & SERVICE SDN BHD | E8: VKP8555 | F8: FASWO2403003 | I8: 0 | J8: 0 | K8: 0
A9: FASSI2403005 | B9: MAR | C9: 45381 | D9: ENG GUAN AGRICULTURE SDN BHD | E9: NDV7169 | F9: FASWO2403006 | G9: 848 | H9: 243 | I9: 1091 | J9: 0 | K9: 1091 | L9: CASH
A10: FASSI2404001 | B10: APR | C10: 45407 | D10: FM GLOBAL LOGISTICS (M) SDN BHD | E10: VHS9530 | F10: FASWO2404001 | G10: 124.5 | H10: 863.8 | I10: 988.3 | J10: 0 | K10: 988.3 | L10: CASH
A11: FASSI2404002 | B11: APR | C11: 45409 | D11: ASMAWI CONSTRUCTION | E11: VLW3392 | F11: FASWO2404002 | I11: 0 | J11: 0 | K11: 0
A12: FASSI2404003 | B12: APR | C12: 45409 | D12: H&M TRANSPORT | E12: RAT9186 | F12: FASWO2403005 | I12: 0 | J12: 0 | K12: 0
A13: FASSI2404004 | B13: APR | C13: 45411 | D13: ENG GUAN AGRICULTURE SDN BHD | E13: NDV7169 | F13: FASWO2404003 | I13: 0 | J13: 0 | K13: 0
A14: FASSI2405001 | B14: MAY | C14: 45440 | D14: H&M TRANSPORT | E14: RAT9186 | F14: FASWO2405001 | I14: 0 | J14: 0 | K14: 0
A15: FASSI2405002 | B15: MAY | C15: 45440 | D15: H&M TRANSPORT | E15: RAT9186 | F15: FASWO2405002 | I15: 0 | J15: 0 | K15: 0
A16: FASSI2406001 | B16: JUNE | C16: 45467 | D16: GOH PENG LENG | E16: PPL7533 | F16: FASWO2406004 | G16: 433.59 | H16: 181.44 | I16: 615 | J16: -0.03 | K16: 615 | L16: CASH
A17: FASSI2406002 | B17: JUNE | C17: 45444 | D17: REDHA CONSTRUCTIONS | E17: BRM1186 | F17: FASWO2406001 | I17: 0 | J17: 0 | K17: 0
A18: FASSI2406003 | B18: JUNE | C18: 45471 | D18: LCH TRANSPORT & SERVICE SDN BHD | E18: VKP8555 | F18: FASWO2406002 | I18: 0 | J18: 0 | K18: 0
A19: FASSI2406004 | B19: JUNE | C19: 45455 | D19: FU SHENG TRADING | E19: UKM 2118 | F19: FASWO2406003 | I19: 0 | J19: 0 | K19: 0
A20: FASSI2406005 | B20: JUNE | C20: 45469 | D20: MOHD RODZUAN BIN BEDOLLAH | E20: MDR5421 | F20: FASWO2406005 | I20: 0 | J20: 0 | K20: 0
A21: FASSI2407001 | B21: JULY | C21: 45488 | D21: YPF SAWIT TRADING | E21: JWC1993 | F21: FASWO2407001 | I21: 0 | J21: 0 | K21: 0
A22: FASSI2407002 | B22: JULY | C22: 45499 | D22: KENASAN TRADINGS | E22: SK5448E | F22: FASWO2407002 | I22: 0 | J22: 0 | K22: 0
A23: FASSI2409001 | B23: SEP | C23: 45537 | D23: REDHA CONSTRUCTIONS | E23: BRM1186 | F23: FASWO2409001 | I23: 0 | J23: 0 | K23: 0
A24: FASSI2409002 | B24: SEP | C24: 45539 | D24: H&M TRANSPORT | E24: RAT9186 | F24: FASWO2409002 | I24: 0 | J24: 0 | K24: 0
A25: FASSI2409003 | B25: SEP | C25: 45558 | D25: ENG GUAN AGRICULTURE SDN BHD | E25: NDV7169 | F25: FASWO2409003 | I25: 0 | J25: 0 | K25: 0
A26: FASSI2409004 | B26: SEP | C26: 45565 | D26: EDARAN RIZ SDN BHD | E26: 7018327 | F26: FASWO2409006 | G26: 407.55 | H26: 1300 | I26: 1707.55 | J26: 0 | K26: 1707.55 | L26: CASH
A27: FASSI2410001 | B27: OCT | C27: 45579 | D27: GOH PENG LENG | E27: PPL7533 | F27: FASWO2410001 | I27: 0 | J27: 0 | K27: 0
A28: FASSI2410002 | B28: OCT | C28: 45593 | D28: GOH PENG LENG | E28: PPL7533 | F28: FASWO2410003 | G28: 321.31 | H28: 280 | I28: 601.3 | J28: -0.01 | K28: 601.3 | L28: CASH
A29: FASSI2411001 | B29: NOV | C29: 45603 | D29: ASMAWI CONSTRUCTION | E29: VLW3392 | F29: FASWO2411001 | I29: 0 | J29: 0 | K29: 0
A30: FASSI2411002 | B30: NOV | C30: 45612 | D30: KENASAN TRADINGS | E30: SK5448E | F30: FASWO2411002 | I30: 0 | J30: 0 | K30: 0
A31: FASSI2411003 | B31: NOV | C31: 45625 | D31: MOHD RODZUAN BIN BEDOLLAH | E31: MDR5421 | F31: FASWO2411003 | I31: 0 | J31: 0 | K31: 0
A32: FASSI2411004 | B32: NOV | C32: 45625 | D32: EDARAN RIZ SDN BHD | E32: VGT3790 | F32: FASWO2411004 | H32: 656 | I32: 656 | J32: 0 | K32: 656 | L32: INV
A33: FASSI2411005 | B33: NOV | C33: 45625 | D33: EDARAN RIZ SDN BHD | E33: VGW6873 | F33: FASWO2411005 | H33: 736 | I33: 736 | J33: 0 | K33: 736 | L33: INV
A34: FASSI2411006 | B34: NOV | C34: 45625 | D34: EDARAN RIZ SDN BHD | E34: VGS7608 | F34: FASWO2411006 | H34: 320 | I34: 320 | J34: 0 | K34: 320 | L34: INV
A35: FASSI2411007 | B35: NOV | C35: 45625 | D35: EDARAN RIZ SDN BHD | E35: VGK8942 | F35: FASWO2411007 | H35: 320 | I35: 320 | J35: 0 | K35: 320 | L35: INV
A36: FASSI2411008 | B36: NOV | C36: 45625 | D36: EDARAN RIZ SDN BHD | E36: VGU7551 | F36: FASWO2411008 | H36: 320 | I36: 320 | J36: 0 | K36: 320 | L36: INV
A37: FASSI2411009 | B37: NOV | C37: 45625 | D37: EDARAN RIZ SDN BHD | E37: VGL7449 | F37: FASWO2411009 | H37: 240 | I37: 240 | J37: 0 | K37: 240 | L37: INV
A38: FASSI2411010 | B38: NOV | C38: 45625 | D38: EDARAN RIZ SDN BHD | E38: VGK9635 | F38: FASWO2411010 | H38: 472 | I38: 472 | J38: 0 | K38: 472 | L38: INV
A39: FASSI2411011 | B39: NOV | C39: 45625 | D39: EDARAN RIZ SDN BHD | E39: VGN2843 | F39: FASWO2411011 | H39: 392 | I39: 392 | J39: 0 | K39: 392 | L39: INV
A40: FASSI2411012 | B40: NOV | C40: 45626 | D40: LHL MARKETING | E40: AMR3233 | F40: FASWO2408001 | I40: 0 | J40: 0 | K40: 0
A41: FASSI2412001 | B41: DEC | C41: 45636 | D41: REDHA CONSTRUCTIONS | E41: BRM1186 | F41: FASWO2412001 | I41: 0 | J41: 0 | K41: 0
A42: FASSI2412002 | B42: DEC | C42: 45657 | D42: TRUCK-LINK AUTO PARTS SDN BHD | E42: VGQ1734 | F42: FASWO2403007 | G42: 521.38 | H42: 818.8 | I42: 1340.18 | J42: 0 | K42: 1340.18 | L42: INV
A43: FASSI2412003 | B43: DEC | C43: 45657 | D43: TRUCK-LINK AUTO PARTS SDN BHD | E43: VFP3816 | F43: FASWO2412002 | G43: 150 | H43: 1000 | I43: 1150 | J43: 0 | K43: 1150 | L43: INV
K45: =SUM(K2:K44) -> 12398

Sheet FUSO WC 2024
A1: WARRANTY CLAIM LISTING
A2: DATE | B2: MONTH | C2: CLAIM NO | D2: CLAIM TO | E2: INVOICE NO | F2: REGNO | G2: PART | H2: LABOUR | I2: TOTAL | J2: AMOUNT
A3: 45371 | B3: MAR | C3: FASWC2403001 | D3: HAP SENG TRUCK DISTRIBUTION SDN BHD | E3: FASSI2403004 | F3: VKP8555 | G3: 148.8 | H3: 56.88 | I3: 205.68 | J3: 205.68
A4: 45411 | B4: APR | C4: FASWC2404001 | D4: HAP SENG TRUCK DISTRIBUTION SDN BHD | E4: FASSI2404004 | F4: NDV7169 | G4: 2867.57 | H4: 450 | I4: 3317.57 | J4: 3317.57
A5: 45440 | B5: MAY | C5: FASWC2405001 | D5: HAP SENG TRUCK DISTRIBUTION SDN BHD | E5: FASSI2405002 | F5: RAT9186 | G5: 327.36 | H5: 42 | I5: 369.36 | J5: 369.36
A6: 45579 | B6: OCT | C6: FASWC2410001 | D6: HAP SENG TRUCK DISTRIBUTION SDN BHD | E6: FASSI2410001 | F6: PPL7533 | G6: 1824.24 | H6: 96 | I6: 1920.24 | J6: 1920.24
A7: 45602 | B7: NOV | C7: FASWC2411001 | D7: HAP SENG TRUCK DISTRIBUTION SDN BHD | E7: FASSI2411012 | F7: AMR3233 | G7: 409.2 | H7: 252 | I7: 661.2 | J7: 661.2
J9: =SUM(J3:J8) -> 6474.05
A11: FREE SERVICE
A12: 45304 | B12: JAN | C12: FASFS2401001 | D12: HAP SENG TRUCK DISTRIBUTION SDN BHD | E12: FASSI2401001 | F12: VKP8555 | G12: 240.21 | H12: 108 | I12: 348.21 | J12: 348.21
A13: 45358 | B13: MAR | C13: FASFS2403001 | D13: HAP SENG TRUCK DISTRIBUTION SDN BHD | E13: FASSI2403001 | F13: UKM 2118 | G13: 225.81 | H13: 126 | I13: 351.81 | J13: 351.81
A14: 45359 | B14: MAR | C14: FASFS2403002 | D14: HAP SENG TRUCK DISTRIBUTION SDN BHD | E14: FASSI2403002 | F14: BRM1186 | G14: 225.81 | H14: 126 | I14: 351.81 | J14: 351.81
A15: 45359 | B15: MAR | C15: FASFS2403003 | D15: HAP SENG TRUCK DISTRIBUTION SDN BHD | E15: FASSI2403003 | F15: NDV7169 | G15: 501.18 | H15: 222 | I15: 723.18 | J15: 723.18
A16: 45409 | B16: APR | C16: FASFS2404001 | D16: HAP SENG TRUCK DISTRIBUTION SDN BHD | E16: FASSI2404002 | F16: VLW3392 | G16: 395.23 | H16: 180 | I16: 575.23 | J16: 575.23
A17: 45409 | B17: APR | C17: FASFS2404002 | D17: HAP SENG TRUCK DISTRIBUTION SDN BHD | E17: FASSI2404003 | F17: RAT9186 | G17: 494.18 | H17: 198 | I17: 692.18 | J17: 692.18
A18: 45440 | B18: MAY | C18: FASFS2405001 | D18: HAP SENG TRUCK DISTRIBUTION SDN BHD | E18: FASSI2405001 | F18: RAT9186 | G18: 225.81 | H18: 126 | I18: 351.81 | J18: 351.81
A19: 45444 | B19: JUNE | C19: FASFS2406001 | D19: HAP SENG TRUCK DISTRIBUTION SDN BHD | E19: FASSI2406002 | F19: BRM1186 | G19: 240.21 | H19: 108 | I19: 348.21 | J19: 348.21
A20: 45471 | B20: JUNE | C20: FASFS2406002 | D20: HAP SENG TRUCK DISTRIBUTION SDN BHD | E20: FASSI2406003 | F20: VKP8555 | G20: 501.18 | H20: 222 | I20: 723.18 | J20: 723.18
A21: 45455 | B21: JUNE | C21: FASFS2406003 | D21: HAP SENG TRUCK DISTRIBUTION SDN BHD | E21: FASSI2406004 | F21: UKM 2118 | G21: 240.21 | H21: 108 | I21: 348.21 | J21: 348.21
A22: 45469 | B22: JUNE | C22: FASFS2406004 | D22: HAP SENG TRUCK DISTRIBUTION SDN BHD | E22: FASSI2406005 | F22: MDR5421 | G22: 240.21 | H22: 108 | I22: 348.21 | J22: 348.21
A23: 45482 | B23: JULY | C23: FASFS2407001 | D23: HAP SENG TRUCK DISTRIBUTION SDN BHD | E23: FASSI2407001 | F23: JWC1993 | G23: 240.21 | H23: 108 | I23: 348.21 | J23: 348.21
... A31: 45639 | B31: DEC | C31: FASFS2412001 | D31: HAP SENG TRUCK DISTRIBUTION SDN BHD | E31: FASSI2412001 | F31: BRM1186 | G31: 325.01 | H31: 120 | I31: 445.01 | J31: 445.01
J33: =SUM(J12:J32) -> 9590.64

Sheet 2025
B1: Auto Raya Sdn Bhd
B2: Monthly Summary After Sales 2025
C4: HINO
C5: ACCIDENT | H5: WINDSCREEN | M5: OTHERS | P5: TOTAL
C6: INTAKE | D6: INS - PARTS | E6: INS - LABOURS | F6: CREDIT | G6: CASH | H6: INTAKE | I6: INS - PARTS | J6: INS - LABOURS | K6: CREDIT | L6: CASH | M6: INTAKE | N6: CASH | O6: CREDIT | P6: INTAKE | Q6: TOTAL | R6: Avg
B7: JANUARY | C7: 2 | D7: ='HINO 2025'!G2+'HINO 2025'!G3 -> 62208.69 | E7: ='HINO 2025'!H2+'HINO 2025'!H3 -> 19860 | F7: 950 | G7: 0 | H7: 1 | I7: ='HINO 2025'!G4 -> 908.52 | J7: ='HINO 2025'!H4 -> 480 | K7: 0 | L7: 0 | M7: 0 | N7: 0 | O7: 0 | P7: =SUM(C7+H7+M7) -> 3 | Q7: =D7+E7+F7+G7+I7+J7+L7+K7+N7+O7 -> 84407.21 | R7: =Q7/P7 -> 28135.737
B8: FEBRUARY | C8: 5 | D8: ='HINO 2025'!G5+'HINO 2025'!G6+'HINO 2025'!G8+'HINO 2025'!G9+'HINO 2025'!G10 -> 102728.34 | E8: ='HINO 2025'!H5+'HINO 2025'!H6+'HINO 2025'!H8+'HINO 2025'!H9+'HINO 2025'!H10 -> 14760 | F8: 2280 | G8: 0 | H8: 1 | I8: ='HINO 2025'!G7 -> 973.08 | J8: ='HINO 2025'!H7 -> 420 | K8: 0 | L8: 0 | M8: 0 | N8: 0 | O8: 0 | P8: =SUM(C8+H8+M8) -> 6 | Q8: =D8+E8+F8+G8+I8+J8+L8+K8+N8+O8 -> 121161.42 | R8: =Q8/P8 -> 20193.57
B9: MARCH | C9: 1 | D9: ='HINO 2025'!G13 -> 110273.46 | E9: ='HINO 2025'!H13 -> 5028 | F9: 0 | G9: 0 | H9: 3 | I9: ='HINO 2025'!G11+'HINO 2025'!G12+'HINO 2025'!G14 -> 2634.24 | J9: ='HINO 2025'!H11+'HINO 2025'!H12+'HINO 2025'!H14 -> 1260 | K9: 0 | L9: 0 | M9: 0 | N9: 0 | O9: 0 | P9: =SUM(C9+H9+M9) -> 4 | Q9: =D9+E9+F9+G9+I9+J9+L9+K9+N9+O9 -> 119195.7 | R9: =Q9/P9 -> 29798.925
B10: APRIL | C10: 4 | D10: 204242.82 | E10: 16848 | F10: 2907 | G10: 0 | H10: 0 | I10: 0 | J10: 0 | K10: 0 | L10: 0 | M10: 0 | N10: 0 | O10: 0 | P10: =SUM(C10+H10+M10) -> 4 | Q10: =D10+E10+F10+G10+I10+J10+L10+K10+N10+O10 -> 223997.82 | R10: =Q10/P10 -> 55999.455
B11: MAY | C11: 3 | D11: 39133.91 | E11: 21360 | F11: 6615.37 | G11: 0 | H11: 1 | I11: 973.08 | J11: 420 | K11: 0 | L11: 0 | M11: 1 | N11: 975 | P11: =SUM(C11+H11+M11) -> 5 | Q11: =D11+E11+F11+G11+I11+J11+L11+K11+N11+O11 -> 69477.36 | R11: =Q11/P11 -> 13895.472
B12: JUNE | C12: 3 | D12: 92302.72 | E12: 13246.8 | F12: 6378 | G12: 0 | H12: 0 | I12: 0 | J12: 0 | K12: 0 | L12: 0 | M12: 0 | N12: 0 | O12: 0 | P12: =SUM(C12+H12+M12) -> 3 | Q12: =D12+E12+F12+G12+I12+J12+L12+K12+N12+O12 -> 111927.52 | R12: =Q12/P12 -> 37309.173
B13: JULY | C13: 7 | D13: 272907.57 | E13: 31188 | F13: 2261 | G13: 0 | H13: 2 | I13: 2231.16 | J13: 840 | K13: 0 | L13: 0 | M13: 0 | N13: 0 | O13: 0 | P13: =SUM(C13+H13+M13) -> 9 | Q13: =D13+E13+F13+G13+I13+J13+L13+K13+N13+O13 -> 309427.73 | R13: =Q13/P13 -> 34380.859
B14: AUGUST | C14: 2 | D14: 10050.07 | E14: 4389 | F14: 0 | G14: 0 | H14: 2 | I14: 1887.84 | J14: 627 | K14: 0 | L14: 0 | M14: 0 | N14: 0 | O14: 0 | P14: =SUM(C14+H14+M14) -> 4 | Q14: =D14+E14+F14+G14+I14+J14+L14+K14+N14+O14 -> 16953.91 | R14: =Q14/P14 -> 4238.4775
B15: SEPTEMBER | C15: 4 | D15: 82294.18 | E15: 16188 | F15: 3935 | G15: 0 | H15: 1 | I15: 994.08 | J15: 399 | K15: 0 | L15: 0 | M15: 2 | N15: 7060 | O15: 0 | P15: =SUM(C15+H15+M15) -> 7 | Q15: =D15+E15+F15+G15+I15+J15+L15+K15+N15+O15 -> 110870.26 | R15: =Q15/P15 -> 15838.609
B16: OCTOBER | C16: 6 | D16: 157880.89 | E16: 29979.15 | F16: 0 | G16: 0 | H16: 3 | I16: 2032.24 | J16: 1197 | K16: 0 | L16: 0 | M16: 0 | N16: 0 | O16: 0 | P16: =SUM(C16+H16+M16) -> 9 | Q16: =D16+E16+F16+G16+I16+J16+L16+K16+N16+O16 -> 191089.28 | R16: =Q16/P16 -> 21232.142
B17: NOVEMBER | C17: 6 | D17: 171427.56 | E17: 35017.38 | F17: 9520 | G17: 0 | H17: 2 | I17: 658.16 | J17: 798 | K17: 0 | L17: 0 | M17: 0 | N17: 0 | O17: 0 | P17: =SUM(C17+H17+M17) -> 8 | Q17: =D17+E17+F17+G17+I17+J17+L17+K17+N17+O17 -> 217421.1 | R17: =Q17/P17 -> 27177.638
B18: DECEMBER | C18: 3 | D18: 82793.62 | E18: 18616.2 | F18: 950 | G18: 0 | H18: 0 | I18: 0 | J18: 0 | K18: 0 | L18: 0 | M18: 0 | N18: 0 | O18: 0 | P18: =SUM(C18+H18+M18) -> 3 | Q18: =D18+E18+F18+G18+I18+J18+L18+K18+N18+O18 -> 102359.82 | R18: =Q18/P18 -> 34119.94
C19: =SUM(C7:C18) -> 46 | D19: =SUM(D7:D18) -> 1388243.8 | E19: =SUM(E7:E18) -> 226480.53 | F19: =SUM(F7:F18) -> 35796.37 | G19: =SUM(G7:G18) -> 0 | H19: =SUM(H7:H18) -> 16 | I19: =SUM(I7:I18) -> 13292.4 | J19: =SUM(J7:J18) -> 6441 | ... Q19: =SUM(Q7:Q18) -> 1678289.1 | R19: =Q19/P19 -> 25819.833
C22: MITSUBISHI
C23: ACCIDENT | H23: WINDSCREEN | M23: OTHERS | P23: TOTAL
C24: INTAKE | D24: INS - PARTS | E24: INS - LABOURS | F24: CREDIT | G24: CASH | H24: INTAKE | I24: INS - PARTS | J24: INS - LABOURS | K24: CREDIT | L24: CASH | M24: INTAKE | N24: CASH | O24: CREDIT | P24: INTAKE | Q24: TOTAL | R24: Avg
B25: JANUARY | C25: 10 | D25: ='MITS 2025'!G2+'MITS 2025'!G4+'MITS 2025'!G5+'MITS 2025'!G7+'MITS 2025'!G8+'MITS 2025'!G11+'MITS 2025'!G12+'MITS 2025'!G13+'MITS 2025'!G14+'MITS 2025'!G15 -> 98603.04 | E25: ='MITS 2025'!H2+'MITS 2025'!H4+'MITS 2025'!H5+'MITS 2025'!H7+'MITS 2025'!H8+'MITS 2025'!H11+'MITS 2025'!H12+'MITS 2025'!H13+'MITS 2025'!H14+'MITS 2025'!H15 -> 36816 | F25: 0 | G25: ='MITS 2025'!K9 -> 515 | H25: 2 | I25: ='MITS 2025'!G3+'MITS 2025'!G6 -> 4181.87 | J25: ='MITS 2025'!H3+'MITS 2025'!H6 -> 528 | K25: 0 | L25: 0 | M25: 1 | N25: 0 | O25: ='MITS 2025'!K10 -> 115 | P25: =SUM(C25+H25+M25) -> 13 | Q25: =D25+E25+F25+G25+I25+J25+K25+L25+N25+O25 -> 140758.91 | R25: =Q25/P25 -> 10827.608
B26: FEBRUARY | C26: 8 | D26: ='MITS 2025'!G16+'MITS 2025'!G17+'MITS 2025'!G20+'MITS 2025'!G23+'MITS 2025'!G24+'MITS 2025'!G25+'MITS 2025'!G26+'MITS 2025'!G27 -> 88403.77 | E26: ='MITS 2025'!H16+'MITS 2025'!H17+'MITS 2025'!H20+'MITS 2025'!H23+'MITS 2025'!H24+'MITS 2025'!H25+'MITS 2025'!H26+'MITS 2025'!H27 -> 27570 | F26: 0 | G26: 0 | H26: 4 | I26: ='MITS 2025'!G18+'MITS 2025'!G19+'MITS 2025'!G21+'MITS 2025'!G28 -> 7232.75 | J26: ='MITS 2025'!H18+'MITS 2025'!H19+'MITS 2025'!H21+'MITS 2025'!H28 -> 1068 | K26: 0 | L26: 350 | M26: 1 | N26: ='MITS 2025'!K22 -> 1603.8 | O26: 0 | P26: =SUM(C26+H26+M26) -> 13 | Q26: =D26+E26+F26+G26+I26+J26+K26+L26+N26+O26 -> 126228.32 | R26: =Q26/P26 -> 9709.8708
B27: MARCH | C27: 9 | D27: ='MITS 2025'!G29+'MITS 2025'!G30+'MITS 2025'!G37+'MITS 2025'!G35+'MITS 2025'!G38+'MITS 2025'!G39+'MITS 2025'!G42+'MITS 2025'!G43+'MITS 2025'!G44 -> 78790.87 | E27: ='MITS 2025'!H29+'MITS 2025'!H30+'MITS 2025'!H37+'MITS 2025'!H35+'MITS 2025'!H38+'MITS 2025'!H39+'MITS 2025'!H42+'MITS 2025'!H43+'MITS 2025'!H44 -> 26745.6 | F27: 1977.05 | G27: 0 | H27: 6 | I27: ='MITS 2025'!G31+'MITS 2025'!G32+'MITS 2025'!G33+'MITS 2025'!G36+'MITS 2025'!G40+'MITS 2025'!G41 -> 14086.82 | J27: ='MITS 2025'!H31+'MITS 2025'!H32+'MITS 2025'!H33+'MITS 2025'!H36+'MITS 2025'!H40+'MITS 2025'!H41 -> 1476 | K27: 1027.98 | L27: 0 | M27: 1 | N27: ='MITS 2025'!K34 -> 1242.2 | O27: 0 | P27: =SUM(C27+H27+M27) -> 16 | Q27: =D27+E27+F27+G27+I27+J27+K27+L27+N27+O27 -> 125346.52 | R27: =Q27/P27 -> 7834.1575
B28: APRIL | C28: 4 | D28: 38080.99 | E28: 9636 | F28: 1805 | G28: 0 | H28: 6 | I28: 15145.54 | J28: 1536 | K28: 179.74 | L28: 0 | M28: 0 | N28: 0 | O28: 0 | P28: =SUM(C28+H28+M28) -> 10 | Q28: =D28+E28+F28+G28+I28+J28+K28+L28+N28+O28 -> 66383.27 | R28: =Q28/P28 -> 6638.327
B29: MAY | C29: 4 | D29: 59154.41 | E29: 22044 | F29: 0 | G29: 0 | H29: 5 | I29: 10917.52 | J29: 1260 | K29: 353.55 | L29: 0 | M29: 3 | N29: 5151.9 | O29: 7046.72 | P29: =SUM(C29+H29+M29) -> 12 | Q29: =D29+E29+F29+G29+I29+J29+K29+L29+N29+O29 -> 105928.1 | R29: =Q29/P29 -> 8827.3417
B30: JUNE | C30: 8 | D30: 125740.31 | E30: 33924 | F30: 2520.16 | G30: 0 | H30: 3 | I30: 7373.44 | J30: 804 | K30: 0 | L30: 0 | M30: 5 | N30: 2401 | O30: 6690.53 | P30: =SUM(C30+H30+M30) -> 16 | Q30: =D30+E30+F30+G30+I30+J30+K30+L30+N30+O30 -> 179453.44 | R30: =Q30/P30 -> 11215.84
B31: JULY | C31: 5 | D31: 52374.98 | E31: 18828 | F31: 2185 | G31: 0 | H31: 9 | I31: 18701.7 | J31: 2304 | K31: 501.92 | L31: 0 | M31: 1 | N31: 0 | O31: 6409.65 | P31: =SUM(C31+H31+M31) -> 15 | Q31: =D31+E31+F31+G31+I31+J31+K31+L31+N31+O31 -> 101305.25 | R31: =Q31/P31 -> 6753.6833
B32: AUGUST | C32: 4 | D32: 50679.19 | E32: 10442.4 | F32: 1690.05 | G32: 0 | H32: 10 | I32: 19128.34 | J32: 2485.2 | K32: 539.65 | L32: 0 | M32: 1 | N32: 0 | O32: 676 | P32: =SUM(C32+H32+M32) -> 15 | Q32: =D32+E32+F32+G32+I32+J32+K32+L32+N32+O32 -> 85640.83 | R32: =Q32/P32 -> 5709.3887
B33: SEPTEMBER | C33: 6 | D33: 121390.93 | E33: 25182.6 | F33: 3531.15 | G33: 0 | H33: 4 | I33: 7771.57 | J33: 809.4 | K33: 99.94 | L33: 0 | M33: 0 | N33: 0 | O33: 0 | P33: =SUM(C33+H33+M33) -> 10 | Q33: =D33+E33+F33+G33+I33+J33+K33+L33+N33+O33 -> 158785.59 | R33: =Q33/P33 -> 15878.559
B34: OCTOBER | C34: 6 | D34: 112833.75 | E34: 28078.2 | F34: 75.95 | G34: 0 | H34: 5 | I34: 8150.69 | J34: 1242.6 | K34: 410.48 | L34: 0 | M34: 2 | N34: 93 | O34: 136.6 | P34: =SUM(C34+H34+M34) -> 13 | Q34: =D34+E34+F34+G34+I34+J34+K34+L34+N34+O34 -> 151021.27 | R34: =Q34/P34 -> 11617.021
B35: NOVEMBER | C35: 4 | D35: 87613.38 | E35: 12961.8 | F35: 0 | G35: 0 | H35: 6 | I35: 13755.31 | J35: 1447.8 | K35: 172.98 | L35: 0 | M35: 0 | N35: 0 | O35: 0 | P35: =SUM(C35+H35+M35) -> 10 | Q35: =D35+E35+F35+G35+I35+J35+K35+L35+N35+O35 -> 115951.27 | R35: =Q35/P35 -> 11595.127
B36: DECEMBER | C36: 6 | D36: 95400.75 | E36: 19191.9 | F36: 370.5 | G36: 0 | H36: 7 | I36: 10956.79 | J36: 1637.8 | K36: 1008.22 | L36: 0 | M36: 1 | N36: 962 | O36: 0 | P36: =SUM(C36+H36+M36) -> 14 | Q36: =D36+E36+F36+G36+I36+J36+K36+L36+N36+O36 -> 129527.96 | R36: =Q36/P36 -> 9251.9971
C37: =SUM(C25:C36) -> 74 | D37: =SUM(D25:D36) -> 1009066.4 | E37: =SUM(E25:E36) -> 271420.5 | F37: =SUM(F25:F36) -> 14154.86 | G37: =SUM(G25:G36) -> 515 | H37: =SUM(H25:H36) -> 67 | I37: =SUM(I25:I36) -> 137402.34 | J37: =SUM(J25:J36) -> 16598.8 | ... Q37: =SUM(Q25:Q36) -> 1486330.7 | R37: =Q37/P37 -> 9467.0747
C40: AFTER SALES SERVICE
C41: SERVICE FUSO | M41: SERVICE HINO | P41: TOTAL
C42: INTAKE | D42: FREE SERVICE | G42: INTAKE | H42: WARRANTY | I42: INTAKE | L42: CASH | M42: INTAKE | N42: INVOICE | O42: CASH | P42: INTAKE | Q42: TOTAL | R42: Avg
B43: JANUARY | C43: 2 | D43: ='FUSO WC 2025'!J21+'FUSO WC 2025'!J22 -> 1446.36 | G43: 0 | H43: 0 | I43: 2 | L43: ='FUSO 2025'!L3+'FUSO 2025'!L5 -> 549.5 | M43: 0 | N43: 0 | O43: 0 | P43: =SUM(C43+G43+I43+M43) -> 4 | Q43: =SUM(D43+H43+L43+N43+O43) -> 1995.86 | R43: =Q43/P43 -> 498.965
B44: FEBRUARY | C44: 2 | D44: ='FUSO WC 2025'!J23+'FUSO WC 2025'!J24 -> 696.42 | G44: 1 | H44: ='FUSO WC 2025'!J3 -> 1544.76 | I44: 0 | L44: 0 | M44: 0 | N44: 0 | O44: 0 | P44: =SUM(C44+G44+I44+M44) -> 3 | Q44: =SUM(D44+H44+L44+N44+O44) -> 2241.18 | R44: =Q44/P44 -> 747.06
B45: MARCH | C45: 1 | D45: ='FUSO WC 2025'!J25 -> 453.01 | G45: 1 | H45: ='FUSO WC 2025'!J4 -> 369.36 | I45: 3 | L45: ='FUSO 2025'!L9+'FUSO 2025'!L10+'FUSO 2025'!L11 -> 1402.1 | M45: 0 | N45: 0 | O45: 0 | P45: =SUM(C45+G45+I45+M45) -> 5 | Q45: =SUM(D45+H45+L45+N45+O45) -> 2224.47 | R45: =Q45/P45 -> 444.894
B46: APRIL | C46: 1 | D46: 453.01 | G46: 1 | H46: 2402 | I46: 0 | L46: 0 | M46: 0 | N46: 0 | O46: 0 | P46: =SUM(C46+G46+I46+M46) -> 2 | Q46: =SUM(D46+H46+L46+N46+O46) -> 2855.01 | R46: =Q46/P46 -> 1427.505
B47: MAY | C47: 0 | D47: 0 | G47: 1 | H47: 453.01 | I47: 1 | L47: 291.8 | M47: 0 | N47: 0 | O47: 0 | P47: =SUM(C47+G47+I47+M47) -> 2 | Q47: =SUM(D47+H47+L47+N47+O47) -> 744.81 | R47: =Q47/P47 -> 372.405
B48: JUNE | C48: 1 | D48: 748.18 | G48: 0 | H48: 0 | I48: 2 | L48: 1369.63 | M48: 0 | N48: 0 | O48: 0 | P48: =SUM(C48+G48+I48+M48) -> 3 | Q48: =SUM(D48+H48+L48+N48+O48) -> 2117.81 | R48: =Q48/P48 -> 705.93667
B49: JULY | C49: 0 | D49: 0 | G49: 0 | H49: 0 | I49: 3 | L49: 2467.96 | M49: 0 | N49: 0 | O49: 0 | P49: =SUM(C49+G49+I49+M49) -> 3 | Q49: =SUM(D49+H49+L49+N49+O49) -> 2467.96 | R49: =Q49/P49 -> 822.65333
B50: AUGUST | C50: 0 | D50: 0 | G50: 0 | H50: 0 | I50: 1 | L50: 774.27 | M50: 0 | N50: 0 | O50: 0 | P50: =SUM(C50+G50+I50+M50) -> 1 | Q50: =SUM(D50+H50+L50+N50+O50) -> 774.27 | R50: =Q50/P50 -> 774.27
B51: SEPTEMBER | C51: 0 | D51: 0 | G51: 0 | H51: 0 | I51: 1 | L51: 296.82 | M51: 0 | N51: 0 | O51: 0 | P51: =SUM(C51+G51+I51+M51) -> 1 | Q51: =SUM(D51+H51+L51+N51+O51) -> 296.82 | R51: =Q51/P51 -> 296.82
B52: OCTOBER | C52: 0 | D52: 0 | G52: 0 | H52: 0 | I52: 3 | L52: 566.77 | M52: 0 | N52: 0 | O52: 0 | P52: =SUM(C52+G52+I52+M52) -> 3 | Q52: =SUM(D52+H52+L52+N52+O52) -> 566.77 | R52: =Q52/P52 -> 188.92333
B53: NOVEMBER | C53: 1 | D53: 454.61 | G53: 0 | H53: 0 | I53: 2 | L53: 627.58 | M53: 0 | N53: 0 | O53: 0 | P53: =SUM(C53+G53+I53+M53) -> 3 | Q53: =SUM(D53+H53+L53+N53+O53) -> 1082.19 | R53: =Q53/P53 -> 360.73
B54: DECEMBER | C54: 0 | D54: 0 | G54: 0 | H54: 0 | I54: 0 | L54: 0 | M54: 0 | N54: 0 | O54: 0 | P54: =SUM(C54+G54+I54+M54) -> 0 | Q54: =SUM(D54+H54+L54+N54+O54) -> 0 | R54: =Q54/P54 -> #DIV/0!
C55: =SUM(C43:C54) -> 8 | D55: =SUM(D43:D54) -> 4251.59 | G55: =SUM(G43:G54) -> 4 | H55: =SUM(H43:H54) -> 4769.13 | I55: =SUM(I43:I54) -> 18 | L55: =SUM(L43:L54) -> 8346.43 | M55: =SUM(M43:M54) -> 0 | N55: =SUM(N43:N54) -> 0 | P55: =SUM(P43:P54) -> 30 | Q55: =SUM(Q43:Q54) -> 17367.15 | R55: =Q55/P55 -> 578.905
I57: Average Per Month : | L57: =(Q19/(COUNTA(C7:C18))) -> 139857.43 | M57: HINO
I58: Average Per Month : | L58: =(Q37/(COUNTA(C25:C36))) -> 123860.89 | M58: MITSUBUSHI
I59: Average Per Month : | L59: =Q55/(COUNTA(C43:C54)) -> 1447.2625 | M59: AFTER SALES SERVICE
P60: B&P Sales %
D61: Hino | G61: Mitsubishi | I61: B&P | L61: Service | N61: Total | P61: Hino | Q61: Mitsubishi | R61: Service
B62: Total Insurance | D62: =SUM(D19+I19) -> 1401536.2 | G62: =SUM(D37+I37) -> 1146468.7 | I62: =D62+G62 -> 2548004.9 | L62: =D55+H55+N55 -> 9020.72 | N62: =SUM(I62:M62) -> 2557025.7 | P62: =SUM(D62/N62) -> 0.54811191 | Q62: =SUM(G62/N62) -> 0.44836027 | R62: =L62/N62 -> 0.0035278176
B63: Total WindScreen | D63: =SUM(I19:L19) -> 19733.4 | G63: =SUM(I37:L37) -> 158645.6 | I63: =D63+G63 -> 178379 | N63: =SUM(I63:M63) -> 178379 | P63: =SUM(D63/N63) -> 0.11062625 | Q63: =SUM(G63/N63) -> 0.88937375 | R63: =L63/N63 -> 0
B64: Total Cash Job | D64: =G19+L19+N19 -> 8035 | G64: =G37+L37+N37 -> 12318.9 | I64: =D64+G64 -> 20353.9 | L64: =L55 -> 8346.43 | N64: =SUM(I64:M64) -> 28700.33 | P64: =SUM(D64/N64) -> 0.27996194 | Q64: =SUM(G64/N64) -> 0.42922503 | R64: =L64/N64 -> 0.29081303
B65: Others | D65: =O19 -> 0 | G65: =O37 -> 21074.5 | I65: =D65+G65 -> 21074.5 | N65: =SUM(I65:M65) -> 21074.5
B66: Total : | D66: =SUM(D62:D65)-I19 -> 1416012.2 | G66: =SUM(G62:G65)-I37 -> 1201105.4 | I66: =SUM(I62:I65)-I63 -> 2589433.3 | L66: =SUM(L62:L65) -> 17367.15 | N66: =SUM(N62:N65)-N63 -> 2606800.5 | P66: - | Q66: -

Sheet 2026
B1: Auto Raya Sdn Bhd
B2: Monthly Summary After Sales 2026
C4: HINO
C5: ACCIDENT | H5: WINDSCREEN | M5: OTHERS | P5: TOTAL
C6: INTAKE | D6: INS - PARTS | E6: INS - LABOURS | F6: CREDIT | G6: CASH | H6: INTAKE | I6: INS - PARTS | J6: INS - LABOURS | K6: CREDIT | L6: CASH | M6: INTAKE | N6: CASH | O6: CREDIT | P6: INTAKE | Q6: TOTAL | R6: Avg
B7: JANUARY | C7: 6 | D7: 182814.26 | E7: 26744.4 | F7: 7700 | G7: 0 | H7: 1 | I7: 994.08 | J7: 399 | K7: 0 | L7: 0 | M7: 0 | N7: 0 | O7: 0 | P7: =SUM(C7+H7+M7) -> 7 | Q7: =D7+E7+F7+G7+I7+J7+L7+K7+N7+O7 -> 218651.74 | R7: =Q7/P7 -> 31235.963
B8: FEBRUARY | C8: 6 | D8: 190831.86 | E8: 31717.8 | F8: 2375 | G8: 0 | H8: 1 | I8: 994.08 | J8: 399 | K8: 0 | L8: 0 | M8: 1 | N8: 800 | O8: 0 | P8: =SUM(C8+H8+M8) -> 8 | Q8: =D8+E8+F8+G8+I8+J8+L8+K8+N8+O8 -> 227117.74 | R8: =Q8/P8 -> 28389.717
B9: MARCH | C9: 0 | D9: 0 | E9: 0 | F9: 0 | G9: 0 | H9: 1 | I9: 994.08 | J9: 399 | K9: 0 | L9: 0 | M9: 1 | N9: 2664 | O9: 0 | P9: =SUM(C9+H9+M9) -> 2 | Q9: =D9+E9+F9+G9+I9+J9+L9+K9+N9+O9 -> 4057.08 | R9: =Q9/P9 -> 2028.54
B10: APRIL | C10: 1 | D10: 2762.89 | E10: 3306 | F10: 500 | G10: 0 | H10: 0 | I10: 0 | J10: 0 | K10: 0 | L10: 0 | M10: 0 | N10: 0 | O10: 0 | P10: =SUM(C10+H10+M10) -> 1 | Q10: =D10+E10+F10+G10+I10+J10+L10+K10+N10+O10 -> 6568.89 | R10: =Q10/P10 -> 6568.89
B11: MAY | C11: 2 | D11: 83670.26 | E11: 15173.4 | F11: 2550 | G11: 0 | H11: 0 | I11: 0 | J11: 0 | K11: 0 | L11: 0 | M11: 0 | N11: 0 | O11: 0 | P11: =SUM(C11+H11+M11) -> 2 | Q11: =D11+E11+F11+G11+I11+J11+L11+K11+N11+O11 -> 101393.66 | R11: =Q11/P11 -> 50696.83
B12: JUNE | C12: 3 | D12: 185938.63 | E12: 17613 | F12: 0 | H12: 2 | I12: 2273.16 | J12: 798 | K12: 0 | L12: 0 | M12: 0 | N12: 0 | O12: 0 | P12: =SUM(C12+H12+M12) -> 5 | Q12: =D12+E12+F12+G12+I12+J12+L12+K12+N12+O12 -> 206622.79 | R12: =Q12/P12 -> 41324.558
B13: JULY | C13: 2 | D13: 72864.52 | E13: 24681 | F13: 0 | G13: 0 | H13: 0 | I13: 0 | J13: 0 | K13: 0 | L13: 0 | M13: 1 | N13: 5620 | O13: 0 | P13: =SUM(C13+H13+M13) -> 3 | Q13: =D13+E13+F13+G13+I13+J13+L13+K13+N13+O13 -> 103165.52 | R13: =Q13/P13 -> 34388.507
B14: AUGUST | C14: 3 | D14: 145249.87 | E14: 20052.6 | F14: 2437.5 | G14: 0 | H14: 0 | I14: 0 | J14: 0 | K14: 0 | L14: 0 | M14: 0 | N14: 0 | O14: 0 | P14: =SUM(C14+H14+M14) -> 3 | Q14: =D14+E14+F14+G14+I14+J14+L14+K14+N14+O14 -> 167739.97 | R14: =Q14/P14 -> 55913.323
B15: SEPTEMBER | C15: 1 | D15: 59446.52 | E15: 5814 | F15: 3515 | G15: 0 | H15: 1 | I15: 994.08 | J15: 399 | K15: 0 | L15: 0 | M15: 0 | N15: 0 | O15: 0 | P15: =SUM(C15+H15+M15) -> 2 | Q15: =D15+E15+F15+G15+I15+J15+L15+K15+N15+O15 -> 70168.6 | R15: =Q15/P15 -> 35084.3
B16: OCTOBER | P16: =SUM(C16+H16+M16) -> 0 | Q16: =D16+E16+F16+G16+I16+J16+L16+K16+N16+O16 -> 0 | R16: =Q16/P16 -> #DIV/0!
B17: NOVEMBER | P17: =SUM(C17+H17+M17) -> 0 | Q17: =D17+E17+F17+G17+I17+J17+L17+K17+N17+O17 -> 0 | R17: =Q17/P17 -> #DIV/0!
B18: DECEMBER | P18: =SUM(C18+H18+M18) -> 0 | Q18: =D18+E18+F18+G18+I18+J18+L18+K18+N18+O18 -> 0 | R18: =Q18/P18 -> #DIV/0!
C19: =SUM(C7:C18) -> 24 | D19: =SUM(D7:D18) -> 923578.81 | E19: =SUM(E7:E18) -> 145102.2 | F19: =SUM(F7:F18) -> 19077.5 | G19: =SUM(G7:G18) -> 0 | H19: =SUM(H7:H18) -> 6 | I19: =SUM(I7:I18) -> 6249.48 | J19: =SUM(J7:J18) -> 2394 | ... Q19: =SUM(Q7:Q18) -> 1105486 | R19: =Q19/P19 -> 33499.575
C22: MITSUBISHI
C23: ACCIDENT | H23: WINDSCREEN | M23: OTHERS | P23: TOTAL
C24: INTAKE | D24: INS - PARTS | E24: INS - LABOURS | F24: CREDIT | G24: CASH | H24: INTAKE | I24: INS - PARTS | J24: INS - LABOURS | K24: CREDIT | L24: CASH | M24: INTAKE | N24: CASH | O24: CREDIT | P24: INTAKE | Q24: TOTAL | R24: Avg
B25: JANUARY | C25: 7 | D25: 76626.36 | E25: 21295.2 | F25: 1868.65 | G25: 0 | H25: 8 | I25: 14982.87 | J25: 1881 | K25: 0 | L25: 0 | M25: 1 | N25: 1560 | O25: 0 | P25: =SUM(C25+H25+M25) -> 16 | Q25: =D25+E25+F25+G25+I25+J25+K25+L25+N25+O25 -> 118214.08 | R25: =Q25/P25 -> 7388.38
B26: FEBRUARY | C26: 3 | D26: 81784.47 | E26: 21922.2 | F26: 2375 | G26: 0 | H26: 1 | I26: 2091.82 | J26: 262.2 | K26: 0 | L26: 0 | M26: 0 | N26: 0 | O26: 0 | P26: =SUM(C26+H26+M26) -> 4 | Q26: =D26+E26+F26+G26+I26+J26+K26+L26+N26+O26 -> 108435.69 | R26: =Q26/P26 -> 27108.923
B27: MARCH | C27: 3 | D27: 35006.71 | E27: 7706.4 | F27: 0 | G27: 0 | H27: 0 | I27: 0 | J27: 0 | K27: 172.98 | L27: 0 | M27: 2 | N27: 649.9 | O27: 4551.26 | P27: =SUM(C27+H27+M27) -> 5 | Q27: =D27+E27+F27+G27+I27+J27+K27+L27+N27+O27 -> 48087.25 | R27: =Q27/P27 -> 9617.45
B28: APRIL | C28: 5 | D28: 52416.14 | E28: 13474.8 | F28: 2411.69 | G28: 0 | H28: 6 | I28: 13219.85 | J28: 1504.8 | K28: 0 | L28: 0 | M28: 3 | N28: 0 | O28: 20263.86 | P28: =SUM(C28+H28+M28) -> 14 | Q28: =D28+E28+F28+G28+I28+J28+K28+L28+N28+O28 -> 103291.14 | R28: =Q28/P28 -> 7377.9386
B29: MAY | C29: 10 | D29: 153504.63 | E29: 34108.8 | F29: 2061.7 | G29: 0 | H29: 2 | I29: 5165.15 | J29: 490.2 | K29: 0 | L29: 0 | M29: 0 | N29: 0 | O29: 0 | P29: =SUM(C29+H29+M29) -> 12 | Q29: =D29+E29+F29+G29+I29+J29+K29+L29+N29+O29 -> 195330.48 | R29: =Q29/P29 -> 16277.54
B30: JUNE | C30: 3 | D30: 25784.15 | E30: 14763 | F30: 1527 | H30: 3 | I30: 6214.63 | J30: 752.4 | K30: 172.98 | L30: 0 | M30: 2 | N30: 0 | O30: 2843.9 | P30: =SUM(C30+H30+M30) -> 8 | Q30: =D30+E30+F30+G30+I30+J30+K30+L30+N30+O30 -> 52058.06 | R30: =Q30/P30 -> 6507.2575
B31: JULY | C31: 4 | D31: 71069.6 | E31: 11947.2 | F31: 0 | G31: 0 | H31: 3 | I31: 7169.65 | J31: 815.1 | K31: 30 | L31: 0 | M31: 0 | N31: 0 | O31: 0 | P31: =SUM(C31+H31+M31) -> 7 | Q31: =D31+E31+F31+G31+I31+J31+K31+L31+N31+O31 -> 91031.55 | R31: =Q31/P31 -> 13004.507
B32: AUGUST | C32: 8 | D32: 160868.59 | E32: 33504.6 | F32: 1028.85 | G32: 0 | H32: 4 | I32: 8499.22 | J32: 1014.6 | K32: 0 | L32: 0 | M32: 2 | N32: 0 | O32: 12756.45 | P32: =SUM(C32+H32+M32) -> 14 | Q32: =D32+E32+F32+G32+I32+J32+K32+L32+N32+O32 -> 217672.31 | R32: =Q32/P32 -> 15548.022
B33: SEPTEMBER | C33: 2 | D33: 16887.58 | E33: 3283.2 | F33: 0 | G33: 0 | H33: 2 | I33: 4198.81 | J33: 490.2 | K33: 337.44 | L33: 0 | M33: 4 | N33: 390 | O33: 3967.88 | P33: =SUM(C33+H33+M33) -> 8 | Q33: =D33+E33+F33+G33+I33+J33+K33+L33+N33+O33 -> 29555.11 | R33: =Q33/P33 -> 3694.3888
B34: OCTOBER | P34: =SUM(C34+H34+M34) -> 0 | Q34: =D34+E34+F34+G34+I34+J34+K34+L34+N34+O34 -> 0 | R34: =Q34/P34 -> #DIV/0!
B35: NOVEMBER | P35: =SUM(C35+H35+M35) -> 0 | Q35: =D35+E35+F35+G35+I35+J35+K35+L35+N35+O35 -> 0 | R35: =Q35/P35 -> #DIV/0!
B36: DECEMBER | P36: =SUM(C36+H36+M36) -> 0 | Q36: =D36+E36+F36+G36+I36+J36+K36+L36+N36+O36 -> 0 | R36: =Q36/P36 -> #DIV/0!
C37: =SUM(C25:C36) -> 45 | D37: =SUM(D25:D36) -> 673948.23 | E37: =SUM(E25:E36) -> 162005.4 | F37: =SUM(F25:F36) -> 11272.89 | G37: =SUM(G25:G36) -> 0 | H37: =SUM(H25:H36) -> 29 | I37: =SUM(I25:I36) -> 61542 | J37: =SUM(J25:J36) -> 7210.5 | ... Q37: =SUM(Q25:Q36) -> 963675.67 | R37: =Q37/P37 -> 10950.86
C40: AFTER SALES SERVICE
C41: SERVICE FUSO | M41: SERVICE HINO | P41: TOTAL
C42: INTAKE | D42: FREE SERVICE | G42: INTAKE | H42: WARRANTY | I42: INTAKE | L42: CASH | M42: INTAKE | N42: INVOICE | O42: CASH | P42: INTAKE | Q42: TOTAL | R42: Avg
B43: JANUARY | C43: 0 | D43: 0 | G43: 0 | H43: 0 | I43: 2 | L43: 1092.58 | M43: 0 | N43: 0 | O43: 0 | P43: =SUM(C43+G43+I43+M43) -> 2 | Q43: =SUM(D43+H43+L43+N43+O43) -> 1092.58 | R43: =Q43/P43 -> 546.29
B44: FEBRUARY | C44: 0 | D44: 0 | G44: 0 | H44: 0 | I44: 1 | L44: 727.33 | M44: 0 | N44: 0 | O44: 0 | P44: =SUM(C44+G44+I44+M44) -> 1 | Q44: =SUM(D44+H44+L44+N44+O44) -> 727.33 | R44: =Q44/P44 -> 727.33
B45: MARCH | C45: 0 | D45: 0 | G45: 0 | H45: 0 | I45: 1 | L45: 634.33 | M45: 0 | N45: 0 | O45: 0 | P45: =SUM(C45+G45+I45+M45) -> 1 | Q45: =SUM(D45+H45+L45+N45+O45) -> 634.33 | R45: =Q45/P45 -> 634.33
B46: APRIL | C46: 0 | D46: 0 | G46: 0 | H46: 0 | I46: 1 | L46: 296.82 | M46: 0 | N46: 0 | O46: 0 | P46: =SUM(C46+G46+I46+M46) -> 1 | Q46: =SUM(D46+H46+L46+N46+O46) -> 296.82 | R46: =Q46/P46 -> 296.82
B47: MAY | C47: 0 | D47: 0 | G47: 0 | H47: 0 | I47: 1 | L47: 649.55 | M47: 0 | N47: 0 | O47: 0 | P47: =SUM(C47+G47+I47+M47) -> 1 | Q47: =SUM(D47+H47+L47+N47+O47) -> 649.55 | R47: =Q47/P47 -> 649.55
B48: JUNE | C48: 0 | D48: 0 | G48: 0 | H48: 0 | I48: 1 | L48: 336.86 | M48: 0 | N48: 0 | O48: 0 | P48: =SUM(C48+G48+I48+M48) -> 1 | Q48: =SUM(D48+H48+L48+N48+O48) -> 336.86 | R48: =Q48/P48 -> 336.86
B49: JULY | C49: 0 | D49: 0 | G49: 0 | H49: 0 | I49: 1 | L49: 369.98 | M49: 0 | N49: 0 | O49: 0 | P49: =SUM(C49+G49+I49+M49) -> 1 | Q49: =SUM(D49+H49+L49+N49+O49) -> 369.98 | R49: =Q49/P49 -> 369.98
B50: AUGUST | C50: 0 | D50: 0 | G50: 0 | H50: 0 | I50: 1 | L50: 336.86 | M50: 0 | N50: 0 | O50: 0 | P50: =SUM(C50+G50+I50+M50) -> 1 | Q50: =SUM(D50+H50+L50+N50+O50) -> 336.86 | R50: =Q50/P50 -> 336.86
B51: SEPTEMBER | C51: 0 | D51: 0 | G51: 0 | H51: 0 | I51: 2 | L51: 861.66 | M51: 0 | N51: 0 | O51: 0 | P51: =SUM(C51+G51+I51+M51) -> 2 | Q51: =SUM(D51+H51+L51+N51+O51) -> 861.66 | R51: =Q51/P51 -> 430.83
B52: OCTOBER | P52: =SUM(C52+G52+I52+M52) -> 0 | Q52: =SUM(D52+H52+L52+N52+O52) -> 0 | R52: =Q52/P52 -> #DIV/0!
B53: NOVEMBER | P53: =SUM(C53+G53+I53+M53) -> 0 | Q53: =SUM(D53+H53+L53+N53+O53) -> 0 | R53: =Q53/P53 -> #DIV/0!
B54: DECEMBER | P54: =SUM(C54+G54+I54+M54) -> 0 | Q54: =SUM(D54+H54+L54+N54+O54) -> 0 | R54: =Q54/P54 -> #DIV/0!
C55: =SUM(C43:C54) -> 0 | D55: =SUM(D43:D54) -> 0 | G55: =SUM(G43:G54) -> 0 | H55: =SUM(H43:H54) -> 0 | I55: =SUM(I43:I54) -> 11 | L55: =SUM(L43:L54) -> 5305.97 | M55: =SUM(M43:M54) -> 0 | N55: =SUM(N43:N54) -> 0 | P55: =SUM(P43:P54) -> 11 | Q55: =SUM(Q43:Q54) -> 5305.97 | R55: =Q55/P55 -> 482.36091
I57: Average Per Month : | L57: =(Q19/(COUNTA(C7:C18))) -> 122831.78 | M57: HINO
I58: Average Per Month : | L58: =(Q37/(COUNTA(C25:C36))) -> 107075.07 | M58: MITSUBUSHI
I59: Average Per Month : | L59: =Q55/(COUNTA(C43:C54)) -> 589.55222 | M59: AFTER SALES SERVICE
P60: B&P Sales %
D61: Hino | G61: Mitsubishi | I61: B&P | L61: Service | N61: Total | P61: Hino | Q61: Mitsubishi | R61: Service
B62: Total Insurance | D62: =SUM(D19+I19) -> 929828.29 | G62: =SUM(D37+I37) -> 735490.23 | I62: =D62+G62 -> 1665318.5 | L62: =D55+H55+N55 -> 0 | N62: =SUM(I62:M62) -> 1665318.5 | P62: =SUM(D62/N62) -> 0.55834862 | Q62: =SUM(G62/N62) -> 0.44165138 | R62: =L62/N62 -> 0
B63: Total WindScreen | D63: =SUM(I19:L19) -> 8643.48 | G63: =SUM(I37:L37) -> 69465.9 | I63: =D63+G63 -> 78109.38 | N63: =SUM(I63:M63) -> 78109.38 | P63: =SUM(D63/N63) -> 0.11065867 | Q63: =SUM(G63/N63) -> 0.88934133 | R63: =L63/N63 -> 0
B64: Total Cash Job | D64: =G19+L19+N19 -> 9084 | G64: =G37+L37+N37 -> 2599.9 | I64: =D64+G64 -> 11683.9 | L64: =L55 -> 5305.97 | N64: =SUM(I64:M64) -> 16989.87 | P64: =SUM(D64/N64) -> 0.53467154 | Q64: =SUM(G64/N64) -> 0.15302648 | R64: =L64/N64 -> 0.31230198
B65: Others | D65: =O19 -> 0 | G65: =O37 -> 44383.35 | I65: =D65+G65 -> 44383.35 | N65: =SUM(I65:M65) -> 44383.35
B66: Total : | D66: =SUM(D62:D65)-I19 -> 941306.29 | G66: =SUM(G62:G65)-I37 -> 790397.38 | I66: =SUM(I62:I65)-I63 -> 1721385.8 | L66: =SUM(L62:L65) -> 5305.97 | N66: =SUM(N62:N65)-N63 -> 1726691.7 | P66: - | Q66: -

Sheet MITSUBISHI MEETING
C2: MITSUBISHI
B3: YA 2024 | C3: ACCIDENT | H3: WINDSCREEN | M3: OTHERS | P3: TOTAL
C4: INTAKE | D4: INS - PARTS | E4: INS - LABOURS | F4: CREDIT | G4: CASH | H4: INTAKE | I4: INS - PARTS | J4: INS - LABOURS | K4: CREDIT | L4: CASH | M4: INTAKE | N4: CASH | O4: CREDIT | P4: INTAKE | Q4: TOTAL | R4: Avg
B5: 45231 | C5: 0 | D5: 0 | E5: 0 | F5: 0 | G5: 0 | H5: 1 | I5: 1084.9 | J5: 228 | K5: 0 | L5: 0 | M5: 1 | N5: 600 | O5: 0 | P5: =SUM(C5+H5+M5) -> 2 | Q5: =SUM(D5+E5+F5+G5+I5+J5+K5+L5+N5+O5) -> 1912.9 | R5: =Q5/P5 -> 956.45
B6: 45261 | C6: 6 | D6: 72705.35 | E6: 21240 | H6: 3 | I6: 5679.72 | J6: 816 | K6: 0 | L6: 0 | M6: 1 | N6: 900 | O6: 0 | P6: =SUM(C6+H6+M6) -> 10 | Q6: =SUM(D6+E6+F6+G6+I6+J6+K6+L6+N6+O6) -> 101341.07 | R6: =Q6/P6 -> 10134.107
B7: 45292 | C7: 7 | D7: 93567.1 | E7: 30384 | G7: 0 | H7: 5 | I7: 9659.41 | J7: 1248 | K7: 0 | L7: 0 | M7: 1 | N7: 1400 | O7: 0 | P7: =SUM(C7+H7+M7) -> 13 | Q7: =SUM(D7+E7+F7+G7+I7+J7+K7+L7+N7+O7) -> 136258.51 | R7: =Q7/P7 -> 10481.424
B8: 45323 | C8: 2 | D8: 52204.13 | E8: 7488 | G8: 0 | H8: 1 | I8: 2237.22 | J8: 240 | K8: 0 | L8: 0 | M8: 1 | N8: 0 | O8: 10870.95 | P8: =SUM(C8+H8+M8) -> 4 | Q8: =SUM(D8+E8+F8+G8+I8+J8+K8+L8+N8+O8) -> 73040.3 | R8: =Q8/P8 -> 18260.075
B9: 45352 | C9: 7 | D9: 82354.95 | E9: 23040 | F9: 8699.63 | G9: 0 | H9: 4 | I9: 6231.13 | J9: 1266 | K9: 0 | L9: 2131.1 | M9: 2 | N9: 1344.1 | O9: 0 | P9: =SUM(C9+H9+M9) -> 13 | Q9: =SUM(D9+E9+F9+G9+I9+J9+K9+L9+N9+O9) -> 125066.91 | R9: =Q9/P9 -> 9620.5315
C10: =SUM(C5:C9) -> 22 | D10: =SUM(D5:D9) -> 300831.53 | E10: =SUM(E5:E9) -> 82152 | F10: =SUM(F5:F9) -> 8699.63 | G10: =SUM(G5:G9) -> 0 | H10: =SUM(H5:H9) -> 14 | I10: =SUM(I5:I9) -> 24892.38 | J10: =SUM(J5:J9) -> 3798 | ... Q10: =SUM(Q5:Q9) -> 437619.69
C15: MITSUBISHI
B16: YA 2025 | C16: ACCIDENT | H16: WINDSCREEN | M16: OTHERS | P16: TOTAL
C17: INTAKE | D17: INS - PARTS | E17: INS - LABOURS | F17: CREDIT | G17: CASH | H17: INTAKE | I17: INS - PARTS | J17: INS - LABOURS | K17: CREDIT | L17: CASH | M17: INTAKE | N17: CASH | O17: CREDIT | P17: INTAKE | Q17: TOTAL | R17: Avg
B18: 45383 | C18: 7 | D18: 82116.35 | E18: 22728 | F18: 10184.71 | G18: 0 | H18: 6 | I18: 11876.13 | J18: 1428 | K18: 0 | L18: 0 | M18: 4 | N18: 0 | O18: 1130 | P18: =SUM(C18+H18+M18) -> 17 | Q18: =SUM(D18+E18+F18+G18+I18+J18+K18+L18+N18+O18) -> 129463.19 | R18: =Q18/P18 -> 7615.4818
B19: 45413 | C19: 10 | D19: 83909.6 | E19: 26700 | F19: 712.5 | G19: 0 | H19: 3 | I19: 4617.89 | J19: 720 | K19: 0 | L19: 0 | M19: 6 | N19: 0 | O19: 2705.85 | P19: =SUM(C19+H19+M19) -> 19 | Q19: =SUM(D19+E19+F19+G19+I19+J19+K19+L19+N19+O19) -> 119365.84 | R19: =Q19/P19 -> 6282.4126
B20: 45444 | C20: 5 | D20: 66073.51 | E20: 18072 | F20: 0 | G20: 1528.86 | H20: 5 | I20: 8742.65 | J20: 1164 | K20: 0 | L20: 0 | M20: 0 | N20: 0 | O20: 0 | P20: =SUM(C20+H20+M20) -> 10 | Q20: =SUM(D20+E20+F20+G20+I20+J20+K20+L20+N20+O20) -> 95581.02 | R20: =Q20/P20 -> 9558.102
B21: 45474 | C21: 9 | D21: 162237.65 | E21: 41439 | F21: 6368.37 | G21: 0 | H21: 5 | I21: 6771.83 | J21: 912 | K21: 0 | L21: 0 | M21: 0 | N21: 0 | O21: 0 | P21: =SUM(C21+H21+M21) -> 14 | Q21: =SUM(D21+E21+F21+G21+I21+J21+K21+L21+N21+O21) -> 217728.85 | R21: =Q21/P21 -> 15552.061
B22: 45505 | C22: 10 | D22: 72365.72 | E22: 33528 | F22: 5076.27 | G22: 0 | H22: 3 | I22: 7186.78 | J22: 792 | K22: 0 | L22: 0 | M22: 4 | N22: 300 | O22: 6811.39 | P22: =SUM(C22+H22+M22) -> 17 | Q22: =SUM(D22+E22+F22+G22+I22+J22+K22+L22+N22+O22) -> 126060.16 | R22: =Q22/P22 -> 7415.3035
B23: 45536 | C23: 5 | D23: 56523.05 | E23: 24036 | F23: 0 | G23: 0 | H23: 5 | I23: 10975.58 | J23: 1320 | K23: 0 | L23: 0 | M23: 4 | N23: 2102.1 | O23: 930 | P23: =SUM(C23+H23+M23) -> 14 | Q23: =SUM(D23+E23+F23+G23+I23+J23+K23+L23+N23+O23) -> 95886.73 | R23: =Q23/P23 -> 6849.0521
B24: 45566 | C24: 8 | D24: 166938.41 | E24: 28158 | F24: 2907 | G24: 0 | H24: 7 | I24: 14217.34 | J24: 1860 | K24: 0 | L24: 0 | M24: 3 | N24: 7884.81 | O24: 1961 | P24: =SUM(C24+H24+M24) -> 18 | Q24: =SUM(D24+E24+F24+G24+I24+J24+K24+L24+N24+O24) -> 223926.56 | R24: =Q24/P24 -> 12440.364
B25: 45597 | C25: 9 | D25: 68433.45 | E25: 17389 | F25: 4421.28 | G25: 0 | H25: 4 | I25: 8353.54 | J25: 1032 | K25: 0 | L25: 0 | M25: 0 | N25: 0 | O25: 0 | P25: =SUM(C25+H25+M25) -> 13 | Q25: =SUM(D25+E25+F25+G25+I25+J25+K25+L25+N25+O25) -> 99629.27 | R25: =Q25/P25 -> 7663.79
B26: 45627 | C26: 2 | D26: 59314.97 | E26: 7476 | F26: 1320.5 | G26: 0 | H26: 7 | I26: 11923.41 | J26: 1776 | K26: 951.48 | L26: 0 | M26: 0 | N26: 0 | O26: 0 | P26: =SUM(C26+H26+M26) -> 9 | Q26: =SUM(D26+E26+F26+G26+I26+J26+K26+L26+N26+O26) -> 82762.36 | R26: =Q26/P26 -> 9195.8178
B27: 45658 | C27: 10 | D27: 98603.04 | E27: 36816 | F27: 0 | G27: 515 | H27: 2 | I27: 4181.87 | J27: 528 | K27: 0 | L27: 0 | M27: 1 | N27: 0 | O27: 115 | P27: =SUM(C27+H27+M27) -> 13 | Q27: =D27+E27+F27+G27+I27+J27+K27+L27+N27+O27 -> 140758.91 | R27: =Q27/P27 -> 10827.608
B28: 45689 | C28: 8 | D28: 88403.77 | E28: 27570 | F28: 0 | G28: 0 | H28: 4 | I28: 7232.75 | J28: 1068 | K28: 0 | L28: 350 | M28: 1 | N28: 1603.8 | O28: 0 | P28: =SUM(C28+H28+M28) -> 13 | Q28: =D28+E28+F28+G28+I28+J28+K28+L28+N28+O28 -> 126228.32 | R28: =Q28/P28 -> 9709.8708
B29: 45717 | C29: 9 | D29: 78790.87 | E29: 26745.6 | F29: 1977.05 | G29: 0 | H29: 6 | I29: 14086.82 | J29: 1476 | K29: 1027.98 | L29: 0 | M29: 1 | N29: 1242.2 | O29: 0 | P29: =SUM(C29+H29+M29) -> 16 | Q29: =D29+E29+F29+G29+I29+J29+K29+L29+N29+O29 -> 125346.52 | R29: =Q29/P29 -> 7834.1575
C30: =SUM(C18:C29) -> 92 | D30: =SUM(D18:D29) -> 1083710.4 | E30: =SUM(E18:E29) -> 310657.6 | F30: =SUM(F18:F29) -> 32967.68 | G30: =SUM(G18:G29) -> 2043.86 | H30: =SUM(H18:H29) -> 57 | I30: =SUM(I18:I29) -> 110166.59 | J30: =SUM(J18:J29) -> 14076 | ... Q30: =SUM(Q18:Q29) -> 1582737.7 | R30: =Q30/P30 -> 9148.773

Sheet HINO 2025
A1: TRANSNO | B1: MONTH | C1: DATE | D1: CUSTOMER NAME | E1: REG NO | F1: JOBNO | G1: P.TOTAL | H1: L.TOTAL | I1: GTOTAL | J1: DISC | K1: TOTAL | L1: SVC TYPE
A2: HBPSI2501001 | B2: JAN | C2: 45661 | D2: EDARAN RIZ SDN BHD | E2: NDS8129 | F2: HBPWO2412002 | G2: 13107.13 | H2: 3960 | I2: 17067.13 | J2: 0 | K2: 17067.13 | L2: OD
A3: HBPSI2501002 | B3: JAN | C3: 45675 | D3: EDARAN RIZ SDN BHD | E3: DDQ3939 | F3: HBPWO2410001 | G3: 49101.56 | H3: 15900 | I3: 65001.56 | J3: 0 | K3: 65001.56 | L3: OD
A4: HBPSI2501003 | B4: JAN | C4: 45678 | D4: EDARAN RIZ SDN BHD | E4: CDL9638 | F4: HBPWO2501005 | G4: 908.52 | H4: 480 | I4: 1388.52 | J4: 0 | K4: 1388.52 | L4: WS
A5: HBPSI2502001 | B5: FEB | C5: 45692 | D5: EDARAN RIZ SDN BHD | E5: BRJ2698 | F5: HBPWO2501003 | G5: 18369.73 | H5: 3024 | I5: 21393.73 | J5: 0 | K5: 21393.73 | L5: OD
A6: HBPSI2502002 | B6: FEB | C6: 45693 | D6: EDARAN RIZ SDN BHD | E6: CCK8261 | F6: HBPWO2501004 | G6: 3354.59 | H6: 1308 | I6: 4662.59 | J6: 0 | K6: 4662.59 | L6: OD
A7: HBPSI2502003 | B7: FEB | C7: 45701 | D7: EDARAN RIZ SDN BHD | E7: PPS6686 | F7: HBPWO2502001 | G7: 973.08 | H7: 420 | I7: 1393.08 | J7: 0 | K7: 1393.08 | L7: WS
A8: HBPSI2502004 | B8: FEB | C8: 45703 | D8: EDARAN RIZ SDN BHD | E8: JWG7787 | F8: HBPWO2501001 | G8: 40851.62 | H8: 2760 | I8: 43611.62 | J8: 0 | K8: 43611.62 | L8: OD
A9: HBPSI2502005 | B9: FEB | C9: 45705 | D9: EDARAN RIZ SDN BHD | E9: VAW6836 | F9: HBPWO2412003 | G9: 16670.74 | H9: 4668 | I9: 21338.74 | J9: 0 | K9: 21338.74 | L9: OD
A10: HBPSI2502006 | B10: FEB | C10: 45706 | D10: EDARAN RIZ SDN BHD | E10: CCK3900 | F10: HBPWO2501007 | G10: 23481.66 | H10: 3000 | I10: 26481.66 | J10: 0 | K10: 26481.66 | L10: OD
A11: HBPSI2503001 | B11: MAR | C11: 45727 | D11: EDARAN RIZ SDN BHD | E11: VBQ5526 | F11: HBPWO2503002 | G11: 973.08 | H11: 420 | I11: 1393.08 | J11: 0 | K11: 1393.08 | L11: WS
A12: HBPSI2503002 | B12: MAR | C12: 45733 | D12: EDARAN RIZ SDN BHD | E12: VAB1218 | F12: HBPWO2503004 | G12: 973.08 | H12: 420 | I12: 1393.08 | J12: 0 | K12: 1393.08 | L12: WS
A13: HBPSI2503003 | B13: MAR | C13: 45736 | D13: EDARAN RIZ SDN BHD | E13: VNE6271 | F13: HBPWO2412004 | G13: 110273.46 | H13: 5028 | I13: 115301.46 | J13: 0 | K13: 115301.46 | L13: OD
... A18: HBPSI2504004 | B18: APR | C18: 45777 | D18: EDARAN RIZ SDN BHD | E18: CCK1925 | F18: HBPWO2503007 | G18: 18687.64 | H18: 2700 | I18: 21387.64 | J18: 0 | K18: 21387.64 | L18: OD
A19: HBPSI2505001 | B19: MAY | C19: 45785 | D19: LAUNDRY CARE SDN BHD | E19: VND1146 | F19: HBPWO2505002 | G19: 825 | H19: 150 | I19: 975 | K19: 975 | L19: CR
A20: HBPSI2505002 | B20: MAY | C20: 45787 | D20: EDARAN RIZ SDN BHD | E20: VJN8266 | F20: HBPWO2503003 | G20: 9344.94 | H20: 5664 | I20: 15008.94 | J20: 0 | K20: 15008.94 | L20: OD
A21: HBPSI2505003 | B21: MAY | C21: 45792 | D21: EDARAN RIZ SDN BHD | E21: VND1146 | F21: HBPWO2503008 | G21: 13816.58 | H21: 1572 | I21: 15388.58 | J21: 0 | K21: 15388.58 | L21: OD
A22: HBPSI2505004 | B22: MAY | C22: 45801 | D22: EDARAN RIZ SDN BHD | E22: VND1146 | F22: HBPWO2505003 | G22: 973.08 | H22: 420 | I22: 1393.08 | J22: 0 | K22: 1393.08 | L22: WS
A23: HBPSI2505005 | B23: MAY | C23: 45803 | D23: EDARAN RIZ SDN BHD | E23: TBX3119 | F23: HBPWO2501008 | G23: 15972.39 | H23: 14124 | I23: 30096.39 | J23: 0 | K23: 30096.39 | L23: OD
A24: HBPSI2506001 | B24: JUNE | C24: 45812 | D24: EDARAN RIZ SDN BHD | E24: VBN9692 | F24: HBPWO2502003 | G24: 42337.94 | H24: 4356 | I24: 46693.94 | J24: 0 | K24: 46693.94 | L24: OD
A25: HBPSI2506002 | B25: JUNE | C25: 45817 | D25: EDARAN RIZ SDN BHD | E25: CES7371 | F25: HBPWO2504007 | G25: 22228.46 | H25: 1930.8 | I25: 24159.26 | J25: 0 | K25: 24159.26 | L25: OD
A26: HBPSI2506003 | B26: JUNE | C26: 45832 | D26: EDARAN RIZ SDN BHD | E26: BQE8701 | F26: HBPWO2505001 | G26: 27736.32 | H26: 6960 | I26: 34696.32 | J26: 0 | K26: 34696.32 | L26: OD
A27: HBPSI2507001 | B27: JULY | C27: 45845 | D27: EDARAN RIZ SDN BHD | E27: TCM6638 | F27: HBPWO2504006 | G27: 53842.38 | H27: 2676 | I27: 56518.38 | J27: 0 | K27: 56518.38 | L27: OD
A28: HBPSI2507002 | B28: JULY | C28: 45849 | D28: EDARAN RIZ SDN BHD | E28: BQE8701 | F28: HBPWO2507002 | G28: 2419.97 | H28: 180 | I28: 2599.97 | J28: 0 | K28: 2599.97 | L28: OD
A29: HBPSI2507003 | B29: JULY | C29: 45849 | D29: EDARAN RIZ SDN BHD | E29: VHR2203 | F29: HBPWO2506002 | G29: 19871.92 | H29: 6144 | I29: 26015.92 | J29: 0 | K29: 26015.92 | L29: OD
A30: HBPSI2507004 | B30: JULY | C30: 45853 | D30: EDARAN RIZ SDN BHD | E30: VHA8821 | F30: HBPWO2503001 | G30: 35499.46 | H30: 18948 | I30: 54447.46 | J30: 0 | K30: 54447.46 | L30: OD
A31: HBPSI2507005 | B31: JULY | C31: 45853 | D31: EDARAN RIZ SDN BHD | E31: PQX6686 | F31: HBPWO2507001 | G31: 1258.08 | H31: 420 | I31: 1678.08 | J31: 0 | K31: 1678.08 | L31: WS
A32: HBPSI2507006 | B32: JULY | C32: 45862 | D32: EDARAN RIZ SDN BHD | E32: VJP6332 | F32: HBPWO2504005 | G32: 64600 | I32: 64600 | J32: 0 | K32: 64600 | L32: OD
A33: HBPSI2507007 | B33: JULY | C33: 45862 | D33: EDARAN RIZ SDN BHD | E33: KFV6117 | F33: HBPWO2507004 | G33: 973.08 | H33: 420 | I33: 1393.08 | J33: 0 | K33: 1393.08 | L33: WS
A34: HBPSI2507008 | B34: JULY | C34: 45867 | D34: EDARAN RIZ SDN BHD | E34: KFV6117 | F34: HBPWO2507006 | H34: 96 | I34: 96 | K34: 96 | L34: SERVICE FOR PUSPAKOM CHECKING
A35: HBPSI2507009 | B35: JULY | C35: 45869 | D35: EDARAN RIZ SDN BHD | E35: VBG8310 | F35: HBPWO2505004 | G35: 20673.84 | H35: 3240 | I35: 23913.84 | J35: 0 | K35: 23913.84 | L35: OD
A36: HBPSI2507010 | B36: JULY | C36: 45869 | D36: EDARAN RIZ SDN BHD | E36: TCU6118 | F36: HBPWO2504004 | G36: 76000 | I36: 76000 | J36: 0 | K36: 76000 | L36: OD
A37: HBPSI2508001 | B37: AUG | C37: 45885 | D37: EDARAN RIZ SDN BHD | E37: VKN6872 | F37: HBPWO2508001 | G37: 893.76 | H37: 228 | I37: 1121.76 | J37: 0 | K37: 1140 | L37: WS
A38: HBPSI2508002 | B38: AUG | C38: 45885 | D38: EDARAN RIZ SDN BHD | E38: VMB7073 | F38: HBPWO2507005 | G38: 5367.5 | H38: 2736 | I38: 8103.5 | J38: 0 | K38: 8322.38 | L38: OD
A39: HBPSI2508003 | B39: AUG | C39: 45889 | D39: EDARAN RIZ SDN BHD | E39: VMH8922 | F39: HBPWO2508006 | G39: 4682.57 | H39: 1653 | I39: 6335.57 | J39: 0 | K39: 6467.81 | L39: OD
A40: HBPSI2508004 | B40: AUG | C40: 45894 | D40: EDARAN RIZ SDN BHD | E40: VPK5422 | F40: HBPWO2508007 | G40: 994.08 | H40: 399 | I40: 1393.08 | J40: 0 | K40: 1425 | L40: WS
A41: HBPSI2509001 | B41: SEP | C41: 45906 | D41: EDARAN RIZ SDN BHD | E41: CCR8626 | F41: HBPWO2507007 | G41: 1947.5 | H41: 5962.2 | I41: 7909.7 | J41: 0 | K41: 8386.68 | L41: OD
A42: HBPSI2509002 | B42: SEP | C42: 45912 | D42: EDARAN RIZ SDN BHD | E42: TCY8339 | F42: HBPWO2508008 | G42: 3972.38 | H42: 1664.4 | I42: 5636.78 | J42: 0 | K42: 5636.78 | L42: OD
A43: HBPSI2509003 | B43: SEP | C43: 45913 | D43: EDARAN RIZ SDN BHD | E43: VBQ5526 | F43: HBPWO2509002 | G43: 994.08 | H43: 399 | I43: 1393.08 | J43: 0 | K43: 1425 | L43: WS
A44: HBPSI2509004 | B44: SEP | C44: 45920 | D44: EDARAN RIZ SDN BHD | E44: BSA7328 | F44: HBPWO2501009 | G44: 2701.72 | H44: 1140 | I44: 3841.72 | J44: 0 | K44: 3932.92 | L44: OD
A45: HBPSI2509005 | B45: SEP | C45: 45924 | D45: EDARAN RIZ SDN BHD | E45: PKS6199 | F45: HBPWO2509006 | H45: 760 | I45: 760 | J45: 0 | K45: 820.8 | L45: CR
A46: HBPSI2509006 | B46: SEP | C46: 45930 | D46: EDARAN RIZ SDN BHD | E46: VJG5093 | F46: HBPWO2504001 | G46: 73672.58 | H46: 7421.4 | I46: 81093.98 | J46: 0 | K46: 81687.69 | L46: OD
A47: HBPSI2510001 | B47: OCT | C47: 45931 | D47: EDARAN RIZ SDN BHD | E47: SYU1218 | F47: HBPWO2509010 | G47: 994.08 | H47: 399 | I47: 1393.08 | J47: 0 | K47: 1425 | L47: WS
A48: HBPSI2510002 | B48: OCT | C48: 45938 | D48: EDARAN RIZ SDN BHD | E48: CEK9938 | F48: HBPWO2510002 | G48: 11491 | H48: 969 | I48: 12460 | J48: 0 | K48: 12537.52 | L48: OD
A49: HBPSI2510003 | B49: OCT | C49: 45940 | D49: EDARAN RIZ SDN BHD | E49: AES53 | F49: HBPWO2503006 | G49: 36212.21 | H49: 7361.55 | I49: 43573.76 | J49: 0 | K49: 44162.68 | L49: OD
A50: HBPSI2510004 | B50: OCT | C50: 45951 | D50: EDARAN RIZ SDN BHD | E50: BQE8707 | F50: HBPWO2510004 | G50: 329.08 | H50: 399 | I50: 728.08 | J50: 0 | K50: 760 | L50: WS
A51: HBPSI2510005 | B51: OCT | C51: 45955 | D51: EDARAN RIZ SDN BHD | E51: VAQ8667 | F51: HBPWO2509005 | G51: 7788.24 | H51: 1744.2 | I51: 9532.44 | J51: 0 | K51: 9671.98 | L51: OD
A52: HBPSI2510006 | B52: OCT | C52: 45958 | D52: EDARAN RIZ SDN BHD | E52: VLM7620 | F52: HBPWO2507003 | G52: 56101.97 | H52: 9405 | I52: 65506.97 | J52: 0 | K52: 66259.37 | L52: OD
A53: HBPSI2510007 | B53: OCT | C53: 45958 | D53: EDARAN RIZ SDN BHD | E53: NEA7298 | F53: HBPWO2510006 | G53: 709.08 | H53: 399 | I53: 1108.08 | J53: 0 | K53: 1140 | L53: WS
A54: HBPSI2510008 | B54: OCT | C54: 45958 | D54: EDARAN RIZ SDN BHD | E54: VJV2210 | F54: HBPWO2509001 | G54: 34862.09 | H54: 6623.4 | I54: 41485.49 | J54: 0 | K54: 42015.36 | L54: OD
A55: HBPSI2510009 | B55: OCT | C55: 45959 | D55: EDARAN RIZ SDN BHD | E55: TBX3119 | F55: HBPWO2509004 | G55: 11425.38 | H55: 3876 | I55: 15301.38 | J55: 0 | K55: 15611.46 | L55: OD
A56: HBPSI2511001 | B56: NOV | C56: 45965 | D56: EDARAN RIZ SDN BHD | E56: VET1482 | F56: HBPWO2508009 | G56: 41965.96 | H56: 8515.8 | I56: 50481.76 | J56: 0 | K56: 51163.02 | L56: OD
A57: HBPSI2511002 | B57: NOV | C57: 45965 | D57: EDARAN RIZ SDN BHD | E57: BSA7328 | F57: HBPWO2511001 | G57: 2748.12 | H57: 114 | I57: 2862.12 | J57: 0 | K57: 2871.24 | L57: OD
... A66: HBPSI2512003 | B66: DEC | C66: 46018 | D66: EDARAN RIZ SDN BHD | E66: DDF2289 | F66: HBPWO2511003 | G66: 15263.94 | H66: 10054.8 | I66: 25318.74 | J66: 0 | K66: 26123.12 | L66: OD
I73: =SUM(I2:I66)-I34 -> 1636192.8
A75: INVOICE LISTING
A76: TRANSNO | B76: MONTH | C76: DATE | D76: CUSTOMER NAME | E76: REFERENCE | F76: TOTAL | G76: DN | H76: G.TOTAL
A77: HBPIV2501001 | B77: JAN | C77: 45678 | D77: EDARAN RIZ SDN BHD | E77: VED7588 | F77: 950 | H77: 950 | I77: OD | J77: CREDIT
A78: HBPIV2502001 | B78: FEB | C78: 45692 | D78: EDARAN RIZ SDN BHD | E78: BRJ2698 | F78: 2280 | H78: 2280 | I78: OD | J78: CREDIT
A79: HBPIV2504001 | B79: APR | C79: 45757 | D79: EDARAN RIZ SDN BHD | E79: VED7588 | F79: 1957 | H79: 1957 | I79: OD | J79: CREDIT
A80: HBPIV2504002 | B80: APR | C80: 45770 | D80: EDARAN RIZ SDN BHD | E80: KEM6686 | F80: 950 | H80: 950 | I80: OD | J80: CREDIT
A81: HBPIV2505001 | B81: MAY | C81: 45786 | D81: EDARAN RIZ SDN BHD | E81: TBX3119 | F81: 6615.37 | H81: 6615.37 | I81: OD
A82: HBPIV2506001 | B82: JUNE | C82: 45820 | D82: EDARAN RIZ SDN BHD | E82: CES7371 | F82: 2280 | H82: 2280 | I82: OD
A83: HBPIV2506002 | B83: JUNE | C83: 45820 | D83: EDARAN RIZ SDN BHD | E83: AMT9133 | F83: 1180 | H83: 1180 | I83: OD
A84: HBPIV2506003 | B84: JUNE | C84: 45825 | D84: EDARAN RIZ SDN BHD | E84: WYN442 | F84: 1550 | H84: 1550 | I84: OD
A85: HBPIV2506004 | B85: JUNE | C85: 45832 | D85: EDARAN RIZ SDN BHD | E85: VHA8821 | F85: 1368 | H85: 1368 | I85: OD
A86: HBPIV2507001 | B86: JULY | C86: 45847 | D86: EDARAN RIZ SDN BHD | E86: WYN442 | F86: 2261 | H86: 2261 | I86: OD
A87: HBPIV2507002 | B87: JULY | C87: 45869 | D87: EDARAN RIZ SDN BHD | E87: VMX3368 | F87: 7.56 | H87: 7.56 | I87: MERIMEN
A88: HBPIV2509001 | B88: SEP | C88: 45904 | D88: DIESEL TUNING SDN BHD | F88: 5800 | G88: 500 | H88: =F88+G88 -> 6300 | I88: PART PURCHASE | J88: CASH
A89: HBPIV2509002 | B89: SEP | C89: 45926 | D89: EDARAN RIZ SDN BHD | E89: AMT9133 | F89: 3935 | H89: 3935 | I89: OD
A90: HBPIV2511001 | B90: NOV | C90: 45974 | D90: EDARAN RIZ SDN BHD | E90: JWL6113 | F90: 7050 | H90: 7050 | I90: OD
A91: HBPIV2511002 | B91: NOV | C91: 45974 | D91: EDARAN RIZ SDN BHD | E91: JXM1435 | F91: 2470 | H91: 2470 | I91: OD
A92: HBPIV2512001 | B92: DEC | C92: 45995 | D92: EDARAN RIZ SDN BHD | E92: PPE4246 | F92: 950 | H92: 950 | I92: OD
H94: =SUM(H77:H91)-H87+H92 -> 42096.37

Sheet SERVICE 2026
A1: TRANSNO | B1: MONTH | C1: DATE | D1: CUSTOMER NAME | E1: REG NO | F1: JOBNO | G1: P.TOTAL | H1: L.TOTAL | I1: GTOTAL | J1: DISC | K1: TOTAL | L1: SVC TYPE
A2: FASSI2609001 | B2: Sept | C2: 46288 | D2: LHL MARKETING | E2: AMR 3233 | F2: FASWO2609001 | G2: 248.84 | H2: 88 | I2: =+G2+H2+0.02 -> 336.86 | J2: 0 | K2: =+I2 -> 336.86 | L2: CR
A3: FASSI2609002 | B3: Sept | C3: 46289 | D3: ASMAWI CONSTRUCTION | E3: VLW 3392 | F3: FASWO2609002 | G3: 300.8 | H3: 224 | I3: =+G3+H3 -> 524.8 | J3: 0 | K3: =+I3 -> 524.8 | L3: CR
P9: = TRADING INV
G11: =SUM(G2:G10) -> 549.64 | H11: =SUM(H2:H10) -> 312 | I11: =SUM(I2:I10) -> 861.66 | J11: =SUM(J2:J10) -> 0 | K11: =SUM(K2:K10) -> 861.66
A22: INVOICE LISTING
A23: TRANSNO | B23: MONTH | C23: DATE | D23: CUSTOMER NAME | E23: REFERENCE | F23: TOTAL | G23: DN | H23: G.TOTAL | I23: SVC TYPE
H26: =SUM(H24:H25) -> 0

Sheet HINO 2026
A1: TRANSNO | B1: MONTH | C1: DATE | D1: CUSTOMER NAME | E1: REG NO | F1: JOBNO | G1: P.TOTAL | H1: L.TOTAL | I1: GTOTAL | J1: DISC | K1: TOTAL | L1: SVC TYPE
A2: HBPSI2609001 | B2: Sept | C2: 46269 | D2: EDARAN RIZ SDN BHD | E2: CFA 3176 | F2: HBPWO2603005 | G2: 59446.52 | H2: 5814 | I2: =+G2+H2 -> 65260.52 | J2: 0 | K2: =+I2 -> 65260.52 | L2: OD
A3: HBPSI2609002 | B3: Sept | C3: 46289 | D3: EDARAN RIZ SDN BHD | E3: SYU 1218 | F3: HBPWO2609002 | G3: 994.08 | H3: 399 | I3: =+G3+H3 -> 1393.08 | J3: 0 | K3: =+I3 -> 1393.08 | L3: WS
A4: HBPSI2609003 | B4: Sept | C4: 46291 | D4: EDARAN RIZ SDN BHD | E4: VKW 1600 | F4: HBPWO2604002 | G4: 0 | H4: 0 | I4: =+G4+H4 -> 0 | J4: 0 | K4: =+I4 -> 0 | L4: -
J5: 0 | K5: =+I5 -> 0
J6: 0 | K6: =+I6 -> 0
J7: 0 | K7: =+I7 -> 0
J8: 0 | K8: =+I8 -> 0
J9: 0 | K9: =+I9 -> 0
G11: =SUM(G2:G10) -> 60440.6 | H11: =SUM(H2:H10) -> 6213 | I11: =SUM(I2:I10) -> 66653.6 | J11: =SUM(J2:J10) -> 0 | K11: =SUM(K2:K10) -> 66653.6
A17: INVOICE LISTING
A18: TRANSNO | B18: MONTH | C18: DATE | D18: CUSTOMER NAME | E18: REFERENCE | F18: TOTAL | G18: DN | H18: G.TOTAL | I18: SVC TYPE
A19: HBPIV2609001 | B19: Sept | C19: 46291 | D19: EDARAN RIZ SDN BHD | E19: PPE 4246 | F19: 3515 | G19: 0 | H19: =+F19+G19 -> 3515 | I19: STORAGE FEE

Sheet MITS 2025
A1: TRANSNO | B1: MONTH | C1: DATE | D1: CUSTOMER NAME | E1: REG NO | F1: JOBNO | G1: P.TOTAL | H1: L.TOTAL | I1: GTOTAL | J1: DISC | K1: TOTAL | L1: SVC TYPE
A2: MBPSI2501001 | B2: JAN | C2: 45663 | D2: AUTO RAYA TIMUR SDN BHD | E2: BRV5220 | F2: MBPWO2412002 | G2: 13852.3 | H2: 2520 | I2: 16372.3 | K2: 16372.3 | L2: OD
A3: MBPSI2501002 | B3: JAN | C3: 45664 | D3: AUTO RAYA TIMUR SDN BHD | E3: XX6557 | F3: MBPWO2412015 | G3: 2578.85 | H3: 252 | I3: 2830.85 | K3: 2830.85 | L3: WS
A4: MBPSI2501003 | B4: JAN | C4: 45665 | D4: AUTO RAYA TIMUR SDN BHD | E4: VHP42 | F4: MBPWO2412007 | G4: 15403.73 | H4: 3972 | I4: 19375.73 | K4: 19375.73 | L4: OD
A5: MBPSI2501004 | B5: JAN | C5: 45665 | D5: AUTO RAYA TIMUR SDN BHD | E5: CEW4342 | F5: MBPWO2412013 | G5: 2296.44 | H5: 2280 | I5: 4576.44 | K5: 4576.44 | L5: OD
A6: MBPSI2501005 | B6: JAN | C6: 45666 | D6: AUTO RAYA TIMUR SDN BHD | E6: DEP6000 | F6: MBPWO2501002 | G6: 1603.02 | H6: 276 | I6: 1879.02 | K6: 1879.02 | L6: WS
A7: MBPSI2501006 | B7: JAN | C7: 45666 | D7: AUTO RAYA TIMUR SDN BHD | E7: CEW8916 | F7: MBPWO2412011 | G7: 6005.53 | H7: 3948 | I7: 9953.53 | K7: 9953.53 | L7: OD
A8: MBPSI2501007 | B8: JAN | C8: 45674 | D8: AUTO RAYA TIMUR SDN BHD | E8: KFD7766 | F8: MBPWO2412018 | G8: 12843.63 | H8: 4368 | I8: 17211.63 | K8: 17211.63 | L8: OD
A9: MBPSI2501008 | B9: JAN | C9: 45674 | D9: MOHD HUSAIDI BIN MUKHTAR | E9: KFD7766 | F9: MBPWO2501009 | G9: 95 | H9: 420 | I9: 515 | K9: 515 | L9: OD | M9: CASH
A10: MBPSI2501009 | B10: JAN | C10: 45674 | D10: AUTO RAYA TIMUR SDN BHD | E10: VJY9012 | F10: MBPWO2404003 | G10: 45 | H10: 70 | I10: 115 | K10: 115 | L10: CR | M10: CREDIT
A11: MBPSI2501010 | B11: JAN | C11: 45678 | D11: AUTO RAYA TIMUR SDN BHD | E11: DEF5937 | F11: MBPWO2412001 | G11: 2025.32 | H11: 3348 | I11: 5373.32 | K11: 5373.32 | L11: OD
A12: MBPSI2501011 | B12: JAN | C12: 45679 | D12: AUTO RAYA TIMUR SDN BHD | E12: VLA8387 | F12: MBPWO2412019 | G12: 8453.66 | H12: 2628 | I12: 11081.66 | K12: 11081.66 | L12: OD
A13: MBPSI2501012 | B13: JAN | C13: 45680 | D13: AUTO RAYA TIMUR SDN BHD | E13: VGJ2284 | F13: MBPWO2412020 | G13: 10979.84 | H13: 2688 | I13: 13667.84 | K13: 13667.84 | L13: OD
A14: MBPSI2501013 | B14: JAN | C14: 45681 | D14: AUTO RAYA TIMUR SDN BHD | E14: VLG7886 | F14: MBPWO2412008 | G14: 2943.04 | H14: 5004 | I14: 7947.04 | K14: 7947.04 | L14: OD
A15: MBPSI2501014 | B15: JAN | C15: 45684 | D15: AUTO RAYA TIMUR SDN BHD | E15: VGR6670 | F15: MBPWO2501003 | G15: 23799.55 | H15: 6060 | I15: 29859.55 | K15: 29859.55 | L15: OD
A16: MBPSI2502001 | B16: FEB | C16: 45692 | D16: AUTO RAYA TIMUR SDN BHD | E16: JUN1989 | F16: MBPWO2501001 | G16: 6345.16 | H16: 756 | I16: 7101.16 | K16: 7101.16 | L16: OD
A17: MBPSI2502002 | B17: FEB | C17: 45695 | D17: AUTO RAYA TIMUR SDN BHD | E17: VHG2900 | F17: MBPWO2501004 | G17: 6370.65 | H17: 1236 | I17: 7606.65 | K17: 7606.65 | L17: OD
A18: MBPSI2502003 | B18: FEB | C18: 45695 | D18: AUTO RAYA TIMUR SDN BHD | E18: VHN4241 | F18: MBPWO2502002 | G18: 1603.02 | H18: 276 | I18: 1879.02 | K18: 1879.02 | L18: WS
A19: MBPSI2502004 | B19: FEB | C19: 45698 | D19: AUTO RAYA TIMUR SDN BHD | E19: CEX4633 | F19: MBPWO2502003 | G19: 959.95 | H19: 276 | I19: 1235.95 | K19: 1235.95 | L19: WS
A20: MBPSI2502005 | B20: FEB | C20: 45699 | D20: AUTO RAYA TIMUR SDN BHD | E20: JUX1971 | F20: MBPWO2501008 | G20: 13649.55 | H20: 3252 | I20: 16901.55 | K20: 16901.55 | L20: OD
A21: MBPSI2502006 | B21: FEB | C21: 45705 | D21: AUTO RAYA TIMUR SDN BHD | E21: DEH905 | F21: MBPWO2502004 | G21: 1603.02 | H21: 276 | I21: 1879.02 | K21: 1879.02 | L21: WS
A22: MBPSI2502007 | B22: FEB | C22: 45707 | D22: ZAINALDIN BIN ISMAIL | E22: CEX4633 | F22: MBPWO2502007 | G22: 333.8 | H22: 1270 | I22: 1603.8 | K22: 1603.8 | L22: CR | M22: CASH
A23: MBPSI2502008 | B23: FEB | C23: 45709 | D23: AUTO RAYA TIMUR SDN BHD | E23: CEX2379 | F23: MBPWO2501010 | G23: 7213.2 | H23: 2076 | I23: 9289.2 | K23: 9289.2 | L23: OD
A24: MBPSI2502009 | B24: FEB | C24: 45709 | D24: AUTO RAYA TIMUR SDN BHD | E24: QS8485T | F24: MBPWO2501006 | G24: 6980.95 | H24: 4992 | I24: 11972.95 | K24: 11972.95 | L24: OD
A25: MBPSI2502010 | B25: FEB | C25: 45714 | D25: AUTO RAYA TIMUR SDN BHD | E25: VGT4060 | F25: MBPWO2412012 | G25: 24780.27 | H25: 8478 | I25: 33258.27 | K25: 33258.27 | L25: OD
A26: MBPSI2502011 | B26: FEB | C26: 45714 | D26: AUTO RAYA TIMUR SDN BHD | E26: JUS3376 | F26: MBPWO2501005 | G26: 15636.54 | H26: 3804 | I26: 19440.54 | K26: 19440.54 | L26: OD
A27: MBPSI2502012 | B27: FEB | C27: 45715 | D27: AUTO RAYA TIMUR SDN BHD | E27: RAV8458 | F27: MBPWO2501007 | G27: 7427.45 | H27: 2976 | I27: 10403.45 | K27: 10403.45 | L27: OD
A28: MBPSI2502013 | B28: FEB | C28: 45715 | D28: AUTO RAYA TIMUR SDN BHD | E28: CEP6761 | F28: MBPWO2502008 | G28: 3066.76 | H28: 240 | I28: 3306.76 | K28: 3306.76 | L28: WS
A29: MBPSI2503001 | B29: MAR | C29: 45726 | D29: AUTO RAYA TIMUR SDN BHD | E29: BQW6800 | F29: MBPWO2502005 | G29: 11264.75 | H29: 3180 | I29: 14444.75 | K29: 14444.75 | L29: OD
A30: MBPSI2503002 | B30: MAR | C30: 45726 | D30: AUTO RAYA TIMUR SDN BHD | E30: RAX1923 | F30: MBPWO2502001 | G30: 4971.68 | H30: 4848 | I30: 9819.68 | K30: 9819.68 | L30: OD
A31: MBPSI2503003 | B31: MAR | C31: 45726 | D31: AUTO RAYA TIMUR SDN BHD | E31: CEW7550 | F31: MBPWO2503002 | G31: 3066.76 | H31: 240 | I31: 3306.76 | K31: 3306.76 | L31: WS
A32: MBPSI2503004 | B32: MAR | C32: 45726 | D32: AUTO RAYA TIMUR SDN BHD | E32: JUR242 | F32: MBPWO2503007 | G32: 2591.76 | H32: 240 | I32: 2831.76 | K32: 2831.76 | L32: WS
A33: MBPSI2503005 | B33: MAR | C33: 45730 | D33: AUTO RAYA TIMUR SDN BHD | E33: VGQ157 | F33: MBPWO2503008 | G33: 178.02 | H33: 276 | I33: 454.02 | K33: 454.02 | L33: WS
A34: MBPSI2503006 | B34: MAR | C34: 45731 | D34: FADRE BIN HASHIM | E34: RAX1923 | F34: MBPWO2503010 | G34: 422.2 | H34: 820 | I34: 1242.2 | K34: 1242.2 | L34: CR | M34: CASH
A35: MBPSI2503007 | B35: MAR | C35: 45731 | D35: AUTO RAYA TIMUR SDN BHD | E35: JAP72 | F35: MBPWO2412010 | G35: 1183.64 | H35: 900 | I35: 2083.64 | K35: 2083.64 | L35: OD
A36: MBPSI2503008 | B36: MAR | C36: 45742 | D36: AUTO RAYA TIMUR SDN BHD | E36: VHP42 | F36: MBPWO2503009 | G36: 3066.76 | H36: 240 | I36: 3306.76 | K36: 3306.76 | L36: WS
A37: MBPSI2503009 | B37: MAR | C37: 45743 | D37: NOR FAZIDAH BINTI ABD MAJID | E37: VEQ8778 | F37: MBPWO2503015 | G37: 11787.22 | H37: 7041.6 | I37: 18828.82 | K37: 18828.82 | L37: OD
A38: MBPSI2503010 | B38: MAR | C38: 45736 | D38: AUTO RAYA TIMUR SDN BHD | E38: ANC8897 | F38: MBPWO2503001 | G38: 16999.55 | H38: 1536 | I38: 18535.55 | K38: 18535.55 | L38: OD
A39: MBPSI2503011 | B39: MAR | C39: 45736 | D39: AUTO RAYA TIMUR SDN BHD | E39: VGH9547 | F39: MBPWO2502011 | G39: 4653.64 | H39: 1836 | I39: 6489.64 | K39: 6489.64 | L39: OD
A40: MBPSI2503012 | B40: MAR | C40: 45741 | D40: AUTO RAYA TIMUR SDN BHD | E40: CBV41 | F40: MBPWO2503011 | G40: 2116.76 | H40: 240 | I40: 2356.76 | K40: 2356.76 | L40: WS
A41: MBPSI2503013 | B41: MAR | C41: 45742 | D41: AUTO RAYA TIMUR SDN BHD | E41: JUD7971 | F41: MBPWO2503013 | G41: 3066.76 | H41: 240 | I41: 3306.76 | K41: 3306.76 | L41: WS
A42: MBPSI2503014 | B42: MAR | C42: 45744 | D42: AUTO RAYA TIMUR SDN BHD | E42: JUM1970 | F42: MBPWO2503003 | G42: 9123.5 | H42: 2208 | I42: 11331.5 | K42: 11331.5 | L42: OD
A43: MBPSI2503015 | B43: MAR | C43: 45745 | D43: AUTO RAYA TIMUR SDN BHD | E43: VHQ8480 | F43: MBPWO2503014 | G43: 6356.04 | H43: 2292 | I43: 8648.04 | K43: 8648.04 | L43: OD
A44: MBPSI2503016 | B44: MAR | C44: 45745 | D44: AUTO RAYA TIMUR SDN BHD | E44: NDU7770 | F44: MBPWO2503006 | G44: 12450.85 | H44: 2904 | I44: 15354.85 | K44: 15354.85 | L44: OD
A45: MBPSI2504001 | B45: APR | C45: 45751 | D45: AUTO RAYA TIMUR SDN BHD | E45: CEM6013 | F45: MBPWO2502009 | G45: 14048.25 | H45: 3828 | I45: 17876.25 | K45: 17876.25 | L45: OD
A46: MBPSI2504002 | B46: APR | C46: 45763 | D46: AUTO RAYA TIMUR SDN BHD | E46: DEG9557 | F46: MBPWO2504004 | G46: 993.2 | H46: 276 | I46: 1269.2 | K46: 1269.2 | L46: WS
... A66: MBPSI2505012 | B66: MAY | C66: 45797 | D66: AUTO RAYA TIMUR SDN BHD | E66: VMU7214 | F66: MBPWO2505003 | G66: 3066.76 | H66: 240 | I66: 3306.76 | K66: 3306.76 | L66: WS
A67: MBPSI2506001 | B67: JUNE | C67: 45812 | D67: AUTO RAYA TIMUR SDN BHD | E67: P04074 | F67: MBPWO2506001 | G67: 600 | I67: 600 | K67: 600 | L67: CR
A68: MBPSI2506002 | B68: JUNE | C68: 45817 | D68: AUTO RAYA TIMUR SDN BHD | E68: AMH2540 | F68: MBPWO2504001 | G68: 37422.24 | H68: 6516 | I68: 43938.24 | K68: 43938.24 | L68: OD
A69: MBPSI2506003 | B69: JUNE | C69: 45820 | D69: AUTO RAYA TIMUR SDN BHD | E69: WB9689S | F69: MBPWO2506003 | G69: 2553.02 | H69: 276 | I69: 2829.02 | K69: 2829.02 | L69: WS
A70: MBPSI2506004 | B70: JUNE | C70: 45820 | D70: AUTO RAYA TIMUR SDN BHD | E70: CDY982 | F70: MBPWO2504002 | G70: 10254.41 | H70: 5316 | I70: 15570.41 | K70: 15570.41 | L70: OD
A71: MBPSI2506005 | B71: JUNE | C71: 45827 | D71: AUTO RAYA TIMUR SDN BHD | E71: BRW6049 | F71: MBPWO2505010 | G71: 2762.93 | H71: 780 | I71: 3542.93 | K71: 3542.93 | L71: OD
A72: MBPSI2506006 | B72: JUNE | C72: 45828 | D72: AUTO RAYA TIMUR SDN BHD | E72: VKW1324 | F72: MBPWO2412016 | G72: 42069.87 | H72: 10272 | I72: 52341.87 | K72: 52341.87 | L72: OD
A73: MBPSI2506007 | B73: JUNE | C73: 45828 | D73: AUTO RAYA TIMUR SDN BHD | E73: P04363 | F73: MBPWO2503004 | G73: 3886.53 | H73: 1494 | I73: 5380.53 | K73: 5380.53 | L73: OD
A74: MBPSI2506008 | B74: JUNE | C74: 45829 | D74: AUTO RAYA TIMUR SDN BHD | E74: CFB6546 | F74: MBPWO2506006 | G74: 2078.02 | H74: 276 | I74: 2354.02 | K74: 2354.02 | L74: WS
A75: MBPSI2506009 | B75: JUNE | C75: 45831 | D75: AUTO RAYA TIMUR SDN BHD | E75: JVE6728 | F75: MBPWO2505005 | G75: 5367.09 | H75: 2748 | I75: 8115.09 | K75: 8115.09 | L75: OD
A76: MBPSI2506010 | B76: JUNE | C76: 45831 | D76: AUTO RAYA TIMUR SDN BHD | E76: AMF586 | F76: MBPWO2506004 | G76: 2202.49 | H76: 3720 | I76: 5922.49 | K76: 5922.49 | L76: OD
A77: MBPSI2506011 | B77: JUNE | C77: 45832 | D77: AUTO RAYA TIMUR SDN BHD | E77: VJS9641 | F77: MBPWO2505007 | G77: 13028.17 | H77: 2676 | I77: 15704.17 | K77: 15704.17 | L77: OD
A78: MBPSI2506012 | B78: JUNE | C78: 45833 | D78: AUTO RAYA TIMUR SDN BHD | E78: VBK8895 | F78: MBPWO2505011 | G78: 2742.4 | H78: 252 | I78: 2994.4 | K78: 2994.4 | L78: WS
A79: MBPSI2506013 | B79: JUNE | C79: 45834 | D79: AUTO RAYA TIMUR SDN BHD | E79: P05122 | F79: MBPWO2506008 | G79: 710 | I79: 710 | K79: 710 | L79: CR
A80: MBPSI2506014 | B80: JUNE | C80: 45836 | D80: MOHD NIZAM BIN SHAMSUDDIN | E80: JQT1407 | F80: MBPWO2506010 | G80: 521 | H80: 180 | I80: 701 | K80: 701 | L80: CR
A81: MBPSI2506015 | B81: JUNE | C81: 45836 | D81: AUTO RAYA TIMUR SDN BHD | E81: VGE9145 | F81: MBPWO2506005 | G81: 12633.11 | H81: 1896 | I81: 14529.11 | K81: 14529.11 | L81: OD
A82: MBPSI2506016 | B82: JUNE | C82: 45838 | D82: AHMAD MARZUKI BIN YUSOF | E82: TCS8609 | F82: MBPWO2506007 | G82: 1000 | H82: 700 | I82: 1700 | K82: 1700 | L82: CR
A83: MBPSI2507001 | B83: JULY | C83: 45839 | D83: AUTO RAYA TIMUR SDN BHD | E83: TCS8609 | F83: MBPWO2505009 | G83: 13388.96 | H83: 2076 | I83: 15464.96 | K83: 15464.96 | L83: OD
A84: MBPSI2507002 | B84: JULY | C84: 45842 | D84: AUTO RAYA TIMUR SDN BHD | E84: RAX4082 | F84: MBPWO2505008 | G84: 3115.94 | H84: 2304 | I84: 5419.94 | K84: 5419.94 | L84: OD
A85: MBPSI2507003 | B85: JULY | C85: 45845 | D85: AUTO RAYA TIMUR SDN BHD | E85: JXP7858 | F85: MBPWO2506002 | G85: 5064.35 | H85: 2244 | I85: 7308.35 | K85: 7308.35 | L85: OD
A86: MBPSI2507004 | B86: JULY | C86: 45848 | D86: AUTO RAYA TIMUR SDN BHD | E86: CEM9297 | F86: MBPWO2505004 | G86: 23082 | H86: 8496 | I86: 31578 | K86: 31578 | L86: OD
A87: MBPSI2507005 | B87: JULY | C87: 45850 | D87: AUTO RAYA TIMUR SDN BHD | E87: VGB4719 | F87: MBPWO2507002 | G87: 1603.02 | H87: 276 | I87: 1879.02 | K87: 1879.02 | L87: WS
A88: MBPSI2507006 | B88: JULY | C88: 45852 | D88: AUTO RAYA TIMUR SDN BHD | E88: VLK4240 | F88: MBPWO2507005 | G88: 1603.02 | H88: 276 | I88: 1879.02 | K88: 1879.02 | L88: WS
A89: MBPSI2507007 | B89: JULY | C89: 45852 | D89: AUTO RAYA TIMUR SDN BHD | E89: CEU4672 | F89: MBPWO2507003 | G89: 2663.2 | H89: 240 | I89: 2903.2 | K89: 2903.2 | L89: WS
A90: MBPSI2507008 | B90: JULY | C90: 45854 | D90: AUTO RAYA TIMUR SDN BHD | E90: BRA3466 | F90: MBPWO2507007 | G90: 1033.02 | H90: 276 | I90: 1309.02 | K90: 1309.02 | L90: WS
A91: MBPSI2507009 | B91: JULY | C91: 45856 | D91: AUTO RAYA TIMUR SDN BHD | E91: CFA3293 | F91: MBPWO2506009 | G91: 4001.25 | H91: 2408.4 | I91: 6409.65 | K91: 6409.65 | L91: CR
... A111: MBPSI2508014 | B111: AUG | C111: 45891 | D111: AUTO RAYA TIMUR SDN BHD | E111: MDR7865 | F111: MBPWO2508003 | G111: 3064.7 | H111: 228 | I111: 3292.7 | K111: 3310.94 | L111: WS
A112: MBPSI2508015 | B112: AUG | C112: 45897 | D112: AUTO RAYA TIMUR SDN BHD | E112: P04907 | F112: MBPWO2508022 | G112: 196 | H112: 480 | I112: 676 | K112: 714.4 | L112: CR | M112: CREDIT
A113: MBPSI2509001 | B113: SEP | C113: 45904 | D113: AUTO RAYA TIMUR SDN BHD | E113: E5541 | F113: MBPWO2508023 | G113: 2831 | H113: 239.4 | I113: 3070.4 | K113: 3089.55 | L113: WS
A114: MBPSI2509002 | B114: SEP | C114: 45906 | D114: AUTO RAYA TIMUR SDN BHD | E114: UM4797 | F114: MBPWO2507004 | G114: 29654.63 | H114: 4172.4 | I114: 33827.03 | K114: 34160.82 | L114: OD
A115: MBPSI2509003 | B115: SEP | C115: 45906 | D115: AUTO RAYA TIMUR SDN BHD | E115: VJW625 | F115: MBPWO2505006 | G115: 31836.97 | H115: 13064.4 | I115: 44901.37 | K115: 45946.52 | L115: OD
A116: MBPSI2509004 | B116: SEP | C116: 45906 | D116: AUTO RAYA TIMUR SDN BHD | E116: DFE899 | F116: MBPWO2508024 | G116: 2128.76 | H116: 228 | I116: 2356.76 | K116: 2375 | L116: WS
A117: MBPSI2509005 | B117: SEP | C117: 45908 | D117: AUTO RAYA TIMUR SDN BHD | E117: QAB7524H | F117: MBPWO2508004 | G117: 27539.46 | H117: 2519.4 | I117: 30058.86 | K117: 30260.41 | L117: OD
A118: MBPSI2509006 | B118: SEP | C118: 45917 | D118: AUTO RAYA TIMUR SDN BHD | E118: NDY8615 | F118: MBPWO2509004 | G118: 208.05 | H118: 114 | I118: 322.05 | K118: 331.17 | L118: WS
A119: MBPSI2509007 | B119: SEP | C119: 45919 | D119: AUTO RAYA TIMUR SDN BHD | E119: BQT7878 | F119: MBPWO2509005 | G119: 2603.76 | H119: 228 | I119: 2831.76 | K119: 2850 | L119: WS
A120: MBPSI2509008 | B120: SEP | C120: 45920 | D120: AUTO RAYA TIMUR SDN BHD | E120: CEL2861 | F120: MBPWO2508018 | G120: 15601.28 | H120: 1949.4 | I120: 17550.68 | K120: 17706.63 | L120: OD
A121: MBPSI2509009 | B121: SEP | C121: 45929 | D121: AUTO RAYA TIMUR SDN BHD | E121: VHB9956 | F121: MBPWO2508005 | G121: 3777.69 | H121: 1014.6 | I121: 4792.29 | K121: 4873.46 | L121: OD
A122: MBPSI2509010 | B122: SEP | C122: 45930 | D122: AUTO RAYA TIMUR SDN BHD | E122: VFN5440 | F122: MBPWO2509003 | G122: 12980.9 | H122: 2462.4 | I122: 15443.3 | K122: 15640.29 | L122: OD
A123: MBPSI2510001 | B123: OCT | C123: 45933 | D123: AUTO RAYA TIMUR SDN BHD | E123: VEN7288 | F123: MBPWO2509002 | G123: 6028.85 | H123: 1926.6 | I123: 7955.45 | K123: 8109.58 | L123: OD
A124: MBPSI2510002 | B124: OCT | C124: 45936 | D124: AUTO RAYA TIMUR SDN BHD | E124: VPS8091 | F124: MBPWO2509009 | G124: 236.6 | H124: 200 | I124: 136.6 | J124: 300 | K124: 152.6 | L124: CR
A125: MBPSI2510003 | B125: OCT | C125: 45936 | D125: AUTO RAYA TIMUR SDN BHD | E125: VFN59 | F125: MBPWO2508020 | G125: 19314.07 | H125: 6862.8 | I125: 26176.87 | K125: 26725.89 | L125: OD
A126: MBPSI2510004 | B126: OCT | C126: 45937 | D126: SYAIFUL SYAZWAN ANIF BIN NASARUDIN | E126: SWN9307 | F126: MBPWO2510001 | G126: 93 | I126: 93 | K126: 93 | L126: CR
A127: MBPSI2510005 | B127: OCT | C127: 45940 | D127: AUTO RAYA TIMUR SDN BHD | E127: UM6206 | F127: MBPWO2509007 | G127: 4805.1 | H127: 2314.2 | I127: 7119.3 | K127: 7304.44 | L127: OD
A128: MBPSI2510006 | B128: OCT | C128: 45944 | D128: AUTO RAYA TIMUR SDN BHD | E128: VLH5520 | F128: MBPWO2510002 | G128: 1614.05 | H128: 262.2 | I128: 1876.25 | K128: 1897.23 | L128: WS
A129: MBPSI2510007 | B129: OCT | C129: 45945 | D129: AUTO RAYA TIMUR SDN BHD | E129: CER1406 | F129: MBPWO2510006 | G129: 1141.82 | H129: 262.2 | I129: 1404.02 | K129: 1425 | L129: WS
A130: MBPSI2510008 | B130: OCT | C130: 45946 | D130: AUTO RAYA TIMUR SDN BHD | E130: BQH1256 | F130: MBPWO2510007 | G130: 2591.45 | H130: 239.4 | I130: 2830.85 | K130: 2850 | L130: WS
A131: MBPSI2510009 | B131: OCT | C131: 45954 | D131: AUTO RAYA TIMUR SDN BHD | E131: VMU7214 | F131: MBPWO2506011 | G131: 63829.74 | H131: 10921.2 | I131: 74750.94 | K131: 75624.64 | L131: OD
A132: MBPSI2510010 | B132: OCT | C132: 45957 | D132: AUTO RAYA TIMUR SDN BHD | E132: VFV5818 | F132: MBPWO2509001 | G132: 13838.66 | H132: 4605.6 | I132: 18444.26 | K132: 18812.71 | L132: OD
A133: MBPSI2510011 | B133: OCT | C133: 45957 | D133: AUTO RAYA TIMUR SDN BHD | E133: VKR1273 | F133: MBPWO2510011 | G133: 1616.82 | H133: 262.2 | I133: 1879.02 | K133: 1900 | L133: WS
A134: MBPSI2510012 | B134: OCT | C134: 45958 | D134: AUTO RAYA TIMUR SDN BHD | E134: TCQ2294 | F134: MBPWO2510010 | G134: 1186.55 | H134: 216.6 | I134: 1403.15 | K134: 1420.48 | L134: WS
A135: MBPSI2510013 | B135: OCT | C135: 45960 | D135: AUTO RAYA TIMUR SDN BHD | E135: BQK7697 | F135: MBPWO2510005 | G135: 5017.33 | H135: 1447.8 | I135: 6465.13 | K135: 6580.95 | L135: OD
A136: MBPSI2511001 | B136: NOV | C136: 45964 | D136: AUTO RAYA TIMUR SDN BHD | E136: VMS7043 | F136: MBPWO2509006 | G136: 49763.57 | H136: 3591 | I136: 53354.57 | K136: 53641.85 | L136: OD
A137: MBPSI2511002 | B137: NOV | C137: 45965 | D137: AUTO RAYA TIMUR SDN BHD | E137: ANC5554 | F137: MBPWO2510012 | G137: 2532.7 | H137: 228 | I137: 2760.7 | K137: 2778.94 | L137: WS
A138: MBPSI2511003 | B138: NOV | C138: 45967 | D138: AUTO RAYA TIMUR SDN BHD | E138: VKM7660 | F138: MBPWO2510008 | G138: 10137.64 | H138: 1675.8 | I138: 11813.44 | K138: 11947.5 | L138: OD
...

Sheet MITS 2026
A1: TRANSNO | B1: MONTH | C1: DATE | D1: CUSTOMER NAME | E1: REG NO | F1: JOBNO | G1: P.TOTAL | H1: L.TOTAL | I1: GTOTAL | J1: DISC | K1: TOTAL | L1: SVC TYPE
A2: MBPSI2609001 | B2: Sept | C2: 46269 | D2: AUTO RAYA TIMUR SDN BHD | E2: RBB 6769 | F2: MBPWO2607010 | G2: 2070.05 | H2: 262.2 | I2: =+G2+H2 -> 2332.25 | J2: 0 | K2: =+I2-J2 -> 2332.25 | L2: WS
A3: MBPSI2609002 | B3: Sept | C3: 46282 | D3: AUTO RAYA TIMUR SDN BHD | E3: VPD 143 | F3: MBPWO2608004 | G3: 14843.18 | H3: 2394 | I3: =+G3+H3 -> 17237.18 | J3: 0 | K3: =+I3-J3 -> 17237.18 | L3: OD
A4: MBPSI2609003 | B4: Sept | C4: 46288 | D4: AUTO RAYA TIMUR SDN BHD | E4: RAQ 9097 | F4: MBPWO2609001 | G4: 2044.4 | H4: 889.2 | I4: =+G4+H4 -> 2933.6 | J4: 0 | K4: =+I4-J4 -> 2933.6 | L4: OD
A5: MBPSI2609004 | B5: Sept | C5: 46288 | D5: AUTO RAYA TIMUR SDN BHD | E5: CFD 3401 | F5: MBPWO2609002 | G5: 2137.58 | H5: 228 | I5: =+G5+H5 -> 2365.58 | J5: 0 | K5: =I5 -> 2365.58 | L5: CR
A6: MBPSI2609005 | B6: Sept | C6: 46290 | D6: AUTO RAYA TIMUR SDN BHD | E6: CBV 41 | F6: MBPWO2609004 | G6: 2128.76 | H6: 228 | I6: =+G6+H6 -> 2356.76 | J6: 0 | K6: =I6 -> 2356.76 | L6: WS
A7: MBPSI2609006 | B7: Sept | C7: 46291 | D7: AUTO RAYA TIMUR SDN BHD | E7: A03322 | F7: MBPWO2609003 | G7: 186 | H7: 540 | I7: =+G7+H7 -> 726 | J7: 0 | K7: =I7 -> 726 | L7: CR
A8: MBPSI2609007 | B8: Sept | C8: 46291 | D8: AUTO RAYA TIMUR SDN BHD | E8: H054041 | F8: MBPWO2609008 | G8: 336.3 | H8: 540 | I8: =+G8+H8 -> 876.3 | J8: 0 | K8: =I8 -> 876.3 | L8: CR
A9: MBPSI2609008 | B9: Sept | C9: 46294 | D9: SUHADAH BINTI MENHAD | E9: VQK 4472 | F9: MBPWO2609010 | G9: 110 | H9: 280 | I9: =+G9+H9 -> 390 | J9: 0 | K9: =I9 -> 390 | L9: CR
I10: =+G10+H10 -> 0 | J10: 0 | K10: =I10 -> 0
I11: =+G11+H11 -> 0 | K11: =I11 -> 0
I12: =+G12+H12 -> 0 | K12: =I12 -> 0
I13: =+G13+H13 -> 0 | K13: =I13 -> 0
I14: =+G14+H14 -> 0 | K14: =I14 -> 0
I15: =+G15+H15 -> 0 | K15: =I15 -> 0
I16: =+G16+H16 -> 0 | K16: =I16 -> 0
G18: =SUM(G2:G17) -> 23856.27 | H18: =SUM(H2:H17) -> 5361.4 | I18: =SUM(I2:I17) -> 29217.67 | J18: =SUM(J2:J17) -> 0 | K18: =SUM(K2:K17) -> 29217.67
A23: INVOICE LISTING
A24: TRANSNO | B24: MONTH | C24: DATE | D24: CUSTOMER NAME | E24: REFERENCE | F24: TOTAL | G24: DN | H24: G.TOTAL | I24: SVC TYPE
A25: MBPIV2609001 | B25: Sept | C25: 46295 | D25: AUTO RAYA TIMUR SDN BHD | E25: W401Y | F25: 337.44 | G25: 0 | H25: =+F25+G25 -> 337.44 | I25: WS
G26: 0 | H26: =+F26+G26 -> 0
H27: =SUM(H25:H26) -> 337.44

Sheet FUSO 2025
A1: TRANSNO | B1: MONTH | C1: DATE | D1: CUSTOMER NAME | E1: REG NO | F1: JOBNO | G1: P.TOTAL | H1: L.TOTAL | I1: GTOTAL | J1: RD | K1: TAX | L1: TOTAL
A2: FASSI2501001 | B2: JAN | C2: 45659 | D2: H&M TRANSPORT | E2: RAT9186 | F2: FASWO2501001 | I2: 0 | J2: 0 | K2: 0 | L2: 0
A3: FASSI2501002 | B3: JAN | C3: 45667 | D3: LHL MARKETING | E3: AMR3233 | F3: FASWO2501002 | G3: 340.26 | H3: 126 | I3: 466.3 | J3: 0.04 | K3: 0 | L3: 466.3 | M3: CASH
A4: FASSI2501003 | B4: JAN | C4: 45682 | D4: YPF SAWIT TRADING | E4: JWC1993 | F4: FASWO2501004 | I4: 0 | J4: 0 | K4: 0 | L4: 0
A5: FASSI2501004 | B5: JAN | C5: 45685 | D5: YPF SAWIT TRADING | E5: JWC1993 | F5: FASWO2501005 | G5: 83.2 | I5: 83.2 | J5: 0 | K5: 0 | L5: 83.2 | M5: CASH
A6: FASSI2502001 | B6: FEB | C6: 45702 | D6: KENASAN TRADINGS | E6: SK5448E | F6: FASWO2502001 | I6: 0 | J6: 0 | K6: 0 | L6: 0
A7: FASSI2502002 | B7: FEB | C7: 45709 | D7: ASMAWI CONSTRUCTION | E7: VLW3392 | F7: FASWO2502002 | I7: 0 | J7: 0 | K7: 0 | L7: 0
A8: FASSI2502003 | B8: FEB | C8: 45710 | D8: LHL MARKETING | E8: AMR3233 | F8: FASWO2502003 | I8: 0 | J8: 0 | K8: 0 | L8: 0
A9: FASSI2503001 | B9: MAR | C9: 45717 | D9: REDHA CONSTRUCTIONS | E9: BRM1186 | F9: FASWO2503001 | G9: 258.31 | H9: 222 | I9: 480.3 | J9: -0.01 | K9: 0 | L9: 480.3 | M9: CASH
A10: FASSI2503002 | B10: MAR | C10: 45721 | D10: FU SHENG TRADING | E10: UKM 2118 | F10: FASWO2503002 | G10: 415.02 | H10: 204 | I10: 619 | J10: -0.02 | K10: 0 | L10: 619 | M10: CASH
A11: FASSI2503003 | B11: MAR | C11: 45738 | D11: LHL MARKETING | E11: AMR3233 | F11: FASWO2503003 | G11: 236.81 | H11: 66 | I11: 302.8 | J11: -0.01 | K11: 0 | L11: 302.8 | M11: CASH
A12: FASSI2503004 | B12: MAR | C12: 45743 | D12: MOHD RODZUAN BIN BEDOLLAH | E12: MDR5421 | F12: FASWO2503004 | I12: 0 | J12: 0 | K12: 0 | L12: 0
A13: FASSI2503005 | B13: MAR | C13: 45743 | D13: MOHD RODZUAN BIN BEDOLLAH | E13: MDR5421 | F13: FASWO2503005 | I13: 0 | J13: 0 | K13: 0 | L13: 0
A14: FASSI2504001 | B14: APR | C14: 45769 | D14: LHL MARKETING | E14: AMR3233 | F14: FASWO2504001 | G14: 0 | H14: 0 | I14: 0 | J14: 0 | K14: 0 | L14: 0
A15: FASSI2504002 | B15: APR | C15: 45776 | D15: H&M TRANSPORT | E15: RAT9186 | F15: FASWO2504002 | G15: 0 | H15: 0 | I15: 0 | J15: 0 | K15: 0 | L15: 0
A16: FASSI2505001 | B16: MAY | C16: 45794 | D16: YPF SAWIT TRADING | E16: JWC1993 | F16: FASWO2505001 | I16: 0 | K16: 0
A17: FASSI2505002 | B17: MAY | C17: 45797 | D17: LHL MARKETING | E17: AMR3233 | F17: FASWO2505002 | G17: 225.81 | H17: 66 | I17: 291.8 | J17: -0.01 | K17: 0 | L17: 291.8 | M17: CASH
A18: FASSI2506001 | B18: JUNE | C18: 45818 | D18: KENASAN TRADINGS | E18: SK5448E | F18: FASWO2506001 | I18: 0 | J18: 0 | K18: 0 | L18: 0 | M18: CASH
A19: FASSI2506002 | B19: JUNE | C19: 45822 | D19: REDHA CONSTRUCTIONS | E19: BRM1186 | F19: FASWO2506002 | G19: 416.55 | H19: 186 | I19: 602.55 | J19: 0 | K19: 0 | L19: 602.55 | M19: CASH
A20: FASSI2506003 | B20: JUNE | C20: 45828 | D20: ASMAWI CONSTRUCTION | E20: VLW3392 | F20: FASWO2506003 | G20: 563.08 | H20: 204 | I20: 767.08 | J20: 0 | K20: 0 | L20: 767.08 | M20: CASH
A21: FASSI2507001 | B21: JULY | C21: 45847 | D21: TRUCK LINK AUTO SDN BHD | E21: VFY5570 | F21: FASWO2501003 | G21: 329.01 | H21: 900 | I21: 1229.01 | J21: 0 | K21: 0 | L21: 1229.01 | M21: CASH
A22: FASSI2507002 | B22: JULY | C22: 45849 | D22: GOH PENG LENG | E22: PPL7533 | F22: FASWO2507001 | G22: 315.81 | H22: 468 | I22: 783.8 | J22: -0.01 | K22: 0 | L22: 783.8 | M22: CASH
A23: FASSI2507003 | B23: JULY | C23: 45861 | D23: LHL MARKETING | E23: AMR3233 | F23: FASWO2507002 | G23: 353.16 | H23: 102 | I23: 455.15 | J23: -0.01 | K23: 0 | L23: 455.15 | M23: CASH
A24: FASSI2508001 | B24: AUG | C24: 45896 | D24: YPF SAWIT TRADING | E24: JWC1993 | F24: FASWO2508001 | G24: 552.27 | H24: 222 | I24: 774.27 | J24: 0 | K24: 17.76 | L24: 792.03 | M24: CASH
A25: FASSI2509001 | B25: SEP | C25: 45920 | D25: LHL MARKETING | E25: AMR3233 | F25: FASWO2509001 | G25: 230.81 | H25: 66 | I25: 296.82 | J25: 5.28 | K25: 0.01 | L25: 302.1 | M25: CASH
A26: FASSI2510001 | B26: OCT | C26: 45931 | D26: EDARAN RIZ SDN BHD | E26: CCC7671 | F26: FASWO2509003 | H26: 70 | I26: 70 | J26: 0 | K26: 5.6 | L26: 75.6 | M26: CASH
A27: FASSI2510002 | B27: OCT | C27: 45931 | D27: LHL MARKETING | E27: AMR3233 | F27: FASWO2509002 | I27: 0 | J27: 0 | K27: 0 | L27: 0 | M27: CASH
A28: FASSI2510003 | B28: OCT | C28: 45944 | D28: ASMAWI CONSTRUCTION | E28: VLW3392 | F28: FASWO2510002 | G28: 376.77 | H28: 120 | I28: 496.77 | J28: 0 | K28: 9.6 | L28: 506.37 | M28: CASH
A29: FASSI2511001 | B29: NOV | C29: 45976 | D29: KENASAN TRADINGS | E29: SK5448E | F29: FASWO2511001 | I29: 0 | J29: 0 | K29: 0 | L29: 0
A30: FASSI2511002 | B30: NOV | C30: 45980 | D30: REDHA CONSTRUCTIONS | E30: BRM1186 | F30: FASWO2511002 | G30: 240.77 | H30: 90 | I30: 330.77 | J30: 0 | K30: 7.2 | L30: 337.97 | M30: CASH
A31: FASSI2511003 | B31: NOV | C31: 45981 | D31: LHL MARKETING | E31: AMR3233 | F31: FASWO2511003 | G31: 230.81 | H31: 66 | I31: 296.81 | J31: 0 | K31: 5.28 | L31: 302.09 | M31: CASH
I35: =SUM(I2:I31) -> 8346.43

Sheet FUSO 2026
A1: TRANSNO | B1: MONTH | C1: DATE | D1: CUSTOMER NAME | E1: REG NO | F1: JOBNO | G1: P.TOTAL | H1: L.TOTAL | I1: GTOTAL | J1: RD | K1: TAX | L1: TOTAL | M1: SVC TYPE
I23: =SUM(I2:I21) -> 0

Sheet FUSO WC 2025
A1: Warranty
A2: DATE | B2: MONTH | C2: CLAIM NO | D2: CLAIM TO | E2: INVOICE NO | F2: REGNO | G2: PART | H2: LABOUR | I2: TOTAL | J2: AMOUNT
A3: 45713 | B3: FEB | C3: FASWC2502001 | D3: HAP SENG TRUCK DISTRIBUTION SDN BHD | E3: FASSI2502003 | F3: AMR3233 | G3: 1508.76 | H3: 36 | I3: 1544.76 | J3: 1544.76
A4: 45745 | B4: MAR | C4: FASWC2503001 | D4: HAP SENG TRUCK DISTRIBUTION SDN BHD | E4: FASSI2503005 | F4: MDR5421 | G4: 327.36 | H4: 42 | I4: 369.36 | J4: 369.36
A5: 45769 | B5: APR | C5: FASWC2504001 | D5: HAP SENG TRUCK DISTRIBUTION SDN BHD | E5: FASSI2504001 | F5: AMR3233 | G5: 2126 | H5: 276 | I5: 2402 | J5: 2402
A6: 45804 | B6: MAY | C6: FASFS2505001 | D6: HAP SENG TRUCK DISTRIBUTION SDN BHD | E6: FASSI2505001 | F6: JWC1993 | G6: 333.01 | H6: 120 | I6: 453.01 | J6: 453.01
J17: =SUM(J3:J10) -> 4769.13
A20: Free Service
A21: 45664 | B21: JAN | C21: FASFS2501001 | D21: HAP SENG TRUCK DISTRIBUTION SDN BHD | E21: FASSI2501001 | F21: RAT9186 | G21: 501.18 | H21: 222 | I21: 723.18 | J21: 723.18
A22: 45682 | B22: JAN | C22: FASFS2501002 | D22: HAP SENG TRUCK DISTRIBUTION SDN BHD | G22: 501.18 | H22: 222 | I22: 723.18 | J22: 723.18
A23: 45705 | B23: FEB | C23: FASFS2502001 | D23: HAP SENG TRUCK DISTRIBUTION SDN BHD | E23: FASSI2502001 | F23: SK5448E | G23: 240.21 | H23: 108 | I23: 348.21 | J23: 348.21
A24: 45713 | B24: FEB | C24: FASFS2502002 | D24: HAP SENG TRUCK DISTRIBUTION SDN BHD | E24: FASSI2502002 | F24: VLW3392 | G24: 240.21 | H24: 108 | I24: 348.21 | J24: 348.21
A25: 45745 | B25: MAR | C25: FASFS2503001 | D25: HAP SENG TRUCK DISTRIBUTION SDN BHD | E25: FASSI2503004 | F25: MDR5421 | G25: 333.01 | H25: 120 | I25: 453.01 | J25: 453.01
A26: 45776 | B26: APR | C26: FASFS2504001 | D26: HAP SENG TRUCK DISTRIBUTION SDN BHD | E26: FASSI2504002 | F26: RAT9186 | G26: 333.01 | H26: 120 | I26: 453.01 | J26: 453.01
A27: 45838 | B27: JUNE | C27: FASFS2506001 | D27: HAP SENG TRUCK DISTRIBUTION SDN BHD | E27: FASSI2506001 | F27: SK5448E | G27: 526.18 | H27: 222 | I27: 748.18 | J27: 748.18
A28: 45976 | B28: NOV | C28: FASFS2511001 | D28: HAP SENG TRUCK DISTRIBUTION SDN BHD | E28: FASSI2511001 | F28: SK5448E | G28: 334.61 | H28: 120 | I28: 454.61 | J28: 454.61
J37: =SUM(J21:J31) -> 4251.59

Sheet FUSO WC 2026
A1: Warranty
A2: DATE | B2: MONTH | C2: CLAIM NO | D2: CLAIM TO | E2: INVOICE NO | F2: REGNO | G2: PART | H2: LABOUR | I2: TOTAL | J2: AMOUNT
J16: =SUM(J3:J15) -> 0
A21: Free Service
A22: DATE | B22: MONTH | C22: CLAIM NO | D22: CLAIM TO | E22: INVOICE NO | F22: REGNO | G22: PART | H22: LABOUR | I22: TOTAL | J22: AMOUNT
J32: =SUM(J23:J30) -> 0
